{"metadata": {"dataVersion": "2", "matchId": "NA1_5314118179", "participants": ["vDZU4-lwtCUH_gRdFxdXowSN9i9bX0eC66ST9r8crvQpKyFlSJyo4h4z_KIEWg7v3yLw6egguCySPg", "ZDeF5_l5PcdFrBAGZJc3FXH_rMVej7iZ_snsQl6yIZPuBZOPy2JTELg9fTtspAHE7tJzS5wy7460rQ", "sypV6ignya2ap349xSVxeT6q6A0nKEKwNvLQ7sm9K-0YGtFP-98MkzTjGxmQ9tBLwtCJazNBJxDZeg", "FI50B7HRBu_Q4DM4J-zdMFD0Wp0oW12KFlwyvTyXinOf_TfeQr0poPPUAXddHkcp-5j36AUA2W9JdQ", "WWTC7-2jIgGdZWqMyA8_ral_hfYG1o7Qleg1eIq7vx21uYuBR4BZgQIOHQn_EkTjWOv895ltqlxfZQ", "mgro-XgaZs2VV7IEx6Fia0iHo0OiwyiKgENAC2XVlMz9x9RZqqspxORDU1VQJQKLAkpAMVBWvF7__w", "luVFxwDTJizvvnw-GXXpjMUBlp9CxoA9s144AOkyTL8wrHGCBdl8pZ48IRJW3vW1GeIuhufaG7QtmA", "DcfR8ofB2DhC8hVsNS9pGhYc6su48tCFKJKnc3qcwWp_1blbAhY5xNJxK8zSeRy41c-e6XicWbWo_Q", "ofN36YCj4-docqwVmn3DZ7LTIoh0yEpavZlULCidUK_EVu4SnSd2BcGwL7CzPEU-z2pfVQfnvBqPkg", "kUq1GpPXoC7lHnLvvgPdt3O0aiB6Z2UI-DKMaNmVyDHD3GvA43qKgf-toDHJYZCH3-tIoGYuFSSBcg"]}, "info": {"endOfGameResult": "GameComplete", "gameCreation": 1750896682708, "gameDuration": 1259, "gameEndTimestamp": 1750898023433, "gameId": 5314118179, "gameMode": "CLASSIC", "gameName": "teambuilder-match-5314118179", "gameStartTimestamp": 1750896764596, "gameType": "MATCHED_GAME", "gameVersion": "15.13.692.4165", "mapId": 11, "participants": [{"PlayerScore0": 0, "PlayerScore1": 0, "PlayerScore10": 0, "PlayerScore11": 0, "PlayerScore2": 0, "PlayerScore3": 0, "PlayerScore4": 0, "PlayerScore5": 0, "PlayerScore6": 0, "PlayerScore7": 0, "PlayerScore8": 0, "PlayerScore9": 0, "allInPings": 0, "assistMePings": 0, "assists": 0, "baronKills": 0, "basicPings": 0, "challenges": {"12AssistStreakCount": 0, "HealFromMapSources": 0, "InfernalScalePickup": 0, "SWARM_DefeatAatrox": 0, "SWARM_DefeatBriar": 0, "SWARM_DefeatMiniBosses": 0, "SWARM_EvolveWeapon": 0, "SWARM_Have3Passives": 0, "SWARM_KillEnemy": 0, "SWARM_PickupGold": 0, "SWARM_ReachLevel50": 0, "SWARM_Survive15Min": 0, "SWARM_WinWith5EvolvedWeapons": 0, "abilityUses": 144, "acesBefore15Minutes": 0, "alliedJungleMonsterKills": 0, "baronTakedowns": 0, "blastConeOppositeOpponentCount": 0, "bountyGold": 0, "buffsStolen": 0, "completeSupportQuestInTime": 0, "controlWardsPlaced": 0, "damagePerMinute": 508.5886211127553, "damageTakenOnTeamPercentage": 0.22625153164757925, "dancedWithRiftHerald": 0, "deathsByEnemyChamps": 5, "dodgeSkillShotsSmallWindow": 0, "doubleAces": 0, "dragonTakedowns": 0, "earlyLaningPhaseGoldExpAdvantage": 1, "effectiveHealAndShielding": 0, "elderDragonKillsWithOpposingSoul": 0, "elderDragonMultikills": 0, "enemyChampionImmobilizations": 12, "enemyJungleMonsterKills": 0, "epicMonsterKillsNearEnemyJungler": 0, "epicMonsterKillsWithin30SecondsOfSpawn": 0, "epicMonsterSteals": 0, "epicMonsterStolenWithoutSmite": 0, "firstTurretKilled": 1, "firstTurretKilledTime": 867.0563373860001, "fistBumpParticipation": 0, "flawlessAces": 0, "fullTeamTakedown": 0, "gameLength": 1259.316040521, "getTakedownsInAllLanesEarlyJungleAsLaner": 0, "goldPerMinute": 348.412224888442, "hadOpenNexus": 0, "immobilizeAndKillWithAlly": 1, "initialBuffCount": 0, "initialCrabCount": 0, "jungleCsBefore10Minutes": 0, "junglerTakedownsNearDamagedEpicMonster": 0, "kTurretsDestroyedBeforePlatesFall": 0, "kda": 0.6, "killAfterHiddenWithAlly": 0, "killParticipation": 0.08333333333333333, "killedChampTookFullTeamDamageSurvived": 0, "killingSprees": 0, "killsNearEnemyTurret": 2, "killsOnOtherLanesEarlyJungleAsLaner": 0, "killsOnRecentlyHealedByAramPack": 0, "killsUnderOwnTurret": 0, "killsWithHelpFromEpicMonster": 0, "knockEnemyIntoTeamAndKill": 0, "landSkillShotsEarlyGame": 0, "laneMinionsFirst10Minutes": 67, "laningPhaseGoldExpAdvantage": 0, "legendaryCount": 0, "legendaryItemUsed": [3071], "lostAnInhibitor": 0, "maxCsAdvantageOnLaneOpponent": 23, "maxKillDeficit": 2, "maxLevelLeadLaneOpponent": 2, "mejaisFullStackInTime": 0, "moreEnemyJungleThanOpponent": 0, "multiKillOneSpell": 0, "multiTurretRiftHeraldCount": 0, "multikills": 0, "multikillsAfterAggressiveFlash": 0, "outerTurretExecutesBefore10Minutes": 0, "outnumberedKills": 0, "outnumberedNexusKill": 0, "perfectDragonSoulsTaken": 0, "perfectGame": 0, "pickKillWithAlly": 0, "playedChampSelectPosition": 1, "poroExplosions": 0, "quickCleanse": 0, "quickFirstTurret": 0, "quickSoloKills": 0, "riftHeraldTakedowns": 0, "saveAllyFromDeath": 0, "scuttleCrabKills": 0, "skillshotsDodged": 40, "skillshotsHit": 0, "snowballsHit": 0, "soloBaronKills": 0, "soloKills": 2, "soloTurretsLategame": 1, "stealthWardsPlaced": 4, "survivedSingleDigitHpCount": 0, "survivedThreeImmobilizesInFight": 0, "takedownOnFirstTurret": 0, "takedowns": 3, "takedownsAfterGainingLevelAdvantage": 0, "takedownsBeforeJungleMinionSpawn": 0, "takedownsFirstXMinutes": 2, "takedownsInAlcove": 0, "takedownsInEnemyFountain": 0, "teamBaronKills": 0, "teamDamagePercentage": 0.14129246842033572, "teamElderDragonKills": 0, "teamRiftHeraldKills": 1, "teleportTakedowns": 1, "tookLargeDamageSurvived": 0, "turretPlatesTaken": 2, "turretTakedowns": 1, "turretsTakenWithRiftHerald": 5, "twentyMinionsIn3SecondsCount": 0, "twoWardsOneSweeperCount": 0, "unseenRecalls": 0, "visionScoreAdvantageLaneOpponent": -0.2053270936012268, "visionScorePerMinute": 0.3141782120508331, "voidMonsterKill": 0, "wardTakedowns": 0, "wardTakedownsBefore20M": 0, "wardsGuarded": 0}, "champExperience": 11195, "champLevel": 13, "championId": 58, "championName": "Renekton", "championTransform": 0, "commandPings": 0, "consumablesPurchased": 1, "damageDealtToBuildings": 3512, "damageDealtToObjectives": 3512, "damageDealtToTurrets": 3512, "damageSelfMitigated": 19955, "dangerPings": 0, "deaths": 5, "detectorWardsPlaced": 0, "doubleKills": 0, "dragonKills": 0, "eligibleForProgression": true, "enemyMissingPings": 0, "enemyVisionPings": 0, "firstBloodAssist": false, "firstBloodKill": false, "firstTowerAssist": false, "firstTowerKill": false, "gameEndedInEarlySurrender": false, "gameEndedInSurrender": true, "getBackPings": 0, "goldEarned": 7312, "goldSpent": 6275, "holdPings": 0, "individualPosition": "TOP", "inhibitorKills": 0, "inhibitorTakedowns": 0, "inhibitorsLost": 0, "item0": 3047, "item1": 3071, "item2": 1054, "item3": 1037, "item4": 1036, "item5": 1036, "item6": 3340, "itemsPurchased": 11, "killingSprees": 1, "kills": 3, "lane": "TOP", "largestCriticalStrike": 0, "largestKillingSpree": 2, "largestMultiKill": 1, "longestTimeSpentLiving": 382, "magicDamageDealt": 4767, "magicDamageDealtToChampions": 2071, "magicDamageTaken": 2310, "missions": {"playerScore0": 0, "playerScore1": 0, "playerScore2": 0, "playerScore3": 0, "playerScore4": 0, "playerScore5": 0, "playerScore6": 0, "playerScore7": 0, "playerScore8": 0, "playerScore9": 0, "playerScore10": 0, "playerScore11": 0}, "needVisionPings": 0, "neutralMinionsKilled": 0, "nexusKills": 0, "nexusLost": 0, "nexusTakedowns": 0, "objectivesStolen": 0, "objectivesStolenAssists": 0, "onMyWayPings": 0, "participantId": 1, "pentaKills": 0, "perks": {"statPerks": {"defense": 5001, "flex": 5008, "offense": 5008}, "styles": [{"description": "primaryStyle", "selections": [{"perk": 8010, "var1": 215, "var2": 0, "var3": 0}, {"perk": 9111, "var1": 279, "var2": 60, "var3": 0}, {"perk": 9104, "var1": 0, "var2": 0, "var3": 0}, {"perk": 8299, "var1": 538, "var2": 0, "var3": 0}], "style": 8000}, {"description": "subStyle", "selections": [{"perk": 8473, "var1": 617, "var2": 0, "var3": 0}, {"perk": 8242, "var1": 96, "var2": 0, "var3": 0}], "style": 8400}]}, "physicalDamageDealt": 82635, "physicalDamageDealtToChampions": 8603, "physicalDamageTaken": 17491, "placement": 0, "playerAugment1": 0, "playerAugment2": 0, "playerAugment3": 0, "playerAugment4": 0, "playerAugment5": 0, "playerAugment6": 0, "playerSubteamId": 0, "profileIcon": 6521, "pushPings": 0, "puuid": "vDZU4-lwtCUH_gRdFxdXowSN9i9bX0eC66ST9r8crvQpKyFlSJyo4h4z_KIEWg7v3yLw6egguCySPg", "quadraKills": 0, "retreatPings": 0, "riotIdGameName": "15th Accaunt", "riotIdTagline": "NA111", "role": "SOLO", "sightWardsBoughtInGame": 0, "spell1Casts": 53, "spell2Casts": 27, "spell3Casts": 57, "spell4Casts": 7, "subteamPlacement": 0, "summoner1Casts": 3, "summoner1Id": 12, "summoner2Casts": 2, "summoner2Id": 4, "summonerId": "YiP-QxXKg2yy43cUK19QnC3wgKAJa7hbrlDPnus2MNTbShlDDCftCseyfg", "summonerLevel": 101, "summonerName": "", "teamEarlySurrendered": false, "teamId": 100, "teamPosition": "TOP", "timeCCingOthers": 11, "timePlayed": 1259, "totalAllyJungleMinionsKilled": 0, "totalDamageDealt": 94452, "totalDamageDealtToChampions": 10674, "totalDamageShieldedOnTeammates": 0, "totalDamageTaken": 20863, "totalEnemyJungleMinionsKilled": 0, "totalHeal": 3934, "totalHealsOnTeammates": 0, "totalMinionsKilled": 136, "totalTimeCCDealt": 36, "totalTimeSpentDead": 151, "totalUnitsHealed": 1, "tripleKills": 0, "trueDamageDealt": 7050, "trueDamageDealtToChampions": 0, "trueDamageTaken": 1061, "turretKills": 1, "turretTakedowns": 1, "turretsLost": 2, "unrealKills": 0, "visionClearedPings": 0, "visionScore": 6, "visionWardsBoughtInGame": 0, "wardsKilled": 0, "wardsPlaced": 4, "win": true}, {"PlayerScore0": 0, "PlayerScore1": 0, "PlayerScore10": 0, "PlayerScore11": 0, "PlayerScore2": 0, "PlayerScore3": 0, "PlayerScore4": 0, "PlayerScore5": 0, "PlayerScore6": 0, "PlayerScore7": 0, "PlayerScore8": 0, "PlayerScore9": 0, "allInPings": 0, "assistMePings": 1, "assists": 8, "baronKills": 0, "basicPings": 0, "challenges": {"12AssistStreakCount": 0, "HealFromMapSources": 0, "InfernalScalePickup": 0, "SWARM_DefeatAatrox": 0, "SWARM_DefeatBriar": 0, "SWARM_DefeatMiniBosses": 0, "SWARM_EvolveWeapon": 0, "SWARM_Have3Passives": 0, "SWARM_KillEnemy": 0, "SWARM_PickupGold": 0, "SWARM_ReachLevel50": 0, "SWARM_Survive15Min": 0, "SWARM_WinWith5EvolvedWeapons": 0, "abilityUses": 126, "acesBefore15Minutes": 0, "alliedJungleMonsterKills": 48, "baronTakedowns": 0, "blastConeOppositeOpponentCount": 0, "bountyGold": 0, "buffsStolen": 1, "completeSupportQuestInTime": 0, "controlWardsPlaced": 0, "damagePerMinute": 354.5966180178489, "damageTakenOnTeamPercentage": 0.2727716801345114, "dancedWithRiftHerald": 0, "deathsByEnemyChamps": 5, "dodgeSkillShotsSmallWindow": 0, "doubleAces": 0, "dragonTakedowns": 1, "earliestDragonTakedown": 1165.7995438300002, "earlyLaningPhaseGoldExpAdvantage": 0, "effectiveHealAndShielding": 0, "elderDragonKillsWithOpposingSoul": 0, "elderDragonMultikills": 0, "enemyChampionImmobilizations": 11, "enemyJungleMonsterKills": 5, "epicMonsterKillsNearEnemyJungler": 1, "epicMonsterKillsWithin30SecondsOfSpawn": 1, "epicMonsterSteals": 0, "epicMonsterStolenWithoutSmite": 0, "firstTurretKilled": 1, "firstTurretKilledTime": 867.0563373860001, "fistBumpParticipation": 0, "flawlessAces": 0, "fullTeamTakedown": 0, "gameLength": 1259.316040521, "goldPerMinute": 358.75144962913004, "hadOpenNexus": 0, "immobilizeAndKillWithAlly": 4, "initialBuffCount": 2, "initialCrabCount": 2, "jungleCsBefore10Minutes": 56.00000002980232, "junglerKillsEarlyJungle": 0, "junglerTakedownsNearDamagedEpicMonster": 1, "kTurretsDestroyedBeforePlatesFall": 0, "kda": 2, "killAfterHiddenWithAlly": 2, "killParticipation": 0.2777777777777778, "killedChampTookFullTeamDamageSurvived": 0, "killingSprees": 0, "killsNearEnemyTurret": 1, "killsOnLanersEarlyJungleAsJungler": 0, "killsOnRecentlyHealedByAramPack": 0, "killsUnderOwnTurret": 0, "killsWithHelpFromEpicMonster": 1, "knockEnemyIntoTeamAndKill": 1, "landSkillShotsEarlyGame": 0, "laneMinionsFirst10Minutes": 0, "laningPhaseGoldExpAdvantage": 0, "legendaryCount": 0, "legendaryItemUsed": [3124], "lostAnInhibitor": 0, "maxCsAdvantageOnLaneOpponent": 25.399999976158142, "maxKillDeficit": 2, "maxLevelLeadLaneOpponent": 1, "mejaisFullStackInTime": 0, "moreEnemyJungleThanOpponent": -46.500000059604645, "multiKillOneSpell": 0, "multiTurretRiftHeraldCount": 0, "multikills": 0, "multikillsAfterAggressiveFlash": 0, "outerTurretExecutesBefore10Minutes": 0, "outnumberedKills": 0, "outnumberedNexusKill": 0, "perfectDragonSoulsTaken": 0, "perfectGame": 0, "pickKillWithAlly": 7, "playedChampSelectPosition": 1, "poroExplosions": 0, "quickCleanse": 0, "quickFirstTurret": 0, "quickSoloKills": 0, "riftHeraldTakedowns": 1, "saveAllyFromDeath": 0, "scuttleCrabKills": 3, "skillshotsDodged": 4, "skillshotsHit": 0, "snowballsHit": 0, "soloBaronKills": 0, "soloKills": 1, "stealthWardsPlaced": 3, "survivedSingleDigitHpCount": 0, "survivedThreeImmobilizesInFight": 0, "takedownOnFirstTurret": 0, "takedowns": 10, "takedownsAfterGainingLevelAdvantage": 0, "takedownsBeforeJungleMinionSpawn": 0, "takedownsFirstXMinutes": 5, "takedownsInAlcove": 0, "takedownsInEnemyFountain": 0, "teamBaronKills": 0, "teamDamagePercentage": 0.09851150689062914, "teamElderDragonKills": 0, "teamRiftHeraldKills": 1, "tookLargeDamageSurvived": 0, "turretPlatesTaken": 0, "turretTakedowns": 1, "turretsTakenWithRiftHerald": 5, "twentyMinionsIn3SecondsCount": 0, "twoWardsOneSweeperCount": 0, "unseenRecalls": 0, "visionScoreAdvantageLaneOpponent": -0.0436326265335083, "visionScorePerMinute": 0.31726025310170736, "voidMonsterKill": 1, "wardTakedowns": 0, "wardTakedownsBefore20M": 0, "wardsGuarded": 0}, "champExperience": 9686, "champLevel": 12, "championId": 5, "championName": "XinZhao", "championTransform": 0, "commandPings": 8, "consumablesPurchased": 1, "damageDealtToBuildings": 530, "damageDealtToObjectives": 14234, "damageDealtToTurrets": 530, "damageSelfMitigated": 12390, "dangerPings": 0, "deaths": 5, "detectorWardsPlaced": 0, "doubleKills": 0, "dragonKills": 1, "eligibleForProgression": true, "enemyMissingPings": 0, "enemyVisionPings": 0, "firstBloodAssist": false, "firstBloodKill": false, "firstTowerAssist": false, "firstTowerKill": false, "gameEndedInEarlySurrender": false, "gameEndedInSurrender": true, "getBackPings": 0, "goldEarned": 7529, "goldSpent": 6000, "holdPings": 0, "individualPosition": "JUNGLE", "inhibitorKills": 0, "inhibitorTakedowns": 0, "inhibitorsLost": 0, "item0": 3124, "item1": 3123, "item2": 1018, "item3": 3006, "item4": 0, "item5": 0, "item6": 3340, "itemsPurchased": 11, "killingSprees": 0, "kills": 2, "lane": "JUNGLE", "largestCriticalStrike": 294, "largestKillingSpree": 0, "largestMultiKill": 1, "longestTimeSpentLiving": 376, "magicDamageDealt": 7704, "magicDamageDealtToChampions": 631, "magicDamageTaken": 7254, "missions": {"playerScore0": 0, "playerScore1": 0, "playerScore2": 0, "playerScore3": 0, "playerScore4": 0, "playerScore5": 0, "playerScore6": 0, "playerScore7": 0, "playerScore8": 0, "playerScore9": 0, "playerScore10": 0, "playerScore11": 0}, "needVisionPings": 0, "neutralMinionsKilled": 116, "nexusKills": 0, "nexusLost": 0, "nexusTakedowns": 0, "objectivesStolen": 0, "objectivesStolenAssists": 0, "onMyWayPings": 2, "participantId": 2, "pentaKills": 0, "perks": {"statPerks": {"defense": 5013, "flex": 5010, "offense": 5005}, "styles": [{"description": "primaryStyle", "selections": [{"perk": 9923, "var1": 33, "var2": 100, "var3": 0}, {"perk": 8143, "var1": 452, "var2": 0, "var3": 0}, {"perk": 8140, "var1": 10, "var2": 0, "var3": 0}, {"perk": 8105, "var1": 40, "var2": 5, "var3": 0}], "style": 8100}, {"description": "subStyle", "selections": [{"perk": 9111, "var1": 484, "var2": 200, "var3": 0}, {"perk": 9103, "var1": 19, "var2": 20, "var3": 0}], "style": 8000}]}, "physicalDamageDealt": 79493, "physicalDamageDealtToChampions": 6174, "physicalDamageTaken": 17605, "placement": 0, "playerAugment1": 0, "playerAugment2": 0, "playerAugment3": 0, "playerAugment4": 0, "playerAugment5": 0, "playerAugment6": 0, "playerSubteamId": 0, "profileIcon": 948, "pushPings": 0, "puuid": "ZDeF5_l5PcdFrBAGZJc3FXH_rMVej7iZ_snsQl6yIZPuBZOPy2JTELg9fTtspAHE7tJzS5wy7460rQ", "quadraKills": 0, "retreatPings": 4, "riotIdGameName": "Expendus", "riotIdTagline": "JIT", "role": "NONE", "sightWardsBoughtInGame": 0, "spell1Casts": 48, "spell2Casts": 73, "spell3Casts": 0, "spell4Casts": 5, "subteamPlacement": 0, "summoner1Casts": 9, "summoner1Id": 11, "summoner2Casts": 2, "summoner2Id": 4, "summonerId": "5C4P9T_VGNYg8ooXV77YRlOBYFSwLlZLd6L2cBq58ecNBZ5zQER0e8UJTQ", "summonerLevel": 175, "summonerName": "", "teamEarlySurrendered": false, "teamId": 100, "teamPosition": "JUNGLE", "timeCCingOthers": 12, "timePlayed": 1259, "totalAllyJungleMinionsKilled": 78, "totalDamageDealt": 127002, "totalDamageDealtToChampions": 7442, "totalDamageShieldedOnTeammates": 0, "totalDamageTaken": 25152, "totalEnemyJungleMinionsKilled": 12, "totalHeal": 15937, "totalHealsOnTeammates": 0, "totalMinionsKilled": 2, "totalTimeCCDealt": 462, "totalTimeSpentDead": 100, "totalUnitsHealed": 1, "tripleKills": 0, "trueDamageDealt": 39803, "trueDamageDealtToChampions": 636, "trueDamageTaken": 292, "turretKills": 0, "turretTakedowns": 1, "turretsLost": 2, "unrealKills": 0, "visionClearedPings": 0, "visionScore": 6, "visionWardsBoughtInGame": 0, "wardsKilled": 0, "wardsPlaced": 3, "win": true}, {"PlayerScore0": 0, "PlayerScore1": 0, "PlayerScore10": 0, "PlayerScore11": 0, "PlayerScore2": 0, "PlayerScore3": 0, "PlayerScore4": 0, "PlayerScore5": 0, "PlayerScore6": 0, "PlayerScore7": 0, "PlayerScore8": 0, "PlayerScore9": 0, "allInPings": 1, "assistMePings": 0, "assists": 10, "baronKills": 0, "basicPings": 0, "challenges": {"12AssistStreakCount": 0, "HealFromMapSources": 0, "InfernalScalePickup": 0, "SWARM_DefeatAatrox": 0, "SWARM_DefeatBriar": 0, "SWARM_DefeatMiniBosses": 0, "SWARM_EvolveWeapon": 0, "SWARM_Have3Passives": 0, "SWARM_KillEnemy": 0, "SWARM_PickupGold": 0, "SWARM_ReachLevel50": 0, "SWARM_Survive15Min": 0, "SWARM_WinWith5EvolvedWeapons": 0, "abilityUses": 207, "acesBefore15Minutes": 0, "alliedJungleMonsterKills": 0, "baronTakedowns": 0, "blastConeOppositeOpponentCount": 0, "bountyGold": 0, "buffsStolen": 0, "completeSupportQuestInTime": 0, "controlWardTimeCoverageInRiverOrEnemyHalf": 0.36790632291503317, "controlWardsPlaced": 1, "damagePerMinute": 644.2595974373842, "damageTakenOnTeamPercentage": 0.15832025235530414, "dancedWithRiftHerald": 0, "deathsByEnemyChamps": 5, "dodgeSkillShotsSmallWindow": 0, "doubleAces": 0, "dragonTakedowns": 1, "earliestDragonTakedown": 842.407312528, "earlyLaningPhaseGoldExpAdvantage": 0, "effectiveHealAndShielding": 150.3096466064453, "elderDragonKillsWithOpposingSoul": 0, "elderDragonMultikills": 0, "enemyChampionImmobilizations": 18, "enemyJungleMonsterKills": 0, "epicMonsterKillsNearEnemyJungler": 0, "epicMonsterKillsWithin30SecondsOfSpawn": 0, "epicMonsterSteals": 0, "epicMonsterStolenWithoutSmite": 0, "firstTurretKilled": 1, "firstTurretKilledTime": 867.0563373860001, "fistBumpParticipation": 0, "flawlessAces": 0, "fullTeamTakedown": 0, "gameLength": 1259.316040521, "getTakedownsInAllLanesEarlyJungleAsLaner": 0, "goldPerMinute": 392.5543271353704, "hadOpenNexus": 0, "immobilizeAndKillWithAlly": 5, "initialBuffCount": 0, "initialCrabCount": 0, "jungleCsBefore10Minutes": 0, "junglerTakedownsNearDamagedEpicMonster": 0, "kTurretsDestroyedBeforePlatesFall": 0, "kda": 2.8, "killAfterHiddenWithAlly": 1, "killParticipation": 0.3888888888888889, "killedChampTookFullTeamDamageSurvived": 0, "killingSprees": 0, "killsNearEnemyTurret": 3, "killsOnOtherLanesEarlyJungleAsLaner": 0, "killsOnRecentlyHealedByAramPack": 0, "killsUnderOwnTurret": 0, "killsWithHelpFromEpicMonster": 0, "knockEnemyIntoTeamAndKill": 0, "landSkillShotsEarlyGame": 8, "laneMinionsFirst10Minutes": 59, "laningPhaseGoldExpAdvantage": 0, "legendaryCount": 0, "legendaryItemUsed": [6655], "lostAnInhibitor": 0, "maxCsAdvantageOnLaneOpponent": 18, "maxKillDeficit": 2, "maxLevelLeadLaneOpponent": 1, "mejaisFullStackInTime": 0, "moreEnemyJungleThanOpponent": 0, "multiKillOneSpell": 0, "multiTurretRiftHeraldCount": 0, "multikills": 0, "multikillsAfterAggressiveFlash": 0, "outerTurretExecutesBefore10Minutes": 0, "outnumberedKills": 0, "outnumberedNexusKill": 0, "perfectDragonSoulsTaken": 0, "perfectGame": 0, "pickKillWithAlly": 10, "playedChampSelectPosition": 1, "poroExplosions": 0, "quickCleanse": 0, "quickFirstTurret": 0, "quickSoloKills": 0, "riftHeraldTakedowns": 0, "saveAllyFromDeath": 0, "scuttleCrabKills": 0, "skillshotsDodged": 2, "skillshotsHit": 34, "snowballsHit": 0, "soloBaronKills": 0, "soloKills": 2, "stealthWardsPlaced": 7, "survivedSingleDigitHpCount": 0, "survivedThreeImmobilizesInFight": 0, "takedownOnFirstTurret": 0, "takedowns": 14, "takedownsAfterGainingLevelAdvantage": 0, "takedownsBeforeJungleMinionSpawn": 0, "takedownsFirstXMinutes": 7, "takedownsInAlcove": 0, "takedownsInEnemyFountain": 0, "teamBaronKills": 0, "teamDamagePercentage": 0.17898361277972527, "teamElderDragonKills": 0, "teamRiftHeraldKills": 1, "tookLargeDamageSurvived": 0, "turretPlatesTaken": 1, "turretTakedowns": 0, "turretsTakenWithRiftHerald": 5, "twentyMinionsIn3SecondsCount": 0, "twoWardsOneSweeperCount": 0, "unseenRecalls": 0, "visionScoreAdvantageLaneOpponent": 2.1338741779327393, "visionScorePerMinute": 0.7201859803413062, "voidMonsterKill": 0, "wardTakedowns": 1, "wardTakedownsBefore20M": 1, "wardsGuarded": 0}, "champExperience": 11083, "champLevel": 13, "championId": 142, "championName": "Zoe", "championTransform": 0, "commandPings": 1, "consumablesPurchased": 3, "damageDealtToBuildings": 1815, "damageDealtToObjectives": 2215, "damageDealtToTurrets": 1815, "damageSelfMitigated": 6765, "dangerPings": 0, "deaths": 5, "detectorWardsPlaced": 1, "doubleKills": 0, "dragonKills": 0, "eligibleForProgression": true, "enemyMissingPings": 4, "enemyVisionPings": 0, "firstBloodAssist": false, "firstBloodKill": false, "firstTowerAssist": false, "firstTowerKill": false, "gameEndedInEarlySurrender": false, "gameEndedInSurrender": true, "getBackPings": 0, "goldEarned": 8239, "goldSpent": 5865, "holdPings": 0, "individualPosition": "MIDDLE", "inhibitorKills": 0, "inhibitorTakedowns": 0, "inhibitorsLost": 0, "item0": 1056, "item1": 2031, "item2": 6655, "item3": 3145, "item4": 0, "item5": 3020, "item6": 3340, "itemsPurchased": 14, "killingSprees": 0, "kills": 4, "lane": "MIDDLE", "largestCriticalStrike": 0, "largestKillingSpree": 0, "largestMultiKill": 1, "longestTimeSpentLiving": 409, "magicDamageDealt": 48586, "magicDamageDealtToChampions": 9632, "magicDamageTaken": 8663, "missions": {"playerScore0": 0, "playerScore1": 0, "playerScore2": 0, "playerScore3": 0, "playerScore4": 0, "playerScore5": 0, "playerScore6": 0, "playerScore7": 0, "playerScore8": 0, "playerScore9": 0, "playerScore10": 0, "playerScore11": 0}, "needVisionPings": 1, "neutralMinionsKilled": 0, "nexusKills": 0, "nexusLost": 0, "nexusTakedowns": 0, "objectivesStolen": 0, "objectivesStolenAssists": 0, "onMyWayPings": 3, "participantId": 3, "pentaKills": 0, "perks": {"statPerks": {"defense": 5001, "flex": 5008, "offense": 5005}, "styles": [{"description": "primaryStyle", "selections": [{"perk": 8128, "var1": 765, "var2": 11, "var3": 0}, {"perk": 8143, "var1": 668, "var2": 0, "var3": 0}, {"perk": 8140, "var1": 14, "var2": 0, "var3": 0}, {"perk": 8105, "var1": 40, "var2": 5, "var3": 0}], "style": 8100}, {"description": "subStyle", "selections": [{"perk": 8275, "var1": 11, "var2": 0, "var3": 0}, {"perk": 8210, "var1": 8, "var2": 0, "var3": 0}], "style": 8200}]}, "physicalDamageDealt": 10668, "physicalDamageDealtToChampions": 1601, "physicalDamageTaken": 5318, "placement": 0, "playerAugment1": 0, "playerAugment2": 0, "playerAugment3": 0, "playerAugment4": 0, "playerAugment5": 0, "playerAugment6": 0, "playerSubteamId": 0, "profileIcon": 5489, "pushPings": 0, "puuid": "sypV6ignya2ap349xSVxeT6q6A0nKEKwNvLQ7sm9K-0YGtFP-98MkzTjGxmQ9tBLwtCJazNBJxDZeg", "quadraKills": 0, "retreatPings": 0, "riotIdGameName": "16th Account", "riotIdTagline": "STINK", "role": "SOLO", "sightWardsBoughtInGame": 0, "spell1Casts": 139, "spell2Casts": 12, "spell3Casts": 35, "spell4Casts": 21, "subteamPlacement": 0, "summoner1Casts": 3, "summoner1Id": 21, "summoner2Casts": 2, "summoner2Id": 4, "summonerId": "T75BLjqY_KZzc5no24yhCorRRNxUNXxFDQQL9QA8SlCsSK4TshUIzoLssw", "summonerLevel": 274, "summonerName": "", "teamEarlySurrendered": false, "teamId": 100, "teamPosition": "MIDDLE", "timeCCingOthers": 35, "timePlayed": 1259, "totalAllyJungleMinionsKilled": 0, "totalDamageDealt": 62622, "totalDamageDealtToChampions": 13522, "totalDamageShieldedOnTeammates": 150, "totalDamageTaken": 14599, "totalEnemyJungleMinionsKilled": 0, "totalHeal": 1163, "totalHealsOnTeammates": 0, "totalMinionsKilled": 110, "totalTimeCCDealt": 124, "totalTimeSpentDead": 150, "totalUnitsHealed": 1, "tripleKills": 0, "trueDamageDealt": 3367, "trueDamageDealtToChampions": 2287, "trueDamageTaken": 616, "turretKills": 0, "turretTakedowns": 0, "turretsLost": 2, "unrealKills": 0, "visionClearedPings": 0, "visionScore": 15, "visionWardsBoughtInGame": 1, "wardsKilled": 1, "wardsPlaced": 8, "win": true}, {"PlayerScore0": 0, "PlayerScore1": 0, "PlayerScore10": 0, "PlayerScore11": 0, "PlayerScore2": 0, "PlayerScore3": 0, "PlayerScore4": 0, "PlayerScore5": 0, "PlayerScore6": 0, "PlayerScore7": 0, "PlayerScore8": 0, "PlayerScore9": 0, "allInPings": 0, "assistMePings": 0, "assists": 3, "baronKills": 0, "basicPings": 0, "challenges": {"12AssistStreakCount": 0, "HealFromMapSources": 272, "InfernalScalePickup": 0, "SWARM_DefeatAatrox": 0, "SWARM_DefeatBriar": 0, "SWARM_DefeatMiniBosses": 0, "SWARM_EvolveWeapon": 0, "SWARM_Have3Passives": 0, "SWARM_KillEnemy": 0, "SWARM_PickupGold": 0, "SWARM_ReachLevel50": 0, "SWARM_Survive15Min": 0, "SWARM_WinWith5EvolvedWeapons": 0, "abilityUses": 130, "acesBefore15Minutes": 0, "alliedJungleMonsterKills": 0, "baronTakedowns": 0, "blastConeOppositeOpponentCount": 0, "bountyGold": 0, "buffsStolen": 0, "completeSupportQuestInTime": 0, "controlWardsPlaced": 1, "damagePerMinute": 1741.7678337262653, "damageTakenOnTeamPercentage": 0.18295958648954588, "dancedWithRiftHerald": 0, "deathsByEnemyChamps": 4, "dodgeSkillShotsSmallWindow": 0, "doubleAces": 0, "dragonTakedowns": 2, "earliestDragonTakedown": 842.407312528, "earlyLaningPhaseGoldExpAdvantage": 0, "effectiveHealAndShielding": 0, "elderDragonKillsWithOpposingSoul": 0, "elderDragonMultikills": 0, "enemyChampionImmobilizations": 27, "enemyJungleMonsterKills": 0, "epicMonsterKillsNearEnemyJungler": 1, "epicMonsterKillsWithin30SecondsOfSpawn": 0, "epicMonsterSteals": 0, "epicMonsterStolenWithoutSmite": 0, "fastestLegendary": 1055.897534988, "firstTurretKilled": 1, "firstTurretKilledTime": 867.0563373860001, "fistBumpParticipation": 0, "flawlessAces": 0, "fullTeamTakedown": 0, "gameLength": 1259.316040521, "getTakedownsInAllLanesEarlyJungleAsLaner": 0, "goldPerMinute": 700.6236195760479, "hadOpenNexus": 0, "highestChampionDamage": 1, "immobilizeAndKillWithAlly": 6, "initialBuffCount": 0, "initialCrabCount": 0, "jungleCsBefore10Minutes": 0, "junglerTakedownsNearDamagedEpicMonster": 0, "kTurretsDestroyedBeforePlatesFall": 0, "kda": 7, "killAfterHiddenWithAlly": 5, "killParticipation": 0.7777777777777778, "killedChampTookFullTeamDamageSurvived": 0, "killingSprees": 4, "killsNearEnemyTurret": 9, "killsOnOtherLanesEarlyJungleAsLaner": 0, "killsOnRecentlyHealedByAramPack": 0, "killsUnderOwnTurret": 1, "killsWithHelpFromEpicMonster": 1, "knockEnemyIntoTeamAndKill": 6, "landSkillShotsEarlyGame": 9, "laneMinionsFirst10Minutes": 34, "laningPhaseGoldExpAdvantage": 0, "legendaryCount": 2, "legendaryItemUsed": [3153, 3124], "lostAnInhibitor": 0, "maxCsAdvantageOnLaneOpponent": 22, "maxKillDeficit": 2, "maxLevelLeadLaneOpponent": 2, "mejaisFullStackInTime": 0, "moreEnemyJungleThanOpponent": 0, "multiKillOneSpell": 0, "multiTurretRiftHeraldCount": 0, "multikills": 8, "multikillsAfterAggressiveFlash": 2, "outerTurretExecutesBefore10Minutes": 0, "outnumberedKills": 6, "outnumberedNexusKill": 0, "perfectDragonSoulsTaken": 0, "perfectGame": 0, "pickKillWithAlly": 23, "playedChampSelectPosition": 1, "poroExplosions": 0, "quickCleanse": 0, "quickFirstTurret": 0, "quickSoloKills": 0, "riftHeraldTakedowns": 1, "saveAllyFromDeath": 0, "scuttleCrabKills": 2, "skillshotsDodged": 12, "skillshotsHit": 84, "snowballsHit": 0, "soloBaronKills": 0, "soloKills": 2, "stealthWardsPlaced": 6, "survivedSingleDigitHpCount": 0, "survivedThreeImmobilizesInFight": 7, "takedownOnFirstTurret": 1, "takedowns": 28, "takedownsAfterGainingLevelAdvantage": 0, "takedownsBeforeJungleMinionSpawn": 0, "takedownsFirstXMinutes": 14, "takedownsInAlcove": 1, "takedownsInEnemyFountain": 0, "teamBaronKills": 0, "teamDamagePercentage": 0.4838855342533593, "teamElderDragonKills": 0, "teamRiftHeraldKills": 1, "tookLargeDamageSurvived": 0, "turretPlatesTaken": 3, "turretTakedowns": 4, "turretsTakenWithRiftHerald": 5, "twentyMinionsIn3SecondsCount": 0, "twoWardsOneSweeperCount": 0, "unseenRecalls": 0, "visionScoreAdvantageLaneOpponent": 3.5498838424682617, "visionScorePerMinute": 0.6829837047032927, "voidMonsterKill": 1, "wardTakedowns": 0, "wardTakedownsBefore20M": 0, "wardsGuarded": 0}, "champExperience": 11026, "champLevel": 13, "championId": 67, "championName": "Vayne", "championTransform": 0, "commandPings": 10, "consumablesPurchased": 5, "damageDealtToBuildings": 7845, "damageDealtToObjectives": 15824, "damageDealtToTurrets": 7845, "damageSelfMitigated": 8726, "dangerPings": 0, "deaths": 4, "detectorWardsPlaced": 1, "doubleKills": 6, "dragonKills": 1, "eligibleForProgression": true, "enemyMissingPings": 0, "enemyVisionPings": 0, "firstBloodAssist": false, "firstBloodKill": false, "firstTowerAssist": false, "firstTowerKill": true, "gameEndedInEarlySurrender": false, "gameEndedInSurrender": true, "getBackPings": 1, "goldEarned": 14705, "goldSpent": 10205, "holdPings": 0, "individualPosition": "BOTTOM", "inhibitorKills": 0, "inhibitorTakedowns": 0, "inhibitorsLost": 0, "item0": 1055, "item1": 3124, "item2": 3153, "item3": 3172, "item4": 1043, "item5": 1036, "item6": 3340, "itemsPurchased": 21, "killingSprees": 5, "kills": 25, "lane": "BOTTOM", "largestCriticalStrike": 0, "largestKillingSpree": 8, "largestMultiKill": 3, "longestTimeSpentLiving": 408, "magicDamageDealt": 3424, "magicDamageDealtToChampions": 1003, "magicDamageTaken": 5658, "missions": {"playerScore0": 0, "playerScore1": 0, "playerScore2": 0, "playerScore3": 0, "playerScore4": 0, "playerScore5": 0, "playerScore6": 0, "playerScore7": 0, "playerScore8": 0, "playerScore9": 0, "playerScore10": 0, "playerScore11": 0}, "needVisionPings": 0, "neutralMinionsKilled": 12, "nexusKills": 0, "nexusLost": 0, "nexusTakedowns": 0, "objectivesStolen": 0, "objectivesStolenAssists": 0, "onMyWayPings": 3, "participantId": 4, "pentaKills": 0, "perks": {"statPerks": {"defense": 5001, "flex": 5008, "offense": 5005}, "styles": [{"description": "primaryStyle", "selections": [{"perk": 8008, "var1": 1500, "var2": 1500, "var3": 0}, {"perk": 9111, "var1": 1736, "var2": 560, "var3": 0}, {"perk": 9104, "var1": 10, "var2": 20, "var3": 0}, {"perk": 8014, "var1": 1197, "var2": 0, "var3": 0}], "style": 8000}, {"description": "subStyle", "selections": [{"perk": 8429, "var1": 42, "var2": 10, "var3": 9}, {"perk": 8451, "var1": 131, "var2": 0, "var3": 0}], "style": 8400}]}, "physicalDamageDealt": 78983, "physicalDamageDealtToChampions": 28157, "physicalDamageTaken": 10142, "placement": 0, "playerAugment1": 0, "playerAugment2": 0, "playerAugment3": 0, "playerAugment4": 0, "playerAugment5": 0, "playerAugment6": 0, "playerSubteamId": 0, "profileIcon": 6077, "pushPings": 0, "puuid": "FI50B7HRBu_Q4DM4J-zdMFD0Wp0oW12KFlwyvTyXinOf_TfeQr0poPPUAXddHkcp-5j36AUA2W9JdQ", "quadraKills": 0, "retreatPings": 0, "riotIdGameName": "Munchkin78", "riotIdTagline": "NA1", "role": "CARRY", "sightWardsBoughtInGame": 0, "spell1Casts": 103, "spell2Casts": 0, "spell3Casts": 20, "spell4Casts": 7, "subteamPlacement": 0, "summoner1Casts": 3, "summoner1Id": 4, "summoner2Casts": 3, "summoner2Id": 21, "summonerId": "lRYpwlllMxkmBb9Pq5cYIjxI0mom67feseqqrWAS_r2oipI", "summonerLevel": 28, "summonerName": "", "teamEarlySurrendered": false, "teamId": 100, "teamPosition": "BOTTOM", "timeCCingOthers": 19, "timePlayed": 1259, "totalAllyJungleMinionsKilled": 0, "totalDamageDealt": 99173, "totalDamageDealtToChampions": 36557, "totalDamageShieldedOnTeammates": 0, "totalDamageTaken": 16871, "totalEnemyJungleMinionsKilled": 0, "totalHeal": 7731, "totalHealsOnTeammates": 0, "totalMinionsKilled": 89, "totalTimeCCDealt": 110, "totalTimeSpentDead": 90, "totalUnitsHealed": 1, "tripleKills": 2, "trueDamageDealt": 16765, "trueDamageDealtToChampions": 7396, "trueDamageTaken": 1070, "turretKills": 4, "turretTakedowns": 4, "turretsLost": 2, "unrealKills": 0, "visionClearedPings": 0, "visionScore": 14, "visionWardsBoughtInGame": 1, "wardsKilled": 0, "wardsPlaced": 7, "win": true}, {"PlayerScore0": 0, "PlayerScore1": 0, "PlayerScore10": 0, "PlayerScore11": 0, "PlayerScore2": 0, "PlayerScore3": 0, "PlayerScore4": 0, "PlayerScore5": 0, "PlayerScore6": 0, "PlayerScore7": 0, "PlayerScore8": 0, "PlayerScore9": 0, "allInPings": 0, "assistMePings": 0, "assists": 20, "baronKills": 0, "basicPings": 0, "challenges": {"12AssistStreakCount": 1, "HealFromMapSources": 298.43536376953125, "InfernalScalePickup": 0, "SWARM_DefeatAatrox": 0, "SWARM_DefeatBriar": 0, "SWARM_DefeatMiniBosses": 0, "SWARM_EvolveWeapon": 0, "SWARM_Have3Passives": 0, "SWARM_KillEnemy": 0, "SWARM_PickupGold": 0, "SWARM_ReachLevel50": 0, "SWARM_Survive15Min": 0, "SWARM_WinWith5EvolvedWeapons": 0, "abilityUses": 94, "acesBefore15Minutes": 0, "alliedJungleMonsterKills": 0, "baronTakedowns": 0, "blastConeOppositeOpponentCount": 0, "bountyGold": 0, "buffsStolen": 0, "completeSupportQuestInTime": 1, "controlWardsPlaced": 0, "damagePerMinute": 350.3324915875381, "damageTakenOnTeamPercentage": 0.1596969493730593, "dancedWithRiftHerald": 0, "deathsByEnemyChamps": 6, "dodgeSkillShotsSmallWindow": 1, "doubleAces": 0, "dragonTakedowns": 2, "earliestDragonTakedown": 842.407312528, "earlyLaningPhaseGoldExpAdvantage": 0, "effectiveHealAndShielding": 268.5511474609375, "elderDragonKillsWithOpposingSoul": 0, "elderDragonMultikills": 0, "enemyChampionImmobilizations": 45, "enemyJungleMonsterKills": 0, "epicMonsterKillsNearEnemyJungler": 0, "epicMonsterKillsWithin30SecondsOfSpawn": 0, "epicMonsterSteals": 0, "epicMonsterStolenWithoutSmite": 0, "fasterSupportQuestCompletion": 1, "firstTurretKilled": 1, "firstTurretKilledTime": 867.0563373860001, "fistBumpParticipation": 0, "flawlessAces": 0, "fullTeamTakedown": 0, "gameLength": 1259.316040521, "getTakedownsInAllLanesEarlyJungleAsLaner": 0, "goldPerMinute": 352.55123690054467, "hadOpenNexus": 0, "immobilizeAndKillWithAlly": 17, "initialBuffCount": 0, "initialCrabCount": 0, "jungleCsBefore10Minutes": 0, "junglerTakedownsNearDamagedEpicMonster": 0, "kTurretsDestroyedBeforePlatesFall": 0, "kda": 3.6666666666666665, "killAfterHiddenWithAlly": 5, "killParticipation": 0.6111111111111112, "killedChampTookFullTeamDamageSurvived": 0, "killingSprees": 0, "killsNearEnemyTurret": 0, "killsOnOtherLanesEarlyJungleAsLaner": 0, "killsOnRecentlyHealedByAramPack": 0, "killsUnderOwnTurret": 0, "killsWithHelpFromEpicMonster": 0, "knockEnemyIntoTeamAndKill": 0, "landSkillShotsEarlyGame": 4, "laneMinionsFirst10Minutes": 8, "laningPhaseGoldExpAdvantage": 0, "legendaryCount": 0, "legendaryItemUsed": [3190, 3876, 3109], "lostAnInhibitor": 0, "maxCsAdvantageOnLaneOpponent": 6, "maxKillDeficit": 2, "maxLevelLeadLaneOpponent": 1, "mejaisFullStackInTime": 0, "moreEnemyJungleThanOpponent": 0, "multiKillOneSpell": 0, "multiTurretRiftHeraldCount": 0, "multikills": 0, "multikillsAfterAggressiveFlash": 0, "outerTurretExecutesBefore10Minutes": 0, "outnumberedKills": 0, "outnumberedNexusKill": 0, "perfectDragonSoulsTaken": 0, "perfectGame": 0, "pickKillWithAlly": 20, "playedChampSelectPosition": 1, "poroExplosions": 0, "quickCleanse": 0, "quickFirstTurret": 0, "quickSoloKills": 0, "riftHeraldTakedowns": 1, "saveAllyFromDeath": 0, "scuttleCrabKills": 0, "skillshotsDodged": 12, "skillshotsHit": 13, "snowballsHit": 0, "soloBaronKills": 0, "soloKills": 0, "stealthWardsPlaced": 9, "survivedSingleDigitHpCount": 0, "survivedThreeImmobilizesInFight": 5, "takedownOnFirstTurret": 0, "takedowns": 22, "takedownsAfterGainingLevelAdvantage": 0, "takedownsBeforeJungleMinionSpawn": 0, "takedownsFirstXMinutes": 13, "takedownsInAlcove": 0, "takedownsInEnemyFountain": 0, "teamBaronKills": 0, "teamDamagePercentage": 0.0973268776559506, "teamElderDragonKills": 0, "teamRiftHeraldKills": 1, "tookLargeDamageSurvived": 0, "turretPlatesTaken": 3, "turretTakedowns": 0, "turretsTakenWithRiftHerald": 5, "twentyMinionsIn3SecondsCount": 0, "twoWardsOneSweeperCount": 0, "unseenRecalls": 0, "visionScoreAdvantageLaneOpponent": -0.6747490167617798, "visionScorePerMinute": 0.6276941692245249, "voidMonsterKill": 1, "wardTakedowns": 0, "wardTakedownsBefore20M": 0, "wardsGuarded": 0}, "champExperience": 7872, "champLevel": 11, "championId": 89, "championName": "Leona", "championTransform": 0, "commandPings": 0, "consumablesPurchased": 2, "damageDealtToBuildings": 356, "damageDealtToObjectives": 3890, "damageDealtToTurrets": 356, "damageSelfMitigated": 17722, "dangerPings": 0, "deaths": 6, "detectorWardsPlaced": 0, "doubleKills": 0, "dragonKills": 0, "eligibleForProgression": true, "enemyMissingPings": 0, "enemyVisionPings": 0, "firstBloodAssist": false, "firstBloodKill": false, "firstTowerAssist": false, "firstTowerKill": false, "gameEndedInEarlySurrender": false, "gameEndedInSurrender": true, "getBackPings": 1, "goldEarned": 7399, "goldSpent": 7100, "holdPings": 0, "individualPosition": "UTILITY", "inhibitorKills": 0, "inhibitorTakedowns": 0, "inhibitorsLost": 0, "item0": 3876, "item1": 3190, "item2": 3109, "item3": 3174, "item4": 1028, "item5": 0, "item6": 3340, "itemsPurchased": 19, "killingSprees": 1, "kills": 2, "lane": "BOTTOM", "largestCriticalStrike": 0, "largestKillingSpree": 2, "largestMultiKill": 1, "longestTimeSpentLiving": 324, "magicDamageDealt": 8696, "magicDamageDealtToChampions": 3781, "magicDamageTaken": 3675, "missions": {"playerScore0": 0, "playerScore1": 0, "playerScore2": 0, "playerScore3": 0, "playerScore4": 0, "playerScore5": 0, "playerScore6": 0, "playerScore7": 0, "playerScore8": 0, "playerScore9": 0, "playerScore10": 0, "playerScore11": 0}, "needVisionPings": 0, "neutralMinionsKilled": 0, "nexusKills": 0, "nexusLost": 0, "nexusTakedowns": 0, "objectivesStolen": 0, "objectivesStolenAssists": 0, "onMyWayPings": 0, "participantId": 5, "pentaKills": 0, "perks": {"statPerks": {"defense": 5001, "flex": 5001, "offense": 5007}, "styles": [{"description": "primaryStyle", "selections": [{"perk": 8439, "var1": 654, "var2": 666, "var3": 0}, {"perk": 8463, "var1": 747, "var2": 0, "var3": 0}, {"perk": 8473, "var1": 362, "var2": 0, "var3": 0}, {"perk": 8242, "var1": 96, "var2": 0, "var3": 0}], "style": 8400}, {"description": "subStyle", "selections": [{"perk": 8345, "var1": 3, "var2": 0, "var3": 165}, {"perk": 8347, "var1": 0, "var2": 0, "var3": 0}], "style": 8300}]}, "physicalDamageDealt": 8733, "physicalDamageDealtToChampions": 2952, "physicalDamageTaken": 9545, "placement": 0, "playerAugment1": 0, "playerAugment2": 0, "playerAugment3": 0, "playerAugment4": 0, "playerAugment5": 0, "playerAugment6": 0, "playerSubteamId": 0, "profileIcon": 3018, "pushPings": 0, "puuid": "WWTC7-2jIgGdZWqMyA8_ral_hfYG1o7Qleg1eIq7vx21uYuBR4BZgQIOHQn_EkTjWOv895ltqlxfZQ", "quadraKills": 0, "retreatPings": 0, "riotIdGameName": "Meguminn", "riotIdTagline": "MEGU1", "role": "SUPPORT", "sightWardsBoughtInGame": 0, "spell1Casts": 37, "spell2Casts": 29, "spell3Casts": 22, "spell4Casts": 6, "subteamPlacement": 0, "summoner1Casts": 3, "summoner1Id": 4, "summoner2Casts": 5, "summoner2Id": 14, "summonerId": "fc9kDUmbqAbPzff361S102b25tXudN-3280TtNhfLQAf0jAQ", "summonerLevel": 36, "summonerName": "", "teamEarlySurrendered": false, "teamId": 100, "teamPosition": "UTILITY", "timeCCingOthers": 38, "timePlayed": 1259, "totalAllyJungleMinionsKilled": 0, "totalDamageDealt": 21452, "totalDamageDealtToChampions": 7352, "totalDamageShieldedOnTeammates": 12, "totalDamageTaken": 14726, "totalEnemyJungleMinionsKilled": 0, "totalHeal": 1934, "totalHealsOnTeammates": 256, "totalMinionsKilled": 14, "totalTimeCCDealt": 61, "totalTimeSpentDead": 119, "totalUnitsHealed": 4, "tripleKills": 0, "trueDamageDealt": 4022, "trueDamageDealtToChampions": 618, "trueDamageTaken": 1504, "turretKills": 0, "turretTakedowns": 0, "turretsLost": 2, "unrealKills": 0, "visionClearedPings": 0, "visionScore": 13, "visionWardsBoughtInGame": 0, "wardsKilled": 0, "wardsPlaced": 9, "win": true}, {"PlayerScore0": 0, "PlayerScore1": 0, "PlayerScore10": 0, "PlayerScore11": 0, "PlayerScore2": 0, "PlayerScore3": 0, "PlayerScore4": 0, "PlayerScore5": 0, "PlayerScore6": 0, "PlayerScore7": 0, "PlayerScore8": 0, "PlayerScore9": 0, "allInPings": 0, "assistMePings": 0, "assists": 1, "baronKills": 0, "basicPings": 0, "challenges": {"12AssistStreakCount": 0, "HealFromMapSources": 280, "InfernalScalePickup": 0, "SWARM_DefeatAatrox": 0, "SWARM_DefeatBriar": 0, "SWARM_DefeatMiniBosses": 0, "SWARM_EvolveWeapon": 0, "SWARM_Have3Passives": 0, "SWARM_KillEnemy": 0, "SWARM_PickupGold": 0, "SWARM_ReachLevel50": 0, "SWARM_Survive15Min": 0, "SWARM_WinWith5EvolvedWeapons": 0, "abilityUses": 92, "acesBefore15Minutes": 0, "alliedJungleMonsterKills": 0, "baronTakedowns": 0, "blastConeOppositeOpponentCount": 0, "bountyGold": 0, "buffsStolen": 0, "completeSupportQuestInTime": 0, "controlWardsPlaced": 0, "damagePerMinute": 869.2902318306053, "damageTakenOnTeamPercentage": 0.17139288118257948, "dancedWithRiftHerald": 0, "deathsByEnemyChamps": 5, "dodgeSkillShotsSmallWindow": 0, "doubleAces": 0, "dragonTakedowns": 0, "earlyLaningPhaseGoldExpAdvantage": 0, "effectiveHealAndShielding": 0, "elderDragonKillsWithOpposingSoul": 0, "elderDragonMultikills": 0, "enemyChampionImmobilizations": 29, "enemyJungleMonsterKills": 0, "epicMonsterKillsNearEnemyJungler": 0, "epicMonsterKillsWithin30SecondsOfSpawn": 0, "epicMonsterSteals": 0, "epicMonsterStolenWithoutSmite": 0, "firstTurretKilled": 0, "fistBumpParticipation": 0, "flawlessAces": 0, "fullTeamTakedown": 0, "gameLength": 1259.316040521, "getTakedownsInAllLanesEarlyJungleAsLaner": 0, "goldPerMinute": 345.2883193330324, "hadOpenNexus": 0, "immobilizeAndKillWithAlly": 1, "initialBuffCount": 0, "initialCrabCount": 0, "jungleCsBefore10Minutes": 0, "junglerTakedownsNearDamagedEpicMonster": 0, "kTurretsDestroyedBeforePlatesFall": 0, "kda": 1, "killAfterHiddenWithAlly": 1, "killParticipation": 0.2, "killedChampTookFullTeamDamageSurvived": 0, "killingSprees": 1, "killsNearEnemyTurret": 0, "killsOnOtherLanesEarlyJungleAsLaner": 0, "killsOnRecentlyHealedByAramPack": 0, "killsUnderOwnTurret": 0, "killsWithHelpFromEpicMonster": 0, "knockEnemyIntoTeamAndKill": 2, "landSkillShotsEarlyGame": 4, "laneMinionsFirst10Minutes": 50, "laningPhaseGoldExpAdvantage": 0, "legendaryCount": 0, "legendaryItemUsed": [3087, 3071], "lostAnInhibitor": 0, "maxCsAdvantageOnLaneOpponent": 2, "maxKillDeficit": 0, "maxLevelLeadLaneOpponent": 1, "mejaisFullStackInTime": 0, "moreEnemyJungleThanOpponent": 0, "multiKillOneSpell": 0, "multiTurretRiftHeraldCount": 0, "multikills": 0, "multikillsAfterAggressiveFlash": 0, "outerTurretExecutesBefore10Minutes": 0, "outnumberedKills": 0, "outnumberedNexusKill": 0, "perfectDragonSoulsTaken": 0, "perfectGame": 0, "pickKillWithAlly": 3, "playedChampSelectPosition": 1, "poroExplosions": 0, "quickCleanse": 0, "quickFirstTurret": 0, "quickSoloKills": 0, "riftHeraldTakedowns": 0, "saveAllyFromDeath": 0, "scuttleCrabKills": 0, "skillshotsDodged": 1, "skillshotsHit": 22, "snowballsHit": 0, "soloBaronKills": 0, "soloKills": 2, "soloTurretsLategame": 1, "stealthWardsPlaced": 5, "survivedSingleDigitHpCount": 0, "survivedThreeImmobilizesInFight": 0, "takedownOnFirstTurret": 0, "takedowns": 5, "takedownsAfterGainingLevelAdvantage": 0, "takedownsBeforeJungleMinionSpawn": 0, "takedownsFirstXMinutes": 3, "takedownsInAlcove": 0, "takedownsInEnemyFountain": 0, "teamBaronKills": 0, "teamDamagePercentage": 0.29603426486726425, "teamElderDragonKills": 0, "teamRiftHeraldKills": 0, "tookLargeDamageSurvived": 0, "turretPlatesTaken": 0, "turretTakedowns": 1, "turretsTakenWithRiftHerald": 0, "twentyMinionsIn3SecondsCount": 0, "twoWardsOneSweeperCount": 0, "unseenRecalls": 0, "visionScoreAdvantageLaneOpponent": 0.2583794593811035, "visionScorePerMinute": 0.39535539291193983, "voidMonsterKill": 3, "wardTakedowns": 0, "wardTakedownsBefore20M": 0, "wardsGuarded": 0}, "champExperience": 10548, "champLevel": 13, "championId": 6, "championName": "Urgot", "championTransform": 0, "commandPings": 0, "consumablesPurchased": 0, "damageDealtToBuildings": 3942, "damageDealtToObjectives": 6684, "damageDealtToTurrets": 3942, "damageSelfMitigated": 14191, "dangerPings": 0, "deaths": 5, "detectorWardsPlaced": 0, "doubleKills": 0, "dragonKills": 0, "eligibleForProgression": true, "enemyMissingPings": 0, "enemyVisionPings": 0, "firstBloodAssist": false, "firstBloodKill": false, "firstTowerAssist": false, "firstTowerKill": false, "gameEndedInEarlySurrender": false, "gameEndedInSurrender": true, "getBackPings": 0, "goldEarned": 7247, "goldSpent": 6950, "holdPings": 0, "individualPosition": "TOP", "inhibitorKills": 0, "inhibitorTakedowns": 0, "inhibitorsLost": 0, "item0": 3087, "item1": 2031, "item2": 3009, "item3": 3071, "item4": 1028, "item5": 0, "item6": 3340, "itemsPurchased": 14, "killingSprees": 1, "kills": 4, "lane": "TOP", "largestCriticalStrike": 0, "largestKillingSpree": 3, "largestMultiKill": 1, "longestTimeSpentLiving": 617, "magicDamageDealt": 8689, "magicDamageDealtToChampions": 1719, "magicDamageTaken": 2566, "missions": {"playerScore0": 0, "playerScore1": 0, "playerScore2": 0, "playerScore3": 0, "playerScore4": 0, "playerScore5": 0, "playerScore6": 0, "playerScore7": 0, "playerScore8": 0, "playerScore9": 0, "playerScore10": 0, "playerScore11": 0}, "needVisionPings": 0, "neutralMinionsKilled": 2, "nexusKills": 0, "nexusLost": 1, "nexusTakedowns": 0, "objectivesStolen": 0, "objectivesStolenAssists": 0, "onMyWayPings": 0, "participantId": 6, "pentaKills": 0, "perks": {"statPerks": {"defense": 5001, "flex": 5008, "offense": 5008}, "styles": [{"description": "primaryStyle", "selections": [{"perk": 8005, "var1": 1790, "var2": 1790, "var3": 0}, {"perk": 9111, "var1": 372, "var2": 100, "var3": 0}, {"perk": 9105, "var1": 16, "var2": 0, "var3": 0}, {"perk": 8299, "var1": 591, "var2": 0, "var3": 0}], "style": 8000}, {"description": "subStyle", "selections": [{"perk": 8410, "var1": 41, "var2": 0, "var3": 0}, {"perk": 8304, "var1": 10, "var2": 3, "var3": 0}], "style": 8300}]}, "physicalDamageDealt": 68027, "physicalDamageDealtToChampions": 15573, "physicalDamageTaken": 12792, "placement": 0, "playerAugment1": 0, "playerAugment2": 0, "playerAugment3": 0, "playerAugment4": 0, "playerAugment5": 0, "playerAugment6": 0, "playerSubteamId": 0, "profileIcon": 2098, "pushPings": 0, "puuid": "mgro-XgaZs2VV7IEx6Fia0iHo0OiwyiKgENAC2XVlMz9x9RZqqspxORDU1VQJQKLAkpAMVBWvF7__w", "quadraKills": 0, "retreatPings": 0, "riotIdGameName": "TaskForceLee8181", "riotIdTagline": "NA1", "role": "SOLO", "sightWardsBoughtInGame": 0, "spell1Casts": 28, "spell2Casts": 37, "spell3Casts": 20, "spell4Casts": 7, "subteamPlacement": 0, "summoner1Casts": 3, "summoner1Id": 12, "summoner2Casts": 3, "summoner2Id": 4, "summonerId": "XE0uuUzJZL2DjxDADNRZ1HdcKWSgkl_qYFMimAQU9Jyp4_yZ1w5VIHKF-w", "summonerLevel": 112, "summonerName": "", "teamEarlySurrendered": false, "teamId": 200, "teamPosition": "TOP", "timeCCingOthers": 30, "timePlayed": 1259, "totalAllyJungleMinionsKilled": 0, "totalDamageDealt": 79835, "totalDamageDealtToChampions": 18245, "totalDamageShieldedOnTeammates": 0, "totalDamageTaken": 16319, "totalEnemyJungleMinionsKilled": 0, "totalHeal": 2149, "totalHealsOnTeammates": 0, "totalMinionsKilled": 113, "totalTimeCCDealt": 152, "totalTimeSpentDead": 144, "totalUnitsHealed": 1, "tripleKills": 0, "trueDamageDealt": 3119, "trueDamageDealtToChampions": 952, "trueDamageTaken": 960, "turretKills": 1, "turretTakedowns": 1, "turretsLost": 5, "unrealKills": 0, "visionClearedPings": 0, "visionScore": 8, "visionWardsBoughtInGame": 0, "wardsKilled": 0, "wardsPlaced": 5, "win": false}, {"PlayerScore0": 0, "PlayerScore1": 0, "PlayerScore10": 0, "PlayerScore11": 0, "PlayerScore2": 0, "PlayerScore3": 0, "PlayerScore4": 0, "PlayerScore5": 0, "PlayerScore6": 0, "PlayerScore7": 0, "PlayerScore8": 0, "PlayerScore9": 0, "allInPings": 0, "assistMePings": 0, "assists": 5, "baronKills": 0, "basicPings": 0, "challenges": {"12AssistStreakCount": 0, "HealFromMapSources": 0, "InfernalScalePickup": 0, "SWARM_DefeatAatrox": 0, "SWARM_DefeatBriar": 0, "SWARM_DefeatMiniBosses": 0, "SWARM_EvolveWeapon": 0, "SWARM_Have3Passives": 0, "SWARM_KillEnemy": 0, "SWARM_PickupGold": 0, "SWARM_ReachLevel50": 0, "SWARM_Survive15Min": 0, "SWARM_WinWith5EvolvedWeapons": 0, "abilityUses": 104, "acesBefore15Minutes": 0, "alliedJungleMonsterKills": 40, "baronTakedowns": 0, "blastConeOppositeOpponentCount": 0, "bountyGold": 387.84130859375, "buffsStolen": 0, "completeSupportQuestInTime": 0, "controlWardsPlaced": 0, "damagePerMinute": 560.7493757497122, "damageTakenOnTeamPercentage": 0.3338786175859079, "dancedWithRiftHerald": 0, "deathsByEnemyChamps": 8, "dodgeSkillShotsSmallWindow": 0, "doubleAces": 0, "dragonTakedowns": 1, "earliestDragonTakedown": 467.04847545, "earlyLaningPhaseGoldExpAdvantage": 1, "effectiveHealAndShielding": 0, "elderDragonKillsWithOpposingSoul": 0, "elderDragonMultikills": 0, "enemyChampionImmobilizations": 17, "enemyJungleMonsterKills": 6, "epicMonsterKillsNearEnemyJungler": 0, "epicMonsterKillsWithin30SecondsOfSpawn": 0, "epicMonsterSteals": 0, "epicMonsterStolenWithoutSmite": 0, "firstTurretKilled": 0, "fistBumpParticipation": 0, "flawlessAces": 0, "fullTeamTakedown": 0, "gameLength": 1259.316040521, "goldPerMinute": 415.3507417773399, "hadOpenNexus": 0, "immobilizeAndKillWithAlly": 6, "initialBuffCount": 2, "initialCrabCount": 0, "jungleCsBefore10Minutes": 52.000000059604645, "junglerKillsEarlyJungle": 2, "junglerTakedownsNearDamagedEpicMonster": 0, "kTurretsDestroyedBeforePlatesFall": 0, "kda": 1.5, "killAfterHiddenWithAlly": 2, "killParticipation": 0.48, "killedChampTookFullTeamDamageSurvived": 0, "killingSprees": 1, "killsNearEnemyTurret": 4, "killsOnLanersEarlyJungleAsJungler": 3, "killsOnRecentlyHealedByAramPack": 0, "killsUnderOwnTurret": 0, "killsWithHelpFromEpicMonster": 0, "knockEnemyIntoTeamAndKill": 0, "landSkillShotsEarlyGame": 0, "laneMinionsFirst10Minutes": 3, "laningPhaseGoldExpAdvantage": 0, "legendaryCount": 0, "legendaryItemUsed": [6631, 3153], "lostAnInhibitor": 0, "maxCsAdvantageOnLaneOpponent": 11.000000029802322, "maxKillDeficit": 0, "maxLevelLeadLaneOpponent": 2, "mejaisFullStackInTime": 0, "moreEnemyJungleThanOpponent": -37, "multiKillOneSpell": 0, "multiTurretRiftHeraldCount": 0, "multikills": 1, "multikillsAfterAggressiveFlash": 0, "outerTurretExecutesBefore10Minutes": 0, "outnumberedKills": 1, "outnumberedNexusKill": 0, "perfectDragonSoulsTaken": 0, "perfectGame": 0, "pickKillWithAlly": 8, "playedChampSelectPosition": 1, "poroExplosions": 0, "quickCleanse": 0, "quickFirstTurret": 0, "quickSoloKills": 0, "riftHeraldTakedowns": 0, "saveAllyFromDeath": 0, "scuttleCrabKills": 0, "skillshotsDodged": 15, "skillshotsHit": 0, "snowballsHit": 0, "soloBaronKills": 0, "soloKills": 4, "stealthWardsPlaced": 5, "survivedSingleDigitHpCount": 0, "survivedThreeImmobilizesInFight": 1, "takedownOnFirstTurret": 0, "takedowns": 12, "takedownsAfterGainingLevelAdvantage": 0, "takedownsBeforeJungleMinionSpawn": 0, "takedownsFirstXMinutes": 10, "takedownsInAlcove": 0, "takedownsInEnemyFountain": 0, "teamBaronKills": 0, "teamDamagePercentage": 0.19096157203477152, "teamElderDragonKills": 0, "teamRiftHeraldKills": 0, "tookLargeDamageSurvived": 0, "turretPlatesTaken": 0, "turretTakedowns": 0, "turretsTakenWithRiftHerald": 0, "twentyMinionsIn3SecondsCount": 0, "twoWardsOneSweeperCount": 0, "unseenRecalls": 0, "visionScoreAdvantageLaneOpponent": 0.0456233024597168, "visionScorePerMinute": 0.33173471379759856, "voidMonsterKill": 3, "wardTakedowns": 0, "wardTakedownsBefore20M": 0, "wardsGuarded": 0}, "champExperience": 7748, "champLevel": 11, "championId": 19, "championName": "Warwick", "championTransform": 0, "commandPings": 4, "consumablesPurchased": 0, "damageDealtToBuildings": 0, "damageDealtToObjectives": 18875, "damageDealtToTurrets": 0, "damageSelfMitigated": 16133, "dangerPings": 0, "deaths": 8, "detectorWardsPlaced": 0, "doubleKills": 1, "dragonKills": 1, "eligibleForProgression": true, "enemyMissingPings": 0, "enemyVisionPings": 0, "firstBloodAssist": false, "firstBloodKill": false, "firstTowerAssist": false, "firstTowerKill": false, "gameEndedInEarlySurrender": false, "gameEndedInSurrender": true, "getBackPings": 0, "goldEarned": 8717, "goldSpent": 8600, "holdPings": 0, "individualPosition": "JUNGLE", "inhibitorKills": 0, "inhibitorTakedowns": 0, "inhibitorsLost": 0, "item0": 1102, "item1": 6631, "item2": 3111, "item3": 3153, "item4": 1028, "item5": 1029, "item6": 3340, "itemsPurchased": 12, "killingSprees": 1, "kills": 7, "lane": "JUNGLE", "largestCriticalStrike": 0, "largestKillingSpree": 4, "largestMultiKill": 2, "longestTimeSpentLiving": 263, "magicDamageDealt": 25742, "magicDamageDealtToChampions": 5879, "magicDamageTaken": 5357, "missions": {"playerScore0": 0, "playerScore1": 0, "playerScore2": 0, "playerScore3": 0, "playerScore4": 0, "playerScore5": 0, "playerScore6": 0, "playerScore7": 0, "playerScore8": 0, "playerScore9": 0, "playerScore10": 0, "playerScore11": 0}, "needVisionPings": 0, "neutralMinionsKilled": 83, "nexusKills": 0, "nexusLost": 1, "nexusTakedowns": 0, "objectivesStolen": 0, "objectivesStolenAssists": 0, "onMyWayPings": 0, "participantId": 7, "pentaKills": 0, "perks": {"statPerks": {"defense": 5001, "flex": 5008, "offense": 5005}, "styles": [{"description": "primaryStyle", "selections": [{"perk": 8008, "var1": 791, "var2": 791, "var3": 0}, {"perk": 9111, "var1": 542, "var2": 240, "var3": 0}, {"perk": 9104, "var1": 10, "var2": 0, "var3": 0}, {"perk": 8299, "var1": 441, "var2": 0, "var3": 0}], "style": 8000}, {"description": "subStyle", "selections": [{"perk": 8304, "var1": 8, "var2": 1, "var3": 5}, {"perk": 8347, "var1": 0, "var2": 0, "var3": 0}], "style": 8300}]}, "physicalDamageDealt": 55826, "physicalDamageDealtToChampions": 5497, "physicalDamageTaken": 23854, "placement": 0, "playerAugment1": 0, "playerAugment2": 0, "playerAugment3": 0, "playerAugment4": 0, "playerAugment5": 0, "playerAugment6": 0, "playerSubteamId": 0, "profileIcon": 6096, "pushPings": 0, "puuid": "luVFxwDTJizvvnw-GXXpjMUBlp9CxoA9s144AOkyTL8wrHGCBdl8pZ48IRJW3vW1GeIuhufaG7QtmA", "quadraKills": 0, "retreatPings": 0, "riotIdGameName": "Drake 53", "riotIdTagline": "NA1", "role": "NONE", "sightWardsBoughtInGame": 0, "spell1Casts": 67, "spell2Casts": 3, "spell3Casts": 29, "spell4Casts": 5, "subteamPlacement": 0, "summoner1Casts": 3, "summoner1Id": 4, "summoner2Casts": 10, "summoner2Id": 11, "summonerId": "aZtKCXzJ2BvxCpl5DMlncy-Dnn1PIInnl8mtQann6yrDd_ZuP_6kB6y6PQ", "summonerLevel": 92, "summonerName": "", "teamEarlySurrendered": false, "teamId": 200, "teamPosition": "JUNGLE", "timeCCingOthers": 25, "timePlayed": 1259, "totalAllyJungleMinionsKilled": 68, "totalDamageDealt": 114167, "totalDamageDealtToChampions": 11769, "totalDamageShieldedOnTeammates": 0, "totalDamageTaken": 31790, "totalEnemyJungleMinionsKilled": 4, "totalHeal": 15862, "totalHealsOnTeammates": 0, "totalMinionsKilled": 9, "totalTimeCCDealt": 149, "totalTimeSpentDead": 179, "totalUnitsHealed": 1, "tripleKills": 0, "trueDamageDealt": 32598, "trueDamageDealtToChampions": 392, "trueDamageTaken": 2578, "turretKills": 0, "turretTakedowns": 0, "turretsLost": 5, "unrealKills": 0, "visionClearedPings": 0, "visionScore": 6, "visionWardsBoughtInGame": 0, "wardsKilled": 0, "wardsPlaced": 5, "win": false}, {"PlayerScore0": 0, "PlayerScore1": 0, "PlayerScore10": 0, "PlayerScore11": 0, "PlayerScore2": 0, "PlayerScore3": 0, "PlayerScore4": 0, "PlayerScore5": 0, "PlayerScore6": 0, "PlayerScore7": 0, "PlayerScore8": 0, "PlayerScore9": 0, "allInPings": 0, "assistMePings": 0, "assists": 5, "baronKills": 0, "basicPings": 0, "challenges": {"12AssistStreakCount": 0, "HealFromMapSources": 0, "InfernalScalePickup": 0, "SWARM_DefeatAatrox": 0, "SWARM_DefeatBriar": 0, "SWARM_DefeatMiniBosses": 0, "SWARM_EvolveWeapon": 0, "SWARM_Have3Passives": 0, "SWARM_KillEnemy": 0, "SWARM_PickupGold": 0, "SWARM_ReachLevel50": 0, "SWARM_Survive15Min": 0, "SWARM_WinWith5EvolvedWeapons": 0, "abilityUses": 148, "acesBefore15Minutes": 0, "alliedJungleMonsterKills": 0, "baronTakedowns": 0, "blastConeOppositeOpponentCount": 0, "bountyGold": 180.9012451171875, "buffsStolen": 0, "completeSupportQuestInTime": 0, "controlWardsPlaced": 0, "damagePerMinute": 630.9212093336316, "damageTakenOnTeamPercentage": 0.15541498626642447, "dancedWithRiftHerald": 0, "deathsByEnemyChamps": 6, "dodgeSkillShotsSmallWindow": 0, "doubleAces": 0, "dragonTakedowns": 0, "earlyLaningPhaseGoldExpAdvantage": 0, "effectiveHealAndShielding": 0, "elderDragonKillsWithOpposingSoul": 0, "elderDragonMultikills": 0, "enemyChampionImmobilizations": 11, "enemyJungleMonsterKills": 0, "epicMonsterKillsNearEnemyJungler": 0, "epicMonsterKillsWithin30SecondsOfSpawn": 0, "epicMonsterSteals": 0, "epicMonsterStolenWithoutSmite": 0, "firstTurretKilled": 0, "fistBumpParticipation": 0, "flawlessAces": 0, "fullTeamTakedown": 0, "gameLength": 1259.316040521, "getTakedownsInAllLanesEarlyJungleAsLaner": 0, "goldPerMinute": 328.7761241441089, "hadOpenNexus": 0, "immobilizeAndKillWithAlly": 4, "initialBuffCount": 0, "initialCrabCount": 0, "jungleCsBefore10Minutes": 0, "junglerTakedownsNearDamagedEpicMonster": 0, "kTurretsDestroyedBeforePlatesFall": 0, "kda": 1.3333333333333333, "killAfterHiddenWithAlly": 0, "killParticipation": 0.32, "killedChampTookFullTeamDamageSurvived": 0, "killingSprees": 0, "killsNearEnemyTurret": 3, "killsOnOtherLanesEarlyJungleAsLaner": 0, "killsOnRecentlyHealedByAramPack": 0, "killsUnderOwnTurret": 0, "killsWithHelpFromEpicMonster": 0, "knockEnemyIntoTeamAndKill": 0, "landSkillShotsEarlyGame": 2, "laneMinionsFirst10Minutes": 44, "laningPhaseGoldExpAdvantage": 0, "legendaryCount": 0, "legendaryItemUsed": [6655], "lostAnInhibitor": 0, "maxCsAdvantageOnLaneOpponent": 2, "maxKillDeficit": 0, "maxLevelLeadLaneOpponent": 1, "mejaisFullStackInTime": 0, "moreEnemyJungleThanOpponent": 0, "multiKillOneSpell": 0, "multiTurretRiftHeraldCount": 0, "multikills": 0, "multikillsAfterAggressiveFlash": 0, "outerTurretExecutesBefore10Minutes": 0, "outnumberedKills": 0, "outnumberedNexusKill": 0, "perfectDragonSoulsTaken": 0, "perfectGame": 0, "pickKillWithAlly": 6, "playedChampSelectPosition": 1, "poroExplosions": 0, "quickCleanse": 0, "quickFirstTurret": 0, "quickSoloKills": 0, "riftHeraldTakedowns": 0, "saveAllyFromDeath": 0, "scuttleCrabKills": 0, "skillshotsDodged": 44, "skillshotsHit": 20, "snowballsHit": 0, "soloBaronKills": 0, "soloKills": 1, "stealthWardsPlaced": 3, "survivedSingleDigitHpCount": 0, "survivedThreeImmobilizesInFight": 0, "takedownOnFirstTurret": 0, "takedowns": 8, "takedownsAfterGainingLevelAdvantage": 0, "takedownsBeforeJungleMinionSpawn": 0, "takedownsFirstXMinutes": 3, "takedownsInAlcove": 0, "takedownsInEnemyFountain": 0, "teamBaronKills": 0, "teamDamagePercentage": 0.21485838625027004, "teamElderDragonKills": 0, "teamRiftHeraldKills": 0, "tookLargeDamageSurvived": 0, "turretPlatesTaken": 2, "turretTakedowns": 0, "turretsTakenWithRiftHerald": 0, "twentyMinionsIn3SecondsCount": 0, "twoWardsOneSweeperCount": 0, "unseenRecalls": 0, "visionScoreAdvantageLaneOpponent": -0.6809061765670776, "visionScorePerMinute": 0.22980691798417158, "voidMonsterKill": 0, "wardTakedowns": 0, "wardTakedownsBefore20M": 0, "wardsGuarded": 0}, "champExperience": 9551, "champLevel": 12, "championId": 101, "championName": "Xerath", "championTransform": 0, "commandPings": 2, "consumablesPurchased": 2, "damageDealtToBuildings": 1421, "damageDealtToObjectives": 1764, "damageDealtToTurrets": 1421, "damageSelfMitigated": 5121, "dangerPings": 0, "deaths": 6, "detectorWardsPlaced": 0, "doubleKills": 0, "dragonKills": 0, "eligibleForProgression": true, "enemyMissingPings": 3, "enemyVisionPings": 0, "firstBloodAssist": false, "firstBloodKill": false, "firstTowerAssist": false, "firstTowerKill": false, "gameEndedInEarlySurrender": false, "gameEndedInSurrender": true, "getBackPings": 0, "goldEarned": 6900, "goldSpent": 6650, "holdPings": 0, "individualPosition": "MIDDLE", "inhibitorKills": 0, "inhibitorTakedowns": 0, "inhibitorsLost": 0, "item0": 1056, "item1": 6655, "item2": 3020, "item3": 3145, "item4": 1058, "item5": 0, "item6": 3340, "itemsPurchased": 14, "killingSprees": 0, "kills": 3, "lane": "MIDDLE", "largestCriticalStrike": 0, "largestKillingSpree": 0, "largestMultiKill": 1, "longestTimeSpentLiving": 499, "magicDamageDealt": 55038, "magicDamageDealtToChampions": 12511, "magicDamageTaken": 6174, "missions": {"playerScore0": 0, "playerScore1": 0, "playerScore2": 0, "playerScore3": 0, "playerScore4": 0, "playerScore5": 0, "playerScore6": 0, "playerScore7": 0, "playerScore8": 0, "playerScore9": 0, "playerScore10": 0, "playerScore11": 0}, "needVisionPings": 0, "neutralMinionsKilled": 0, "nexusKills": 0, "nexusLost": 1, "nexusTakedowns": 0, "objectivesStolen": 0, "objectivesStolenAssists": 0, "onMyWayPings": 0, "participantId": 8, "pentaKills": 0, "perks": {"statPerks": {"defense": 5001, "flex": 5008, "offense": 5008}, "styles": [{"description": "primaryStyle", "selections": [{"perk": 8229, "var1": 1040, "var2": 0, "var3": 0}, {"perk": 8226, "var1": 250, "var2": 398, "var3": 0}, {"perk": 8210, "var1": 9, "var2": 0, "var3": 0}, {"perk": 8237, "var1": 434, "var2": 0, "var3": 0}], "style": 8200}, {"description": "subStyle", "selections": [{"perk": 8014, "var1": 347, "var2": 0, "var3": 0}, {"perk": 8009, "var1": 1912, "var2": 0, "var3": 0}], "style": 8000}]}, "physicalDamageDealt": 5673, "physicalDamageDealtToChampions": 731, "physicalDamageTaken": 6451, "placement": 0, "playerAugment1": 0, "playerAugment2": 0, "playerAugment3": 0, "playerAugment4": 0, "playerAugment5": 0, "playerAugment6": 0, "playerSubteamId": 0, "profileIcon": 6497, "pushPings": 0, "puuid": "DcfR8ofB2DhC8hVsNS9pGhYc6su48tCFKJKnc3qcwWp_1blbAhY5xNJxK8zSeRy41c-e6XicWbWo_Q", "quadraKills": 0, "retreatPings": 0, "riotIdGameName": "Jerzy", "riotIdTagline": "1234", "role": "SOLO", "sightWardsBoughtInGame": 0, "spell1Casts": 64, "spell2Casts": 33, "spell3Casts": 26, "spell4Casts": 25, "subteamPlacement": 0, "summoner1Casts": 3, "summoner1Id": 4, "summoner2Casts": 3, "summoner2Id": 12, "summonerId": "jQmVB49_vZu-g4JsjQq5AP_sdttMWrX3HkIPjjP7xJ_AC5g", "summonerLevel": 119, "summonerName": "", "teamEarlySurrendered": false, "teamId": 200, "teamPosition": "MIDDLE", "timeCCingOthers": 23, "timePlayed": 1259, "totalAllyJungleMinionsKilled": 0, "totalDamageDealt": 63252, "totalDamageDealtToChampions": 13242, "totalDamageShieldedOnTeammates": 0, "totalDamageTaken": 14797, "totalEnemyJungleMinionsKilled": 0, "totalHeal": 1231, "totalHealsOnTeammates": 0, "totalMinionsKilled": 95, "totalTimeCCDealt": 137, "totalTimeSpentDead": 156, "totalUnitsHealed": 1, "tripleKills": 0, "trueDamageDealt": 2541, "trueDamageDealtToChampions": 0, "trueDamageTaken": 2172, "turretKills": 0, "turretTakedowns": 0, "turretsLost": 5, "unrealKills": 0, "visionClearedPings": 0, "visionScore": 4, "visionWardsBoughtInGame": 0, "wardsKilled": 0, "wardsPlaced": 3, "win": false}, {"PlayerScore0": 0, "PlayerScore1": 0, "PlayerScore10": 0, "PlayerScore11": 0, "PlayerScore2": 0, "PlayerScore3": 0, "PlayerScore4": 0, "PlayerScore5": 0, "PlayerScore6": 0, "PlayerScore7": 0, "PlayerScore8": 0, "PlayerScore9": 0, "allInPings": 0, "assistMePings": 0, "assists": 4, "baronKills": 0, "basicPings": 0, "challenges": {"12AssistStreakCount": 0, "HealFromMapSources": 0, "InfernalScalePickup": 0, "SWARM_DefeatAatrox": 0, "SWARM_DefeatBriar": 0, "SWARM_DefeatMiniBosses": 0, "SWARM_EvolveWeapon": 0, "SWARM_Have3Passives": 0, "SWARM_KillEnemy": 0, "SWARM_PickupGold": 0, "SWARM_ReachLevel50": 0, "SWARM_Survive15Min": 0, "SWARM_WinWith5EvolvedWeapons": 0, "abilityUses": 80, "acesBefore15Minutes": 0, "alliedJungleMonsterKills": 0, "baronTakedowns": 0, "blastConeOppositeOpponentCount": 0, "bountyGold": 171.42666625976562, "buffsStolen": 0, "completeSupportQuestInTime": 0, "controlWardsPlaced": 0, "damagePerMinute": 478.69548775111264, "damageTakenOnTeamPercentage": 0.15106789502271822, "dancedWithRiftHerald": 0, "deathsByEnemyChamps": 9, "dodgeSkillShotsSmallWindow": 0, "doubleAces": 0, "dragonTakedowns": 0, "earlyLaningPhaseGoldExpAdvantage": 0, "effectiveHealAndShielding": 0, "elderDragonKillsWithOpposingSoul": 0, "elderDragonMultikills": 0, "enemyChampionImmobilizations": 0, "enemyJungleMonsterKills": 0, "epicMonsterKillsNearEnemyJungler": 0, "epicMonsterKillsWithin30SecondsOfSpawn": 0, "epicMonsterSteals": 0, "epicMonsterStolenWithoutSmite": 0, "firstTurretKilled": 0, "fistBumpParticipation": 0, "flawlessAces": 0, "fullTeamTakedown": 0, "gameLength": 1259.316040521, "getTakedownsInAllLanesEarlyJungleAsLaner": 0, "goldPerMinute": 387.00862705867587, "hadOpenNexus": 0, "immobilizeAndKillWithAlly": 0, "initialBuffCount": 0, "initialCrabCount": 0, "jungleCsBefore10Minutes": 0, "junglerTakedownsNearDamagedEpicMonster": 1, "kTurretsDestroyedBeforePlatesFall": 0, "kda": 1.1111111111111112, "killAfterHiddenWithAlly": 1, "killParticipation": 0.4, "killedChampTookFullTeamDamageSurvived": 0, "killingSprees": 0, "killsNearEnemyTurret": 3, "killsOnOtherLanesEarlyJungleAsLaner": 0, "killsOnRecentlyHealedByAramPack": 0, "killsUnderOwnTurret": 1, "killsWithHelpFromEpicMonster": 1, "knockEnemyIntoTeamAndKill": 0, "landSkillShotsEarlyGame": 2, "laneMinionsFirst10Minutes": 31, "laningPhaseGoldExpAdvantage": 0, "legendaryCount": 0, "legendaryItemUsed": [6676, 3031], "lostAnInhibitor": 0, "maxCsAdvantageOnLaneOpponent": 7, "maxKillDeficit": 0, "maxLevelLeadLaneOpponent": 1, "mejaisFullStackInTime": 0, "moreEnemyJungleThanOpponent": 0, "multiKillOneSpell": 0, "multiTurretRiftHeraldCount": 0, "multikills": 0, "multikillsAfterAggressiveFlash": 0, "outerTurretExecutesBefore10Minutes": 0, "outnumberedKills": 0, "outnumberedNexusKill": 0, "perfectDragonSoulsTaken": 0, "perfectGame": 0, "pickKillWithAlly": 8, "playedChampSelectPosition": 1, "poroExplosions": 0, "quickCleanse": 0, "quickFirstTurret": 0, "quickSoloKills": 0, "riftHeraldTakedowns": 0, "saveAllyFromDeath": 0, "scuttleCrabKills": 0, "skillshotsDodged": 10, "skillshotsHit": 10, "snowballsHit": 0, "soloBaronKills": 0, "soloKills": 1, "stealthWardsPlaced": 2, "survivedSingleDigitHpCount": 0, "survivedThreeImmobilizesInFight": 0, "takedownOnFirstTurret": 0, "takedowns": 10, "takedownsAfterGainingLevelAdvantage": 0, "takedownsBeforeJungleMinionSpawn": 0, "takedownsFirstXMinutes": 6, "takedownsInAlcove": 0, "takedownsInEnemyFountain": 0, "teamBaronKills": 0, "teamDamagePercentage": 0.16301835868241019, "teamElderDragonKills": 0, "teamRiftHeraldKills": 0, "tookLargeDamageSurvived": 0, "turretPlatesTaken": 2, "turretTakedowns": 1, "turretsTakenWithRiftHerald": 0, "twentyMinionsIn3SecondsCount": 0, "twoWardsOneSweeperCount": 0, "unseenRecalls": 0, "visionScoreAdvantageLaneOpponent": -0.7802141904830933, "visionScorePerMinute": 0.15011014372012418, "voidMonsterKill": 0, "wardTakedowns": 0, "wardTakedownsBefore20M": 0, "wardsGuarded": 0}, "champExperience": 8216, "champLevel": 11, "championId": 29, "championName": "Twitch", "championTransform": 0, "commandPings": 0, "consumablesPurchased": 1, "damageDealtToBuildings": 2382, "damageDealtToObjectives": 2642, "damageDealtToTurrets": 2382, "damageSelfMitigated": 7100, "dangerPings": 0, "deaths": 9, "detectorWardsPlaced": 0, "doubleKills": 0, "dragonKills": 0, "eligibleForProgression": true, "enemyMissingPings": 0, "enemyVisionPings": 0, "firstBloodAssist": true, "firstBloodKill": false, "firstTowerAssist": false, "firstTowerKill": false, "gameEndedInEarlySurrender": false, "gameEndedInSurrender": true, "getBackPings": 0, "goldEarned": 8122, "goldSpent": 6950, "holdPings": 0, "individualPosition": "BOTTOM", "inhibitorKills": 0, "inhibitorTakedowns": 0, "inhibitorsLost": 0, "item0": 1055, "item1": 6676, "item2": 3031, "item3": 0, "item4": 0, "item5": 0, "item6": 3340, "itemsPurchased": 11, "killingSprees": 2, "kills": 6, "lane": "BOTTOM", "largestCriticalStrike": 485, "largestKillingSpree": 2, "largestMultiKill": 1, "longestTimeSpentLiving": 292, "magicDamageDealt": 0, "magicDamageDealtToChampions": 0, "magicDamageTaken": 1671, "missions": {"playerScore0": 0, "playerScore1": 0, "playerScore2": 0, "playerScore3": 0, "playerScore4": 0, "playerScore5": 0, "playerScore6": 0, "playerScore7": 0, "playerScore8": 0, "playerScore9": 0, "playerScore10": 0, "playerScore11": 0}, "needVisionPings": 0, "neutralMinionsKilled": 0, "nexusKills": 0, "nexusLost": 1, "nexusTakedowns": 0, "objectivesStolen": 0, "objectivesStolenAssists": 0, "onMyWayPings": 0, "participantId": 9, "pentaKills": 0, "perks": {"statPerks": {"defense": 5011, "flex": 5008, "offense": 5005}, "styles": [{"description": "primaryStyle", "selections": [{"perk": 8008, "var1": 82, "var2": 82, "var3": 0}, {"perk": 9111, "var1": 428, "var2": 200, "var3": 0}, {"perk": 9104, "var1": 18, "var2": 0, "var3": 0}, {"perk": 8014, "var1": 295, "var2": 0, "var3": 0}], "style": 8000}, {"description": "subStyle", "selections": [{"perk": 8143, "var1": 614, "var2": 0, "var3": 0}, {"perk": 8135, "var1": 320, "var2": 4, "var3": 0}], "style": 8100}]}, "physicalDamageDealt": 42058, "physicalDamageDealtToChampions": 7564, "physicalDamageTaken": 11210, "placement": 0, "playerAugment1": 0, "playerAugment2": 0, "playerAugment3": 0, "playerAugment4": 0, "playerAugment5": 0, "playerAugment6": 0, "playerSubteamId": 0, "profileIcon": 2092, "pushPings": 0, "puuid": "ofN36YCj4-docqwVmn3DZ7LTIoh0yEpavZlULCidUK_EVu4SnSd2BcGwL7CzPEU-z2pfVQfnvBqPkg", "quadraKills": 0, "retreatPings": 0, "riotIdGameName": "tD Cyber", "riotIdTagline": "7175", "role": "CARRY", "sightWardsBoughtInGame": 0, "spell1Casts": 22, "spell2Casts": 28, "spell3Casts": 24, "spell4Casts": 6, "subteamPlacement": 0, "summoner1Casts": 5, "summoner1Id": 21, "summoner2Casts": 4, "summoner2Id": 4, "summonerId": "KEzURWbU6jy9iRWpM4rFjG4aJ1QMO2bMSxgJE14D5ESWXHVMpIOdTynyhw", "summonerLevel": 85, "summonerName": "", "teamEarlySurrendered": false, "teamId": 200, "teamPosition": "BOTTOM", "timeCCingOthers": 8, "timePlayed": 1259, "totalAllyJungleMinionsKilled": 0, "totalDamageDealt": 48480, "totalDamageDealtToChampions": 10047, "totalDamageShieldedOnTeammates": 0, "totalDamageTaken": 14384, "totalEnemyJungleMinionsKilled": 0, "totalHeal": 946, "totalHealsOnTeammates": 0, "totalMinionsKilled": 76, "totalTimeCCDealt": 205, "totalTimeSpentDead": 165, "totalUnitsHealed": 1, "tripleKills": 0, "trueDamageDealt": 6421, "trueDamageDealtToChampions": 2482, "trueDamageTaken": 1502, "turretKills": 1, "turretTakedowns": 1, "turretsLost": 5, "unrealKills": 0, "visionClearedPings": 0, "visionScore": 3, "visionWardsBoughtInGame": 0, "wardsKilled": 0, "wardsPlaced": 2, "win": false}, {"PlayerScore0": 0, "PlayerScore1": 0, "PlayerScore10": 0, "PlayerScore11": 0, "PlayerScore2": 0, "PlayerScore3": 0, "PlayerScore4": 0, "PlayerScore5": 0, "PlayerScore6": 0, "PlayerScore7": 0, "PlayerScore8": 0, "PlayerScore9": 0, "allInPings": 0, "assistMePings": 0, "assists": 6, "baronKills": 0, "basicPings": 0, "challenges": {"12AssistStreakCount": 0, "HealFromMapSources": 202.3000030517578, "InfernalScalePickup": 0, "SWARM_DefeatAatrox": 0, "SWARM_DefeatBriar": 0, "SWARM_DefeatMiniBosses": 0, "SWARM_EvolveWeapon": 0, "SWARM_Have3Passives": 0, "SWARM_KillEnemy": 0, "SWARM_PickupGold": 0, "SWARM_ReachLevel50": 0, "SWARM_Survive15Min": 0, "SWARM_WinWith5EvolvedWeapons": 0, "abilityUses": 70, "acesBefore15Minutes": 0, "alliedJungleMonsterKills": 0, "baronTakedowns": 0, "blastConeOppositeOpponentCount": 0, "bountyGold": 642.8561401367188, "buffsStolen": 0, "completeSupportQuestInTime": 1, "controlWardsPlaced": 1, "damagePerMinute": 396.79509639277666, "damageTakenOnTeamPercentage": 0.18824561994236994, "dancedWithRiftHerald": 0, "deathsByEnemyChamps": 8, "dodgeSkillShotsSmallWindow": 0, "doubleAces": 0, "dragonTakedowns": 0, "earlyLaningPhaseGoldExpAdvantage": 0, "effectiveHealAndShielding": 0, "elderDragonKillsWithOpposingSoul": 0, "elderDragonMultikills": 0, "enemyChampionImmobilizations": 83, "enemyJungleMonsterKills": 0, "epicMonsterKillsNearEnemyJungler": 0, "epicMonsterKillsWithin30SecondsOfSpawn": 0, "epicMonsterSteals": 0, "epicMonsterStolenWithoutSmite": 0, "firstTurretKilled": 0, "fistBumpParticipation": 0, "flawlessAces": 0, "fullTeamTakedown": 0, "gameLength": 1259.316040521, "getTakedownsInAllLanesEarlyJungleAsLaner": 0, "goldPerMinute": 351.0269021991215, "hadOpenNexus": 0, "highestCrowdControlScore": 1, "highestWardKills": 1, "immobilizeAndKillWithAlly": 7, "initialBuffCount": 0, "initialCrabCount": 0, "jungleCsBefore10Minutes": 0, "junglerTakedownsNearDamagedEpicMonster": 0, "kTurretsDestroyedBeforePlatesFall": 0, "kda": 1.375, "killAfterHiddenWithAlly": 0, "killParticipation": 0.44, "killedChampTookFullTeamDamageSurvived": 0, "killingSprees": 0, "killsNearEnemyTurret": 1, "killsOnOtherLanesEarlyJungleAsLaner": 0, "killsOnRecentlyHealedByAramPack": 0, "killsUnderOwnTurret": 2, "killsWithHelpFromEpicMonster": 1, "knockEnemyIntoTeamAndKill": 6, "landSkillShotsEarlyGame": 5, "laneMinionsFirst10Minutes": 5, "laningPhaseGoldExpAdvantage": 0, "legendaryCount": 0, "legendaryItemUsed": [3190, 3876, 3075], "lostAnInhibitor": 0, "maxCsAdvantageOnLaneOpponent": 6, "maxKillDeficit": 0, "maxLevelLeadLaneOpponent": 1, "mejaisFullStackInTime": 0, "moreEnemyJungleThanOpponent": 0, "multiKillOneSpell": 0, "multiTurretRiftHeraldCount": 0, "multikills": 0, "multikillsAfterAggressiveFlash": 0, "outerTurretExecutesBefore10Minutes": 0, "outnumberedKills": 1, "outnumberedNexusKill": 0, "perfectDragonSoulsTaken": 0, "perfectGame": 0, "pickKillWithAlly": 9, "playedChampSelectPosition": 1, "poroExplosions": 0, "quickCleanse": 0, "quickFirstTurret": 0, "quickSoloKills": 0, "riftHeraldTakedowns": 0, "saveAllyFromDeath": 0, "scuttleCrabKills": 0, "skillshotsDodged": 20, "skillshotsHit": 15, "snowballsHit": 0, "soloBaronKills": 0, "soloKills": 1, "stealthWardsPlaced": 11, "survivedSingleDigitHpCount": 0, "survivedThreeImmobilizesInFight": 0, "takedownOnFirstTurret": 0, "takedowns": 11, "takedownsAfterGainingLevelAdvantage": 0, "takedownsBeforeJungleMinionSpawn": 0, "takedownsFirstXMinutes": 6, "takedownsInAlcove": 0, "takedownsInEnemyFountain": 0, "teamBaronKills": 0, "teamDamagePercentage": 0.135127418165284, "teamElderDragonKills": 0, "teamRiftHeraldKills": 0, "tookLargeDamageSurvived": 0, "turretPlatesTaken": 0, "turretTakedowns": 0, "turretsTakenWithRiftHerald": 0, "twentyMinionsIn3SecondsCount": 0, "twoWardsOneSweeperCount": 0, "unseenRecalls": 0, "visionScoreAdvantageLaneOpponent": 2.0745487213134766, "visionScorePerMinute": 1.9298762331926003, "voidMonsterKill": 0, "wardTakedowns": 5, "wardTakedownsBefore20M": 5, "wardsGuarded": 0}, "champExperience": 6991, "champLevel": 10, "championId": 111, "championName": "Nautilus", "championTransform": 0, "commandPings": 0, "consumablesPurchased": 3, "damageDealtToBuildings": 0, "damageDealtToObjectives": 395, "damageDealtToTurrets": 0, "damageSelfMitigated": 20257, "dangerPings": 0, "deaths": 8, "detectorWardsPlaced": 1, "doubleKills": 0, "dragonKills": 0, "eligibleForProgression": true, "enemyMissingPings": 1, "enemyVisionPings": 1, "firstBloodAssist": false, "firstBloodKill": true, "firstTowerAssist": false, "firstTowerKill": false, "gameEndedInEarlySurrender": false, "gameEndedInSurrender": true, "getBackPings": 0, "goldEarned": 7367, "goldSpent": 7075, "holdPings": 0, "individualPosition": "UTILITY", "inhibitorKills": 0, "inhibitorTakedowns": 0, "inhibitorsLost": 0, "item0": 3876, "item1": 3047, "item2": 3190, "item3": 3075, "item4": 1028, "item5": 2022, "item6": 3364, "itemsPurchased": 19, "killingSprees": 2, "kills": 5, "lane": "BOTTOM", "largestCriticalStrike": 0, "largestKillingSpree": 2, "largestMultiKill": 1, "longestTimeSpentLiving": 304, "magicDamageDealt": 9675, "magicDamageDealtToChampions": 4761, "magicDamageTaken": 3209, "missions": {"playerScore0": 0, "playerScore1": 0, "playerScore2": 0, "playerScore3": 0, "playerScore4": 0, "playerScore5": 0, "playerScore6": 0, "playerScore7": 0, "playerScore8": 0, "playerScore9": 0, "playerScore10": 0, "playerScore11": 0}, "needVisionPings": 0, "neutralMinionsKilled": 0, "nexusKills": 0, "nexusLost": 1, "nexusTakedowns": 0, "objectivesStolen": 0, "objectivesStolenAssists": 0, "onMyWayPings": 0, "participantId": 10, "pentaKills": 0, "perks": {"statPerks": {"defense": 5001, "flex": 5001, "offense": 5007}, "styles": [{"description": "primaryStyle", "selections": [{"perk": 8439, "var1": 540, "var2": 492, "var3": 0}, {"perk": 8401, "var1": 305, "var2": 0, "var3": 0}, {"perk": 8473, "var1": 468, "var2": 0, "var3": 0}, {"perk": 8242, "var1": 92, "var2": 0, "var3": 0}], "style": 8400}, {"description": "subStyle", "selections": [{"perk": 8345, "var1": 3, "var2": 0, "var3": 239}, {"perk": 8347, "var1": 0, "var2": 0, "var3": 0}], "style": 8300}]}, "physicalDamageDealt": 4613, "physicalDamageDealtToChampions": 2848, "physicalDamageTaken": 10988, "placement": 0, "playerAugment1": 0, "playerAugment2": 0, "playerAugment3": 0, "playerAugment4": 0, "playerAugment5": 0, "playerAugment6": 0, "playerSubteamId": 0, "profileIcon": 3184, "pushPings": 0, "puuid": "kUq1GpPXoC7lHnLvvgPdt3O0aiB6Z2UI-DKMaNmVyDHD3GvA43qKgf-toDHJYZCH3-tIoGYuFSSBcg", "quadraKills": 0, "retreatPings": 0, "riotIdGameName": "allstarjs", "riotIdTagline": "NA1", "role": "SUPPORT", "sightWardsBoughtInGame": 0, "spell1Casts": 26, "spell2Casts": 16, "spell3Casts": 24, "spell4Casts": 4, "subteamPlacement": 0, "summoner1Casts": 2, "summoner1Id": 4, "summoner2Casts": 5, "summoner2Id": 14, "summonerId": "xfOk1I7xOTaMIwMtnuS54JPFUWLY0Q_NmpL6X1bUYGzHK8M", "summonerLevel": 106, "summonerName": "", "teamEarlySurrendered": false, "teamId": 200, "teamPosition": "UTILITY", "timeCCingOthers": 52, "timePlayed": 1259, "totalAllyJungleMinionsKilled": 0, "totalDamageDealt": 15826, "totalDamageDealtToChampions": 8328, "totalDamageShieldedOnTeammates": 0, "totalDamageTaken": 17923, "totalEnemyJungleMinionsKilled": 0, "totalHeal": 991, "totalHealsOnTeammates": 0, "totalMinionsKilled": 19, "totalTimeCCDealt": 228, "totalTimeSpentDead": 159, "totalUnitsHealed": 1, "tripleKills": 0, "trueDamageDealt": 1537, "trueDamageDealtToChampions": 718, "trueDamageTaken": 3725, "turretKills": 0, "turretTakedowns": 0, "turretsLost": 5, "unrealKills": 0, "visionClearedPings": 0, "visionScore": 40, "visionWardsBoughtInGame": 1, "wardsKilled": 5, "wardsPlaced": 12, "win": false}], "platformId": "NA1", "queueId": 400, "teams": [{"bans": [{"championId": 48, "pickTurn": 1}, {"championId": 555, "pickTurn": 2}, {"championId": 17, "pickTurn": 3}, {"championId": -1, "pickTurn": 4}, {"championId": 90, "pickTurn": 5}], "feats": {"EPIC_MONSTER_KILL": {"featState": 1}, "FIRST_BLOOD": {"featState": 3}, "FIRST_TURRET": {"featState": 1}}, "objectives": {"atakhan": {"first": false, "kills": 0}, "baron": {"first": false, "kills": 0}, "champion": {"first": false, "kills": 36}, "dragon": {"first": false, "kills": 2}, "horde": {"first": false, "kills": 0}, "inhibitor": {"first": false, "kills": 0}, "riftHerald": {"first": true, "kills": 1}, "tower": {"first": true, "kills": 5}}, "teamId": 100, "win": true}, {"bans": [{"championId": 22, "pickTurn": 6}, {"championId": 63, "pickTurn": 7}, {"championId": 17, "pickTurn": 8}, {"championId": 223, "pickTurn": 9}, {"championId": 875, "pickTurn": 10}], "feats": {"EPIC_MONSTER_KILL": {"featState": 2}, "FIRST_BLOOD": {"featState": 1001}, "FIRST_TURRET": {"featState": 1001}}, "objectives": {"atakhan": {"first": false, "kills": 0}, "baron": {"first": false, "kills": 0}, "champion": {"first": true, "kills": 25}, "dragon": {"first": true, "kills": 1}, "horde": {"first": true, "kills": 3}, "inhibitor": {"first": false, "kills": 0}, "riftHerald": {"first": false, "kills": 0}, "tower": {"first": false, "kills": 2}}, "teamId": 200, "win": false}], "tournamentCode": ""}}