{"metadata": {"dataVersion": "2", "matchId": "NA1_5390825401", "participants": ["O9S_iyDiYgyTWJts1-4Fx5qEYFoklULyjJnPrBD8C8pia0OQFTOJJMq085-zEYHZda7LOxSGsOSFyg", "6UWsWalDzFO_iBlraHaY75eyfC3KTM8fXJ0rjGVLzmx-L_sOHO6IDZIGFhp1lixHS8n4uOShaG-UCA", "6Lx0jlEb7h64r-BpEc22J40z1Y-jnN4Dbq_ww8hfUxTQ2XHVH0w0Y-pxCj7Pazn5IFfF_BeD2g1zYA", "HTLcVh5Um6pqIx8c4QBuhXUcXU9_jpyADAHMRPGhFUSesU6atj1L_GLzbVRcuk7rCU_7meKZDKYkow", "bz6DHDAyj1fPX4w60CMxpr9hQLgYlXssNFONGaCjjGyVX5zqBVroZuYW3f---cQm2xvuYEN1Y_pidQ", "SqzFuirWbgPsZgSxmRSbu4rrIHdYkxNlqR5Q3LlzAOifmXiZEhY1Zc5qRR19XGJSxLsenhc8Q2PipA", "ynP1c9S8D0rrvUmHPypxN3mMXUtf2UzVICmqRUxkwcvu5yrNeoecRLQ_qJzsW3bhdZDa-r3aG0z_CQ", "MQXYnF9l3o09tQMyvCjN0v_PrKbFcu7uihOCC6_QaGF1njmoXqG4FxvxSn4ezDTgVS2BnWNUmQspdw", "SBha5vhP-jFCgA-Gn_IQUogYRES3fPuD72gGOvRfwn33I1IjGByKnx0RXfFXB6zNMYMG5UcqWwhFbg", "xyU4fhtryInp_cdKIJZ08pkgQDNXZcE7zJ3IY_oI66IAn7xFfwky0vRcqc-H2tV4q3CCQiqXzGwCCA"]}, "info": {"endOfGameResult": "GameComplete", "gameCreation": 1760201406713, "gameDuration": 900, "gameEndTimestamp": 1760202358556, "gameId": 5390825401, "gameMode": "ARAM", "gameModeMutators": ["mapskin_ha_bilgewater"], "gameName": "teambuilder-match-5390825401", "gameStartTimestamp": 1760201458111, "gameType": "MATCHED_GAME", "gameVersion": "15.20.717.2831", "mapId": 12, "participants": [{"PlayerScore0": 0, "PlayerScore1": 0, "PlayerScore10": 0, "PlayerScore11": 0, "PlayerScore2": 0, "PlayerScore3": 0, "PlayerScore4": 0, "PlayerScore5": 0, "PlayerScore6": 0, "PlayerScore7": 0, "PlayerScore8": 0, "PlayerScore9": 0, "allInPings": 0, "assistMePings": 0, "assists": 27, "baronKills": 0, "basicPings": 0, "challenges": {"12AssistStreakCount": 1, "HealFromMapSources": 1094.8900306224823, "InfernalScalePickup": 0, "SWARM_DefeatAatrox": 0, "SWARM_DefeatBriar": 0, "SWARM_DefeatMiniBosses": 0, "SWARM_EvolveWeapon": 0, "SWARM_Have3Passives": 0, "SWARM_KillEnemy": 0, "SWARM_PickupGold": 0, "SWARM_ReachLevel50": 0, "SWARM_Survive15Min": 0, "SWARM_WinWith5EvolvedWeapons": 0, "abilityUses": 150, "acesBefore15Minutes": 0, "alliedJungleMonsterKills": 0, "baronTakedowns": 0, "blastConeOppositeOpponentCount": 0, "bountyGold": 136.1979217529297, "buffsStolen": 0, "completeSupportQuestInTime": 0, "controlWardsPlaced": 0, "damagePerMinute": 761.6512261874298, "damageTakenOnTeamPercentage": 0.12809656492190752, "dancedWithRiftHerald": 0, "deathsByEnemyChamps": 5, "dodgeSkillShotsSmallWindow": 0, "doubleAces": 0, "dragonTakedowns": 0, "effectiveHealAndShielding": 9259.08984375, "elderDragonKillsWithOpposingSoul": 0, "elderDragonMultikills": 0, "enemyChampionImmobilizations": 39, "enemyJungleMonsterKills": 0, "epicMonsterKillsNearEnemyJungler": 0, "epicMonsterKillsWithin30SecondsOfSpawn": 0, "epicMonsterSteals": 0, "epicMonsterStolenWithoutSmite": 0, "firstTurretKilled": 0, "fistBumpParticipation": 0, "flawlessAces": 0, "fullTeamTakedown": 1, "gameLength": 900.7492330140001, "getTakedownsInAllLanesEarlyJungleAsLaner": 0, "goldPerMinute": 650.2212681702576, "hadAfkTeammate": 1, "hadOpenNexus": 0, "immobilizeAndKillWithAlly": 13, "initialBuffCount": 0, "initialCrabCount": 0, "jungleCsBefore10Minutes": 0, "junglerTakedownsNearDamagedEpicMonster": 0, "kTurretsDestroyedBeforePlatesFall": 0, "kda": 6.4, "killAfterHiddenWithAlly": 3, "killParticipation": 0.9142857142857143, "killedChampTookFullTeamDamageSurvived": 0, "killingSprees": 0, "killsNearEnemyTurret": 1, "killsOnOtherLanesEarlyJungleAsLaner": 0, "killsOnRecentlyHealedByAramPack": 1, "killsUnderOwnTurret": 2, "killsWithHelpFromEpicMonster": 0, "knockEnemyIntoTeamAndKill": 0, "landSkillShotsEarlyGame": 18, "laneMinionsFirst10Minutes": 9, "legendaryCount": 0, "legendaryItemUsed": [6617, 4005], "lostAnInhibitor": 0, "maxKillDeficit": 0, "mejaisFullStackInTime": 0, "moreEnemyJungleThanOpponent": 0, "multiKillOneSpell": 0, "multiTurretRiftHeraldCount": 0, "multikills": 0, "multikillsAfterAggressiveFlash": 0, "outerTurretExecutesBefore10Minutes": 0, "outnumberedKills": 2, "outnumberedNexusKill": 0, "perfectDragonSoulsTaken": 0, "perfectGame": 0, "pickKillWithAlly": 22, "poroExplosions": 0, "quickCleanse": 0, "quickFirstTurret": 0, "quickSoloKills": 0, "riftHeraldTakedowns": 0, "saveAllyFromDeath": 2, "scuttleCrabKills": 0, "skillshotsDodged": 13, "skillshotsHit": 37, "snowballsHit": 1, "soloBaronKills": 0, "soloKills": 0, "stealthWardsPlaced": 0, "survivedSingleDigitHpCount": 0, "survivedThreeImmobilizesInFight": 1, "takedownOnFirstTurret": 0, "takedowns": 32, "takedownsAfterGainingLevelAdvantage": 0, "takedownsBeforeJungleMinionSpawn": 2, "takedownsFirstXMinutes": 32, "takedownsInAlcove": 0, "takedownsInEnemyFountain": 0, "teamBaronKills": 0, "teamDamagePercentage": 0.17323574739536018, "teamElderDragonKills": 0, "teamRiftHeraldKills": 0, "tookLargeDamageSurvived": 0, "turretPlatesTaken": 0, "turretTakedowns": 0, "turretsTakenWithRiftHerald": 0, "twentyMinionsIn3SecondsCount": 0, "twoWardsOneSweeperCount": 0, "unseenRecalls": 0, "visionScorePerMinute": 0, "voidMonsterKill": 0, "wardTakedowns": 0, "wardTakedownsBefore20M": 0, "wardsGuarded": 0}, "champExperience": 15103, "champLevel": 16, "championId": 40, "championName": "Janna", "championTransform": 0, "commandPings": 4, "consumablesPurchased": 0, "damageDealtToBuildings": 179, "damageDealtToObjectives": 179, "damageDealtToTurrets": 179, "damageSelfMitigated": 6505, "dangerPings": 0, "deaths": 5, "detectorWardsPlaced": 0, "doubleKills": 0, "dragonKills": 0, "eligibleForProgression": true, "enemyMissingPings": 3, "enemyVisionPings": 0, "firstBloodAssist": true, "firstBloodKill": false, "firstTowerAssist": false, "firstTowerKill": false, "gameEndedInEarlySurrender": false, "gameEndedInSurrender": false, "getBackPings": 0, "goldEarned": 9761, "goldSpent": 7200, "holdPings": 0, "individualPosition": "Invalid", "inhibitorKills": 0, "inhibitorTakedowns": 0, "inhibitorsLost": 1, "item0": 6617, "item1": 3070, "item2": 3158, "item3": 4005, "item4": 3114, "item5": 1026, "item6": 2052, "itemsPurchased": 10, "killingSprees": 1, "kills": 5, "lane": "NONE", "largestCriticalStrike": 0, "largestKillingSpree": 2, "largestMultiKill": 1, "longestTimeSpentLiving": 243, "magicDamageDealt": 21570, "magicDamageDealtToChampions": 10587, "magicDamageTaken": 7798, "missions": {"playerScore0": 0, "playerScore1": 0, "playerScore2": 0, "playerScore3": 0, "playerScore4": 0, "playerScore5": 0, "playerScore6": 0, "playerScore7": 0, "playerScore8": 0, "playerScore9": 0, "playerScore10": 0, "playerScore11": 0}, "needVisionPings": 0, "neutralMinionsKilled": 0, "nexusKills": 0, "nexusLost": 1, "nexusTakedowns": 0, "objectivesStolen": 0, "objectivesStolenAssists": 0, "onMyWayPings": 0, "participantId": 1, "pentaKills": 0, "perks": {"statPerks": {"defense": 5011, "flex": 5008, "offense": 5008}, "styles": [{"description": "primaryStyle", "selections": [{"perk": 8214, "var1": 1353, "var2": 561, "var3": 0}, {"perk": 8224, "var1": 60, "var2": 1019, "var3": 0}, {"perk": 8234, "var1": 4768, "var2": 0, "var3": 0}, {"perk": 8237, "var1": 530, "var2": 0, "var3": 0}], "style": 8200}, {"description": "subStyle", "selections": [{"perk": 8453, "var1": 1037, "var2": 675, "var3": 0}, {"perk": 8429, "var1": 46, "var2": 11, "var3": 9}], "style": 8400}]}, "physicalDamageDealt": 1717, "physicalDamageDealtToChampions": 677, "physicalDamageTaken": 5114, "placement": 0, "playerAugment1": 0, "playerAugment2": 0, "playerAugment3": 0, "playerAugment4": 0, "playerAugment5": 0, "playerAugment6": 0, "playerSubteamId": 0, "profileIcon": 3523, "pushPings": 0, "puuid": "O9S_iyDiYgyTWJts1-4Fx5qEYFoklULyjJnPrBD8C8pia0OQFTOJJMq085-zEYHZda7LOxSGsOSFyg", "quadraKills": 0, "retreatPings": 1, "riotIdGameName": "WhatHappends", "riotIdTagline": "001", "role": "SUPPORT", "sightWardsBoughtInGame": 0, "spell1Casts": 68, "spell2Casts": 42, "spell3Casts": 35, "spell4Casts": 5, "subteamPlacement": 0, "summoner1Casts": 0, "summoner1Id": 4, "summoner2Casts": 4, "summoner2Id": 32, "summonerId": "Rbh8CqiGfYhGIQr8YRkZJdtREzbtuBdA0osmQ2exfVEMpVa7", "summonerLevel": 463, "summonerName": "", "teamEarlySurrendered": false, "teamId": 100, "teamPosition": "", "timeCCingOthers": 46, "timePlayed": 900, "totalAllyJungleMinionsKilled": 0, "totalDamageDealt": 23458, "totalDamageDealtToChampions": 11434, "totalDamageShieldedOnTeammates": 4655, "totalDamageTaken": 13650, "totalEnemyJungleMinionsKilled": 0, "totalHeal": 7597, "totalHealsOnTeammates": 4603, "totalMinionsKilled": 9, "totalTimeCCDealt": 160, "totalTimeSpentDead": 115, "totalUnitsHealed": 13, "tripleKills": 0, "trueDamageDealt": 170, "trueDamageDealtToChampions": 170, "trueDamageTaken": 737, "turretKills": 0, "turretTakedowns": 0, "turretsLost": 4, "unrealKills": 0, "visionClearedPings": 0, "visionScore": 0, "visionWardsBoughtInGame": 0, "wardsKilled": 0, "wardsPlaced": 0, "win": false}, {"PlayerScore0": 0, "PlayerScore1": 0, "PlayerScore10": 0, "PlayerScore11": 0, "PlayerScore2": 0, "PlayerScore3": 0, "PlayerScore4": 0, "PlayerScore5": 0, "PlayerScore6": 0, "PlayerScore7": 0, "PlayerScore8": 0, "PlayerScore9": 0, "allInPings": 0, "assistMePings": 0, "assists": 2, "baronKills": 0, "basicPings": 0, "challenges": {"12AssistStreakCount": 0, "HealFromMapSources": 0, "InfernalScalePickup": 0, "SWARM_DefeatAatrox": 0, "SWARM_DefeatBriar": 0, "SWARM_DefeatMiniBosses": 0, "SWARM_EvolveWeapon": 0, "SWARM_Have3Passives": 0, "SWARM_KillEnemy": 0, "SWARM_PickupGold": 0, "SWARM_ReachLevel50": 0, "SWARM_Survive15Min": 0, "SWARM_WinWith5EvolvedWeapons": 0, "abilityUses": 11, "acesBefore15Minutes": 0, "alliedJungleMonsterKills": 0, "baronTakedowns": 0, "blastConeOppositeOpponentCount": 0, "bountyGold": 0, "buffsStolen": 0, "completeSupportQuestInTime": 0, "controlWardsPlaced": 0, "damagePerMinute": 53.28043345618544, "damageTakenOnTeamPercentage": 0.02368050781728747, "dancedWithRiftHerald": 0, "deathsByEnemyChamps": 1, "dodgeSkillShotsSmallWindow": 0, "doubleAces": 0, "dragonTakedowns": 0, "effectiveHealAndShielding": 11.744110107421875, "elderDragonKillsWithOpposingSoul": 0, "elderDragonMultikills": 0, "enemyChampionImmobilizations": 8, "enemyJungleMonsterKills": 0, "epicMonsterKillsNearEnemyJungler": 0, "epicMonsterKillsWithin30SecondsOfSpawn": 0, "epicMonsterSteals": 0, "epicMonsterStolenWithoutSmite": 0, "firstTurretKilled": 0, "fistBumpParticipation": 0, "flawlessAces": 0, "fullTeamTakedown": 1, "gameLength": 900.7492330140001, "getTakedownsInAllLanesEarlyJungleAsLaner": 0, "goldPerMinute": 475.3049686258747, "hadOpenNexus": 0, "immobilizeAndKillWithAlly": 2, "initialBuffCount": 0, "initialCrabCount": 0, "jungleCsBefore10Minutes": 0, "junglerTakedownsNearDamagedEpicMonster": 0, "kTurretsDestroyedBeforePlatesFall": 0, "kda": 4, "killAfterHiddenWithAlly": 1, "killParticipation": 0.11428571428571428, "killedChampTookFullTeamDamageSurvived": 0, "killingSprees": 0, "killsNearEnemyTurret": 2, "killsOnOtherLanesEarlyJungleAsLaner": 0, "killsOnRecentlyHealedByAramPack": 0, "killsUnderOwnTurret": 0, "killsWithHelpFromEpicMonster": 0, "knockEnemyIntoTeamAndKill": 0, "landSkillShotsEarlyGame": 3, "laneMinionsFirst10Minutes": 4, "legendaryCount": 0, "legendaryItemUsed": [], "lostAnInhibitor": 0, "maxKillDeficit": 0, "mejaisFullStackInTime": 0, "moreEnemyJungleThanOpponent": 0, "multiKillOneSpell": 0, "multiTurretRiftHeraldCount": 0, "multikills": 0, "multikillsAfterAggressiveFlash": 0, "outerTurretExecutesBefore10Minutes": 0, "outnumberedKills": 1, "outnumberedNexusKill": 0, "perfectDragonSoulsTaken": 0, "perfectGame": 0, "pickKillWithAlly": 4, "poroExplosions": 0, "quickCleanse": 0, "quickFirstTurret": 0, "quickSoloKills": 0, "riftHeraldTakedowns": 0, "saveAllyFromDeath": 0, "scuttleCrabKills": 0, "skillshotsDodged": 4, "skillshotsHit": 3, "snowballsHit": 1, "soloBaronKills": 0, "soloKills": 0, "stealthWardsPlaced": 0, "survivedSingleDigitHpCount": 0, "survivedThreeImmobilizesInFight": 0, "takedownOnFirstTurret": 0, "takedowns": 4, "takedownsAfterGainingLevelAdvantage": 0, "takedownsBeforeJungleMinionSpawn": 2, "takedownsFirstXMinutes": 4, "takedownsInAlcove": 0, "takedownsInEnemyFountain": 0, "teamBaronKills": 0, "teamDamagePercentage": 0.012118506993724276, "teamElderDragonKills": 0, "teamRiftHeraldKills": 0, "tookLargeDamageSurvived": 0, "turretPlatesTaken": 0, "turretTakedowns": 0, "turretsTakenWithRiftHerald": 0, "twentyMinionsIn3SecondsCount": 0, "twoWardsOneSweeperCount": 0, "unseenRecalls": 0, "visionScorePerMinute": 0, "voidMonsterKill": 0, "wardTakedowns": 0, "wardTakedownsBefore20M": 0, "wardsGuarded": 0}, "champExperience": 5728, "champLevel": 9, "championId": 154, "championName": "Zac", "championTransform": 0, "commandPings": 0, "consumablesPurchased": 2, "damageDealtToBuildings": 0, "damageDealtToObjectives": 0, "damageDealtToTurrets": 0, "damageSelfMitigated": 1044, "dangerPings": 0, "deaths": 1, "detectorWardsPlaced": 0, "doubleKills": 0, "dragonKills": 0, "eligibleForProgression": false, "enemyMissingPings": 2, "enemyVisionPings": 0, "firstBloodAssist": true, "firstBloodKill": false, "firstTowerAssist": false, "firstTowerKill": false, "gameEndedInEarlySurrender": false, "gameEndedInSurrender": false, "getBackPings": 0, "goldEarned": 7135, "goldSpent": 2700, "holdPings": 0, "individualPosition": "Invalid", "inhibitorKills": 0, "inhibitorTakedowns": 0, "inhibitorsLost": 1, "item0": 1011, "item1": 3801, "item2": 1011, "item3": 0, "item4": 0, "item5": 0, "item6": 2052, "itemsPurchased": 6, "killingSprees": 1, "kills": 2, "lane": "NONE", "largestCriticalStrike": 0, "largestKillingSpree": 2, "largestMultiKill": 1, "longestTimeSpentLiving": 163, "magicDamageDealt": 986, "magicDamageDealtToChampions": 699, "magicDamageTaken": 555, "missions": {"playerScore0": 0, "playerScore1": 0, "playerScore2": 0, "playerScore3": 0, "playerScore4": 0, "playerScore5": 0, "playerScore6": 0, "playerScore7": 0, "playerScore8": 0, "playerScore9": 0, "playerScore10": 0, "playerScore11": 0}, "needVisionPings": 0, "neutralMinionsKilled": 0, "nexusKills": 0, "nexusLost": 1, "nexusTakedowns": 0, "objectivesStolen": 0, "objectivesStolenAssists": 0, "onMyWayPings": 0, "participantId": 2, "pentaKills": 0, "perks": {"statPerks": {"defense": 5001, "flex": 5001, "offense": 5007}, "styles": [{"description": "primaryStyle", "selections": [{"perk": 8437, "var1": 0, "var2": 0, "var3": 0}, {"perk": 8463, "var1": 72, "var2": 0, "var3": 0}, {"perk": 8429, "var1": 46, "var2": 10, "var3": 9}, {"perk": 8451, "var1": 15, "var2": 0, "var3": 0}], "style": 8400}, {"description": "subStyle", "selections": [{"perk": 9105, "var1": 0, "var2": 0, "var3": 0}, {"perk": 9111, "var1": 192, "var2": 40, "var3": 0}], "style": 8000}]}, "physicalDamageDealt": 758, "physicalDamageDealtToChampions": 100, "physicalDamageTaken": 1395, "placement": 0, "playerAugment1": 0, "playerAugment2": 0, "playerAugment3": 0, "playerAugment4": 0, "playerAugment5": 0, "playerAugment6": 0, "playerSubteamId": 0, "profileIcon": 5649, "pushPings": 0, "puuid": "6UWsWalDzFO_iBlraHaY75eyfC3KTM8fXJ0rjGVLzmx-L_sOHO6IDZIGFhp1lixHS8n4uOShaG-UCA", "quadraKills": 0, "retreatPings": 0, "riotIdGameName": "TedChang", "riotIdTagline": "4444", "role": "SUPPORT", "sightWardsBoughtInGame": 0, "spell1Casts": 4, "spell2Casts": 2, "spell3Casts": 5, "spell4Casts": 0, "subteamPlacement": 0, "summoner1Casts": 1, "summoner1Id": 32, "summoner2Casts": 1, "summoner2Id": 4, "summonerId": "T_OEVW3f6vANjruR1LWOsudIApmQL7NHGY0wNJJYhPMisubD3ZQ7h5m7tw", "summonerLevel": 84, "summonerName": "", "teamEarlySurrendered": false, "teamId": 100, "teamPosition": "", "timeCCingOthers": 3, "timePlayed": 900, "totalAllyJungleMinionsKilled": 0, "totalDamageDealt": 1780, "totalDamageDealtToChampions": 799, "totalDamageShieldedOnTeammates": 0, "totalDamageTaken": 2523, "totalEnemyJungleMinionsKilled": 0, "totalHeal": 1461, "totalHealsOnTeammates": 11, "totalMinionsKilled": 4, "totalTimeCCDealt": 12, "totalTimeSpentDead": 15, "totalUnitsHealed": 2, "tripleKills": 0, "trueDamageDealt": 35, "trueDamageDealtToChampions": 0, "trueDamageTaken": 573, "turretKills": 0, "turretTakedowns": 0, "turretsLost": 4, "unrealKills": 0, "visionClearedPings": 0, "visionScore": 0, "visionWardsBoughtInGame": 0, "wardsKilled": 0, "wardsPlaced": 0, "win": false}, {"PlayerScore0": 0, "PlayerScore1": 0, "PlayerScore10": 0, "PlayerScore11": 0, "PlayerScore2": 0, "PlayerScore3": 0, "PlayerScore4": 0, "PlayerScore5": 0, "PlayerScore6": 0, "PlayerScore7": 0, "PlayerScore8": 0, "PlayerScore9": 0, "allInPings": 0, "assistMePings": 0, "assists": 17, "baronKills": 0, "basicPings": 0, "challenges": {"12AssistStreakCount": 0, "HealFromMapSources": 2162.0817375183105, "InfernalScalePickup": 0, "SWARM_DefeatAatrox": 0, "SWARM_DefeatBriar": 0, "SWARM_DefeatMiniBosses": 0, "SWARM_EvolveWeapon": 0, "SWARM_Have3Passives": 0, "SWARM_KillEnemy": 0, "SWARM_PickupGold": 0, "SWARM_ReachLevel50": 0, "SWARM_Survive15Min": 0, "SWARM_WinWith5EvolvedWeapons": 0, "abilityUses": 127, "acesBefore15Minutes": 0, "alliedJungleMonsterKills": 0, "baronTakedowns": 0, "blastConeOppositeOpponentCount": 0, "bountyGold": 0, "buffsStolen": 0, "completeSupportQuestInTime": 0, "controlWardsPlaced": 0, "damagePerMinute": 1041.3892480013585, "damageTakenOnTeamPercentage": 0.5304101800745529, "dancedWithRiftHerald": 0, "deathsByEnemyChamps": 13, "dodgeSkillShotsSmallWindow": 0, "doubleAces": 0, "dragonTakedowns": 0, "effectiveHealAndShielding": 211.11773681640625, "elderDragonKillsWithOpposingSoul": 0, "elderDragonMultikills": 0, "enemyChampionImmobilizations": 105, "enemyJungleMonsterKills": 0, "epicMonsterKillsNearEnemyJungler": 0, "epicMonsterKillsWithin30SecondsOfSpawn": 0, "epicMonsterSteals": 0, "epicMonsterStolenWithoutSmite": 0, "firstTurretKilled": 0, "fistBumpParticipation": 0, "flawlessAces": 0, "fullTeamTakedown": 1, "gameLength": 900.7492330140001, "getTakedownsInAllLanesEarlyJungleAsLaner": 0, "goldPerMinute": 662.3222620295892, "hadAfkTeammate": 1, "hadOpenNexus": 0, "highestCrowdControlScore": 1, "immobilizeAndKillWithAlly": 19, "initialBuffCount": 0, "initialCrabCount": 0, "jungleCsBefore10Minutes": 0, "junglerTakedownsNearDamagedEpicMonster": 0, "kTurretsDestroyedBeforePlatesFall": 0, "kda": 2, "killAfterHiddenWithAlly": 0, "killParticipation": 0.7428571428571429, "killedChampTookFullTeamDamageSurvived": 0, "killingSprees": 1, "killsNearEnemyTurret": 4, "killsOnOtherLanesEarlyJungleAsLaner": 0, "killsOnRecentlyHealedByAramPack": 0, "killsUnderOwnTurret": 0, "killsWithHelpFromEpicMonster": 0, "knockEnemyIntoTeamAndKill": 14, "landSkillShotsEarlyGame": 13, "laneMinionsFirst10Minutes": 5, "legendaryCount": 0, "legendaryItemUsed": [3084, 2502, 3119, 3121], "lostAnInhibitor": 0, "maxKillDeficit": 0, "mejaisFullStackInTime": 0, "moreEnemyJungleThanOpponent": 0, "multiKillOneSpell": 0, "multiTurretRiftHeraldCount": 0, "multikills": 2, "multikillsAfterAggressiveFlash": 1, "outerTurretExecutesBefore10Minutes": 0, "outnumberedKills": 7, "outnumberedNexusKill": 0, "perfectDragonSoulsTaken": 0, "perfectGame": 0, "pickKillWithAlly": 17, "poroExplosions": 0, "quickCleanse": 0, "quickFirstTurret": 0, "quickSoloKills": 0, "riftHeraldTakedowns": 0, "saveAllyFromDeath": 0, "scuttleCrabKills": 0, "skillshotsDodged": 16, "skillshotsHit": 28, "snowballsHit": 5, "soloBaronKills": 0, "soloKills": 1, "stealthWardsPlaced": 0, "survivedSingleDigitHpCount": 0, "survivedThreeImmobilizesInFight": 4, "takedownOnFirstTurret": 0, "takedowns": 26, "takedownsAfterGainingLevelAdvantage": 0, "takedownsBeforeJungleMinionSpawn": 1, "takedownsFirstXMinutes": 26, "takedownsInAlcove": 0, "takedownsInEnemyFountain": 0, "teamBaronKills": 0, "teamDamagePercentage": 0.2368614905408326, "teamElderDragonKills": 0, "teamRiftHeraldKills": 0, "tookLargeDamageSurvived": 0, "turretPlatesTaken": 0, "turretTakedowns": 0, "turretsTakenWithRiftHerald": 0, "twentyMinionsIn3SecondsCount": 0, "twoWardsOneSweeperCount": 0, "unseenRecalls": 0, "visionScorePerMinute": 0, "voidMonsterKill": 0, "wardTakedowns": 0, "wardTakedownsBefore20M": 0, "wardsGuarded": 0}, "champExperience": 12800, "champLevel": 14, "championId": 57, "championName": "Maokai", "championTransform": 0, "commandPings": 3, "consumablesPurchased": 0, "damageDealtToBuildings": 121, "damageDealtToObjectives": 121, "damageDealtToTurrets": 121, "damageSelfMitigated": 42749, "dangerPings": 0, "deaths": 13, "detectorWardsPlaced": 0, "doubleKills": 2, "dragonKills": 0, "eligibleForProgression": true, "enemyMissingPings": 0, "enemyVisionPings": 0, "firstBloodAssist": true, "firstBloodKill": false, "firstTowerAssist": false, "firstTowerKill": false, "gameEndedInEarlySurrender": false, "gameEndedInSurrender": false, "getBackPings": 0, "goldEarned": 9943, "goldSpent": 9700, "holdPings": 0, "individualPosition": "Invalid", "inhibitorKills": 0, "inhibitorTakedowns": 0, "inhibitorsLost": 1, "item0": 3084, "item1": 3121, "item2": 2502, "item3": 3047, "item4": 1029, "item5": 0, "item6": 2052, "itemsPurchased": 17, "killingSprees": 2, "kills": 9, "lane": "NONE", "largestCriticalStrike": 0, "largestKillingSpree": 4, "largestMultiKill": 2, "longestTimeSpentLiving": 122, "magicDamageDealt": 20282, "magicDamageDealtToChampions": 11713, "magicDamageTaken": 18697, "missions": {"playerScore0": 0, "playerScore1": 0, "playerScore2": 0, "playerScore3": 0, "playerScore4": 0, "playerScore5": 0, "playerScore6": 0, "playerScore7": 0, "playerScore8": 0, "playerScore9": 0, "playerScore10": 0, "playerScore11": 0}, "needVisionPings": 0, "neutralMinionsKilled": 0, "nexusKills": 0, "nexusLost": 1, "nexusTakedowns": 0, "objectivesStolen": 0, "objectivesStolenAssists": 0, "onMyWayPings": 0, "participantId": 3, "pentaKills": 0, "perks": {"statPerks": {"defense": 5001, "flex": 5001, "offense": 5007}, "styles": [{"description": "primaryStyle", "selections": [{"perk": 8437, "var1": 1127, "var2": 844, "var3": 0}, {"perk": 8463, "var1": 1087, "var2": 0, "var3": 0}, {"perk": 8429, "var1": 46, "var2": 13, "var3": 11}, {"perk": 8451, "var1": 266, "var2": 0, "var3": 0}], "style": 8400}, {"description": "subStyle", "selections": [{"perk": 9105, "var1": 7, "var2": 20, "var3": 0}, {"perk": 9111, "var1": 1865, "var2": 260, "var3": 0}], "style": 8000}]}, "physicalDamageDealt": 5919, "physicalDamageDealtToChampions": 3491, "physicalDamageTaken": 30438, "placement": 0, "playerAugment1": 0, "playerAugment2": 0, "playerAugment3": 0, "playerAugment4": 0, "playerAugment5": 0, "playerAugment6": 0, "playerSubteamId": 0, "profileIcon": 6894, "pushPings": 0, "puuid": "6Lx0jlEb7h64r-BpEc22J40z1Y-jnN4Dbq_ww8hfUxTQ2XHVH0w0Y-pxCj7Pazn5IFfF_BeD2g1zYA", "quadraKills": 0, "retreatPings": 0, "riotIdGameName": "Proveit", "riotIdTagline": "0427", "role": "SUPPORT", "sightWardsBoughtInGame": 0, "spell1Casts": 67, "spell2Casts": 30, "spell3Casts": 25, "spell4Casts": 5, "subteamPlacement": 0, "summoner1Casts": 12, "summoner1Id": 32, "summoner2Casts": 3, "summoner2Id": 4, "summonerId": "8y4HL_lfKaogGTWD7g_Fkhmzy2EoMPDF_wUvCFLHgoh6U1a7pd5bBY2kog", "summonerLevel": 55, "summonerName": "", "teamEarlySurrendered": false, "teamId": 100, "teamPosition": "", "timeCCingOthers": 73, "timePlayed": 900, "totalAllyJungleMinionsKilled": 0, "totalDamageDealt": 26630, "totalDamageDealtToChampions": 15633, "totalDamageShieldedOnTeammates": 0, "totalDamageTaken": 56524, "totalEnemyJungleMinionsKilled": 0, "totalHeal": 14458, "totalHealsOnTeammates": 211, "totalMinionsKilled": 12, "totalTimeCCDealt": 234, "totalTimeSpentDead": 292, "totalUnitsHealed": 4, "tripleKills": 0, "trueDamageDealt": 428, "trueDamageDealtToChampions": 428, "trueDamageTaken": 7389, "turretKills": 0, "turretTakedowns": 0, "turretsLost": 4, "unrealKills": 0, "visionClearedPings": 0, "visionScore": 0, "visionWardsBoughtInGame": 0, "wardsKilled": 0, "wardsPlaced": 0, "win": false}, {"PlayerScore0": 0, "PlayerScore1": 0, "PlayerScore10": 0, "PlayerScore11": 0, "PlayerScore2": 0, "PlayerScore3": 0, "PlayerScore4": 0, "PlayerScore5": 0, "PlayerScore6": 0, "PlayerScore7": 0, "PlayerScore8": 0, "PlayerScore9": 0, "allInPings": 0, "assistMePings": 0, "assists": 14, "baronKills": 0, "basicPings": 0, "challenges": {"12AssistStreakCount": 0, "HealFromMapSources": 309.6489248275757, "InfernalScalePickup": 0, "SWARM_DefeatAatrox": 0, "SWARM_DefeatBriar": 0, "SWARM_DefeatMiniBosses": 0, "SWARM_EvolveWeapon": 0, "SWARM_Have3Passives": 0, "SWARM_KillEnemy": 0, "SWARM_PickupGold": 0, "SWARM_ReachLevel50": 0, "SWARM_Survive15Min": 0, "SWARM_WinWith5EvolvedWeapons": 0, "abilityUses": 117, "acesBefore15Minutes": 0, "alliedJungleMonsterKills": 0, "baronTakedowns": 0, "blastConeOppositeOpponentCount": 0, "bountyGold": 822.2935485839844, "buffsStolen": 0, "completeSupportQuestInTime": 0, "controlWardsPlaced": 0, "damagePerMinute": 1094.304897242893, "damageTakenOnTeamPercentage": 0.19611457429930723, "dancedWithRiftHerald": 0, "deathsByEnemyChamps": 8, "dodgeSkillShotsSmallWindow": 0, "doubleAces": 0, "dragonTakedowns": 0, "effectiveHealAndShielding": 369.55267333984375, "elderDragonKillsWithOpposingSoul": 0, "elderDragonMultikills": 0, "enemyChampionImmobilizations": 9, "enemyJungleMonsterKills": 0, "epicMonsterKillsNearEnemyJungler": 0, "epicMonsterKillsWithin30SecondsOfSpawn": 0, "epicMonsterSteals": 0, "epicMonsterStolenWithoutSmite": 0, "firstTurretKilled": 0, "fistBumpParticipation": 0, "flawlessAces": 0, "fullTeamTakedown": 1, "gameLength": 900.7492330140001, "getTakedownsInAllLanesEarlyJungleAsLaner": 0, "goldPerMinute": 690.460491130758, "hadAfkTeammate": 1, "hadOpenNexus": 0, "immobilizeAndKillWithAlly": 4, "initialBuffCount": 0, "initialCrabCount": 0, "jungleCsBefore10Minutes": 0, "junglerTakedownsNearDamagedEpicMonster": 0, "kTurretsDestroyedBeforePlatesFall": 0, "kda": 2.625, "killAfterHiddenWithAlly": 3, "killParticipation": 0.6, "killedChampTookFullTeamDamageSurvived": 0, "killingSprees": 1, "killsNearEnemyTurret": 3, "killsOnOtherLanesEarlyJungleAsLaner": 0, "killsOnRecentlyHealedByAramPack": 0, "killsUnderOwnTurret": 2, "killsWithHelpFromEpicMonster": 0, "knockEnemyIntoTeamAndKill": 0, "landSkillShotsEarlyGame": 11, "laneMinionsFirst10Minutes": 19, "legendaryCount": 0, "legendaryItemUsed": [6653, 3116], "lostAnInhibitor": 0, "maxKillDeficit": 0, "mejaisFullStackInTime": 0, "moreEnemyJungleThanOpponent": 0, "multiKillOneSpell": 0, "multiTurretRiftHeraldCount": 0, "multikills": 2, "multikillsAfterAggressiveFlash": 0, "outerTurretExecutesBefore10Minutes": 0, "outnumberedKills": 5, "outnumberedNexusKill": 0, "perfectDragonSoulsTaken": 0, "perfectGame": 0, "pickKillWithAlly": 11, "poroExplosions": 0, "quickCleanse": 0, "quickFirstTurret": 0, "quickSoloKills": 0, "riftHeraldTakedowns": 0, "saveAllyFromDeath": 0, "scuttleCrabKills": 0, "skillshotsDodged": 16, "skillshotsHit": 19, "snowballsHit": 0, "soloBaronKills": 0, "soloKills": 0, "stealthWardsPlaced": 0, "survivedSingleDigitHpCount": 0, "survivedThreeImmobilizesInFight": 0, "takedownOnFirstTurret": 0, "takedowns": 21, "takedownsAfterGainingLevelAdvantage": 1, "takedownsBeforeJungleMinionSpawn": 1, "takedownsFirstXMinutes": 21, "takedownsInAlcove": 0, "takedownsInEnemyFountain": 0, "teamBaronKills": 0, "teamDamagePercentage": 0.24889702823851909, "teamElderDragonKills": 0, "teamRiftHeraldKills": 0, "tookLargeDamageSurvived": 0, "turretPlatesTaken": 0, "turretTakedowns": 0, "turretsTakenWithRiftHerald": 0, "twentyMinionsIn3SecondsCount": 0, "twoWardsOneSweeperCount": 0, "unseenRecalls": 0, "visionScorePerMinute": 0, "voidMonsterKill": 0, "wardTakedowns": 0, "wardTakedownsBefore20M": 0, "wardsGuarded": 0}, "champExperience": 14374, "champLevel": 15, "championId": 876, "championName": "Lillia", "championTransform": 0, "commandPings": 0, "consumablesPurchased": 0, "damageDealtToBuildings": 121, "damageDealtToObjectives": 121, "damageDealtToTurrets": 121, "damageSelfMitigated": 9911, "dangerPings": 0, "deaths": 8, "detectorWardsPlaced": 0, "doubleKills": 2, "dragonKills": 0, "eligibleForProgression": true, "enemyMissingPings": 0, "enemyVisionPings": 0, "firstBloodAssist": true, "firstBloodKill": false, "firstTowerAssist": false, "firstTowerKill": false, "gameEndedInEarlySurrender": false, "gameEndedInSurrender": false, "getBackPings": 0, "goldEarned": 10365, "goldSpent": 8850, "holdPings": 0, "individualPosition": "Invalid", "inhibitorKills": 0, "inhibitorTakedowns": 0, "inhibitorsLost": 1, "item0": 3802, "item1": 2031, "item2": 6653, "item3": 3020, "item4": 3116, "item5": 3067, "item6": 2052, "itemsPurchased": 11, "killingSprees": 1, "kills": 7, "lane": "NONE", "largestCriticalStrike": 0, "largestKillingSpree": 5, "largestMultiKill": 2, "longestTimeSpentLiving": 231, "magicDamageDealt": 34431, "magicDamageDealtToChampions": 13877, "magicDamageTaken": 9757, "missions": {"playerScore0": 0, "playerScore1": 0, "playerScore2": 0, "playerScore3": 0, "playerScore4": 0, "playerScore5": 0, "playerScore6": 0, "playerScore7": 0, "playerScore8": 0, "playerScore9": 0, "playerScore10": 0, "playerScore11": 0}, "needVisionPings": 0, "neutralMinionsKilled": 0, "nexusKills": 0, "nexusLost": 1, "nexusTakedowns": 0, "objectivesStolen": 0, "objectivesStolenAssists": 0, "onMyWayPings": 0, "participantId": 4, "pentaKills": 0, "perks": {"statPerks": {"defense": 5001, "flex": 5008, "offense": 5008}, "styles": [{"description": "primaryStyle", "selections": [{"perk": 8010, "var1": 107, "var2": 0, "var3": 0}, {"perk": 8009, "var1": 1705, "var2": 0, "var3": 0}, {"perk": 9105, "var1": 7, "var2": 30, "var3": 0}, {"perk": 8014, "var1": 487, "var2": 0, "var3": 0}], "style": 8000}, {"description": "subStyle", "selections": [{"perk": 8234, "var1": 5258, "var2": 0, "var3": 0}, {"perk": 8275, "var1": 8, "var2": 0, "var3": 0}], "style": 8200}]}, "physicalDamageDealt": 2302, "physicalDamageDealtToChampions": 552, "physicalDamageTaken": 9868, "placement": 0, "playerAugment1": 0, "playerAugment2": 0, "playerAugment3": 0, "playerAugment4": 0, "playerAugment5": 0, "playerAugment6": 0, "playerSubteamId": 0, "profileIcon": 4409, "pushPings": 0, "puuid": "HTLcVh5Um6pqIx8c4QBuhXUcXU9_jpyADAHMRPGhFUSesU6atj1L_GLzbVRcuk7rCU_7meKZDKYkow", "quadraKills": 0, "retreatPings": 0, "riotIdGameName": "roasasol", "riotIdTagline": "NA1", "role": "SUPPORT", "sightWardsBoughtInGame": 0, "spell1Casts": 44, "spell2Casts": 25, "spell3Casts": 44, "spell4Casts": 4, "subteamPlacement": 0, "summoner1Casts": 3, "summoner1Id": 4, "summoner2Casts": 5, "summoner2Id": 7, "summonerId": "h7E83-hYyNFmbXybkFWf5s3Opj_GNG-8Dmga7GB-v84_zsG6", "summonerLevel": 423, "summonerName": "", "teamEarlySurrendered": false, "teamId": 100, "teamPosition": "", "timeCCingOthers": 32, "timePlayed": 900, "totalAllyJungleMinionsKilled": 0, "totalDamageDealt": 43969, "totalDamageDealtToChampions": 16428, "totalDamageShieldedOnTeammates": 0, "totalDamageTaken": 20899, "totalEnemyJungleMinionsKilled": 0, "totalHeal": 4236, "totalHealsOnTeammates": 369, "totalMinionsKilled": 29, "totalTimeCCDealt": 259, "totalTimeSpentDead": 152, "totalUnitsHealed": 4, "tripleKills": 0, "trueDamageDealt": 7234, "trueDamageDealtToChampions": 1997, "trueDamageTaken": 1273, "turretKills": 0, "turretTakedowns": 0, "turretsLost": 4, "unrealKills": 0, "visionClearedPings": 0, "visionScore": 0, "visionWardsBoughtInGame": 0, "wardsKilled": 0, "wardsPlaced": 0, "win": false}, {"PlayerScore0": 0, "PlayerScore1": 0, "PlayerScore10": 0, "PlayerScore11": 0, "PlayerScore2": 0, "PlayerScore3": 0, "PlayerScore4": 0, "PlayerScore5": 0, "PlayerScore6": 0, "PlayerScore7": 0, "PlayerScore8": 0, "PlayerScore9": 0, "allInPings": 0, "assistMePings": 0, "assists": 12, "baronKills": 0, "basicPings": 0, "challenges": {"12AssistStreakCount": 0, "HealFromMapSources": 515.7167024612427, "InfernalScalePickup": 0, "SWARM_DefeatAatrox": 0, "SWARM_DefeatBriar": 0, "SWARM_DefeatMiniBosses": 0, "SWARM_EvolveWeapon": 0, "SWARM_Have3Passives": 0, "SWARM_KillEnemy": 0, "SWARM_PickupGold": 0, "SWARM_ReachLevel50": 0, "SWARM_Survive15Min": 0, "SWARM_WinWith5EvolvedWeapons": 0, "abilityUses": 97, "acesBefore15Minutes": 0, "alliedJungleMonsterKills": 0, "baronTakedowns": 0, "blastConeOppositeOpponentCount": 0, "bountyGold": 218.0802459716797, "buffsStolen": 0, "completeSupportQuestInTime": 0, "controlWardsPlaced": 0, "damagePerMinute": 1445.9911615237047, "damageTakenOnTeamPercentage": 0.12169817288694491, "dancedWithRiftHerald": 0, "deathsByEnemyChamps": 7, "dodgeSkillShotsSmallWindow": 0, "doubleAces": 0, "dragonTakedowns": 0, "effectiveHealAndShielding": 0, "elderDragonKillsWithOpposingSoul": 0, "elderDragonMultikills": 0, "enemyChampionImmobilizations": 11, "enemyJungleMonsterKills": 0, "epicMonsterKillsNearEnemyJungler": 0, "epicMonsterKillsWithin30SecondsOfSpawn": 0, "epicMonsterSteals": 0, "epicMonsterStolenWithoutSmite": 0, "firstTurretKilled": 0, "fistBumpParticipation": 0, "flawlessAces": 0, "fullTeamTakedown": 1, "gameLength": 900.7492330140001, "getTakedownsInAllLanesEarlyJungleAsLaner": 0, "goldPerMinute": 763.4278721631862, "hadAfkTeammate": 1, "hadOpenNexus": 0, "immobilizeAndKillWithAlly": 2, "initialBuffCount": 0, "initialCrabCount": 0, "jungleCsBefore10Minutes": 0, "junglerTakedownsNearDamagedEpicMonster": 0, "kTurretsDestroyedBeforePlatesFall": 0, "kda": 3.4285714285714284, "killAfterHiddenWithAlly": 2, "killParticipation": 0.6857142857142857, "killedChampTookFullTeamDamageSurvived": 0, "killingSprees": 1, "killsNearEnemyTurret": 2, "killsOnOtherLanesEarlyJungleAsLaner": 0, "killsOnRecentlyHealedByAramPack": 0, "killsUnderOwnTurret": 7, "killsWithHelpFromEpicMonster": 0, "knockEnemyIntoTeamAndKill": 0, "landSkillShotsEarlyGame": 17, "laneMinionsFirst10Minutes": 44, "legendaryCount": 0, "legendaryItemUsed": [3031, 6676, 3036], "lostAnInhibitor": 0, "maxKillDeficit": 0, "mejaisFullStackInTime": 0, "moreEnemyJungleThanOpponent": 0, "multiKillOneSpell": 0, "multiTurretRiftHeraldCount": 0, "multikills": 2, "multikillsAfterAggressiveFlash": 0, "outerTurretExecutesBefore10Minutes": 0, "outnumberedKills": 0, "outnumberedNexusKill": 0, "perfectDragonSoulsTaken": 0, "perfectGame": 0, "pickKillWithAlly": 18, "poroExplosions": 0, "quickCleanse": 0, "quickFirstTurret": 0, "quickSoloKills": 0, "riftHeraldTakedowns": 0, "saveAllyFromDeath": 0, "scuttleCrabKills": 0, "skillshotsDodged": 12, "skillshotsHit": 35, "snowballsHit": 0, "soloBaronKills": 0, "soloKills": 0, "stealthWardsPlaced": 0, "survivedSingleDigitHpCount": 0, "survivedThreeImmobilizesInFight": 0, "takedownOnFirstTurret": 0, "takedowns": 24, "takedownsAfterGainingLevelAdvantage": 0, "takedownsBeforeJungleMinionSpawn": 2, "takedownsFirstXMinutes": 24, "takedownsInAlcove": 0, "takedownsInEnemyFountain": 0, "teamBaronKills": 0, "teamDamagePercentage": 0.32888722683156385, "teamElderDragonKills": 0, "teamRiftHeraldKills": 0, "tookLargeDamageSurvived": 0, "turretPlatesTaken": 0, "turretTakedowns": 0, "turretsTakenWithRiftHerald": 0, "twentyMinionsIn3SecondsCount": 0, "twoWardsOneSweeperCount": 0, "unseenRecalls": 0, "visionScorePerMinute": 0, "voidMonsterKill": 0, "wardTakedowns": 0, "wardTakedownsBefore20M": 0, "wardsGuarded": 0}, "champExperience": 14732, "champLevel": 16, "championId": 51, "championName": "Caitlyn", "championTransform": 0, "commandPings": 0, "consumablesPurchased": 2, "damageDealtToBuildings": 550, "damageDealtToObjectives": 550, "damageDealtToTurrets": 550, "damageSelfMitigated": 5224, "dangerPings": 0, "deaths": 7, "detectorWardsPlaced": 0, "doubleKills": 2, "dragonKills": 0, "eligibleForProgression": true, "enemyMissingPings": 0, "enemyVisionPings": 0, "firstBloodAssist": false, "firstBloodKill": true, "firstTowerAssist": false, "firstTowerKill": false, "gameEndedInEarlySurrender": false, "gameEndedInSurrender": false, "getBackPings": 0, "goldEarned": 11460, "goldSpent": 11250, "holdPings": 0, "individualPosition": "Invalid", "inhibitorKills": 0, "inhibitorTakedowns": 0, "inhibitorsLost": 1, "item0": 3031, "item1": 6676, "item2": 3006, "item3": 3036, "item4": 1042, "item5": 1042, "item6": 2052, "itemsPurchased": 16, "killingSprees": 4, "kills": 12, "lane": "NONE", "largestCriticalStrike": 825, "largestKillingSpree": 5, "largestMultiKill": 2, "longestTimeSpentLiving": 149, "magicDamageDealt": 2006, "magicDamageDealtToChampions": 1456, "magicDamageTaken": 7060, "missions": {"playerScore0": 0, "playerScore1": 0, "playerScore2": 0, "playerScore3": 0, "playerScore4": 0, "playerScore5": 0, "playerScore6": 0, "playerScore7": 0, "playerScore8": 0, "playerScore9": 0, "playerScore10": 0, "playerScore11": 0}, "needVisionPings": 0, "neutralMinionsKilled": 0, "nexusKills": 0, "nexusLost": 1, "nexusTakedowns": 0, "objectivesStolen": 0, "objectivesStolenAssists": 0, "onMyWayPings": 0, "participantId": 5, "pentaKills": 0, "perks": {"statPerks": {"defense": 5001, "flex": 5008, "offense": 5005}, "styles": [{"description": "primaryStyle", "selections": [{"perk": 8128, "var1": 1282, "var2": 21, "var3": 0}, {"perk": 8126, "var1": 581, "var2": 0, "var3": 0}, {"perk": 8140, "var1": 18, "var2": 0, "var3": 0}, {"perk": 8106, "var1": 5, "var2": 31, "var3": 0}], "style": 8100}, {"description": "subStyle", "selections": [{"perk": 8014, "var1": 797, "var2": 0, "var3": 0}, {"perk": 8009, "var1": 1867, "var2": 0, "var3": 0}], "style": 8000}]}, "physicalDamageDealt": 64228, "physicalDamageDealtToChampions": 19605, "physicalDamageTaken": 5091, "placement": 0, "playerAugment1": 0, "playerAugment2": 0, "playerAugment3": 0, "playerAugment4": 0, "playerAugment5": 0, "playerAugment6": 0, "playerSubteamId": 0, "profileIcon": 5240, "pushPings": 0, "puuid": "bz6DHDAyj1fPX4w60CMxpr9hQLgYlXssNFONGaCjjGyVX5zqBVroZuYW3f---cQm2xvuYEN1Y_pidQ", "quadraKills": 0, "retreatPings": 0, "riotIdGameName": "swordfighter376", "riotIdTagline": "NA1", "role": "DUO", "sightWardsBoughtInGame": 0, "spell1Casts": 44, "spell2Casts": 25, "spell3Casts": 21, "spell4Casts": 7, "subteamPlacement": 0, "summoner1Casts": 3, "summoner1Id": 4, "summoner2Casts": 0, "summoner2Id": 6, "summonerId": "Mp6smaFmQ6AmwWBUQK2A_C4nT2EkGiNMYJOtdDIb8BMvYO0", "summonerLevel": 364, "summonerName": "", "teamEarlySurrendered": false, "teamId": 100, "teamPosition": "", "timeCCingOthers": 19, "timePlayed": 900, "totalAllyJungleMinionsKilled": 0, "totalDamageDealt": 66880, "totalDamageDealtToChampions": 21707, "totalDamageShieldedOnTeammates": 0, "totalDamageTaken": 12969, "totalEnemyJungleMinionsKilled": 0, "totalHeal": 514, "totalHealsOnTeammates": 0, "totalMinionsKilled": 76, "totalTimeCCDealt": 71, "totalTimeSpentDead": 161, "totalUnitsHealed": 1, "tripleKills": 0, "trueDamageDealt": 646, "trueDamageDealtToChampions": 646, "trueDamageTaken": 817, "turretKills": 0, "turretTakedowns": 0, "turretsLost": 4, "unrealKills": 0, "visionClearedPings": 0, "visionScore": 0, "visionWardsBoughtInGame": 0, "wardsKilled": 0, "wardsPlaced": 0, "win": false}, {"PlayerScore0": 0, "PlayerScore1": 0, "PlayerScore10": 0, "PlayerScore11": 0, "PlayerScore2": 0, "PlayerScore3": 0, "PlayerScore4": 0, "PlayerScore5": 0, "PlayerScore6": 0, "PlayerScore7": 0, "PlayerScore8": 0, "PlayerScore9": 0, "allInPings": 0, "assistMePings": 0, "assists": 27, "baronKills": 0, "basicPings": 0, "challenges": {"12AssistStreakCount": 0, "HealFromMapSources": 1271.9952788352966, "InfernalScalePickup": 0, "SWARM_DefeatAatrox": 0, "SWARM_DefeatBriar": 0, "SWARM_DefeatMiniBosses": 0, "SWARM_EvolveWeapon": 0, "SWARM_Have3Passives": 0, "SWARM_KillEnemy": 0, "SWARM_PickupGold": 0, "SWARM_ReachLevel50": 0, "SWARM_Survive15Min": 0, "SWARM_WinWith5EvolvedWeapons": 0, "abilityUses": 196, "acesBefore15Minutes": 0, "alliedJungleMonsterKills": 0, "baronTakedowns": 0, "blastConeOppositeOpponentCount": 0, "bountyGold": 0, "buffsStolen": 0, "completeSupportQuestInTime": 0, "controlWardsPlaced": 0, "damagePerMinute": 1998.5626665912687, "damageTakenOnTeamPercentage": 0.1570444290620521, "dancedWithRiftHerald": 0, "deathsByEnemyChamps": 5, "dodgeSkillShotsSmallWindow": 2, "doubleAces": 0, "dragonTakedowns": 0, "effectiveHealAndShielding": 1903.03857421875, "elderDragonKillsWithOpposingSoul": 0, "elderDragonMultikills": 0, "enemyChampionImmobilizations": 28, "enemyJungleMonsterKills": 0, "epicMonsterKillsNearEnemyJungler": 0, "epicMonsterKillsWithin30SecondsOfSpawn": 0, "epicMonsterSteals": 0, "epicMonsterStolenWithoutSmite": 0, "firstTurretKilled": 1, "firstTurretKilledTime": 350.997325685, "fistBumpParticipation": 0, "flawlessAces": 0, "fullTeamTakedown": 7, "gameLength": 900.7492330140001, "getTakedownsInAllLanesEarlyJungleAsLaner": 0, "goldPerMinute": 722.4630162992162, "hadOpenNexus": 0, "highestChampionDamage": 1, "immobilizeAndKillWithAlly": 9, "initialBuffCount": 0, "initialCrabCount": 0, "jungleCsBefore10Minutes": 0, "junglerTakedownsNearDamagedEpicMonster": 0, "kTurretsDestroyedBeforePlatesFall": 2, "kda": 6.4, "killAfterHiddenWithAlly": 5, "killParticipation": 0.9411764705882353, "killedChampTookFullTeamDamageSurvived": 0, "killingSprees": 0, "killsNearEnemyTurret": 0, "killsOnOtherLanesEarlyJungleAsLaner": 0, "killsOnRecentlyHealedByAramPack": 0, "killsUnderOwnTurret": 2, "killsWithHelpFromEpicMonster": 0, "knockEnemyIntoTeamAndKill": 9, "landSkillShotsEarlyGame": 36, "laneMinionsFirst10Minutes": 37, "legendaryCount": 0, "legendaryItemUsed": [6655, 6653], "lostAnInhibitor": 0, "maxKillDeficit": 4, "mejaisFullStackInTime": 0, "moreEnemyJungleThanOpponent": 0, "multiKillOneSpell": 0, "multiTurretRiftHeraldCount": 0, "multikills": 0, "multikillsAfterAggressiveFlash": 0, "outerTurretExecutesBefore10Minutes": 0, "outnumberedKills": 1, "outnumberedNexusKill": 0, "perfectDragonSoulsTaken": 0, "perfectGame": 0, "pickKillWithAlly": 25, "poroExplosions": 0, "quickCleanse": 0, "quickFirstTurret": 1, "quickSoloKills": 0, "riftHeraldTakedowns": 0, "saveAllyFromDeath": 0, "scuttleCrabKills": 0, "skillshotsDodged": 45, "skillshotsHit": 85, "snowballsHit": 5, "soloBaronKills": 0, "soloKills": 0, "stealthWardsPlaced": 0, "survivedSingleDigitHpCount": 0, "survivedThreeImmobilizesInFight": 6, "takedownOnFirstTurret": 1, "takedowns": 32, "takedownsAfterGainingLevelAdvantage": 1, "takedownsBeforeJungleMinionSpawn": 2, "takedownsFirstXMinutes": 32, "takedownsInAlcove": 0, "takedownsInEnemyFountain": 0, "teamBaronKills": 0, "teamDamagePercentage": 0.3021798400900142, "teamElderDragonKills": 0, "teamRiftHeraldKills": 0, "tookLargeDamageSurvived": 0, "turretPlatesTaken": 0, "turretTakedowns": 4, "turretsTakenWithRiftHerald": 0, "twentyMinionsIn3SecondsCount": 0, "twoWardsOneSweeperCount": 0, "unseenRecalls": 0, "visionScorePerMinute": 0, "voidMonsterKill": 0, "wardTakedowns": 0, "wardTakedownsBefore20M": 0, "wardsGuarded": 0}, "champExperience": 14936, "champLevel": 16, "championId": 61, "championName": "Orianna", "championTransform": 0, "commandPings": 2, "consumablesPurchased": 0, "damageDealtToBuildings": 2382, "damageDealtToObjectives": 2382, "damageDealtToTurrets": 2382, "damageSelfMitigated": 7970, "dangerPings": 0, "deaths": 5, "detectorWardsPlaced": 0, "doubleKills": 0, "dragonKills": 0, "eligibleForProgression": true, "enemyMissingPings": 0, "enemyVisionPings": 0, "firstBloodAssist": false, "firstBloodKill": false, "firstTowerAssist": true, "firstTowerKill": false, "gameEndedInEarlySurrender": false, "gameEndedInSurrender": false, "getBackPings": 0, "goldEarned": 10845, "goldSpent": 9300, "holdPings": 0, "individualPosition": "Invalid", "inhibitorKills": 1, "inhibitorTakedowns": 1, "inhibitorsLost": 0, "item0": 6655, "item1": 2031, "item2": 3020, "item3": 6653, "item4": 1058, "item5": 3145, "item6": 2052, "itemsPurchased": 13, "killingSprees": 2, "kills": 5, "lane": "NONE", "largestCriticalStrike": 0, "largestKillingSpree": 2, "largestMultiKill": 1, "longestTimeSpentLiving": 168, "magicDamageDealt": 60886, "magicDamageDealtToChampions": 26660, "magicDamageTaken": 6265, "missions": {"playerScore0": 0, "playerScore1": 0, "playerScore2": 0, "playerScore3": 0, "playerScore4": 0, "playerScore5": 0, "playerScore6": 0, "playerScore7": 0, "playerScore8": 0, "playerScore9": 0, "playerScore10": 0, "playerScore11": 0}, "needVisionPings": 0, "neutralMinionsKilled": 0, "nexusKills": 0, "nexusLost": 0, "nexusTakedowns": 1, "objectivesStolen": 0, "objectivesStolenAssists": 0, "onMyWayPings": 0, "participantId": 6, "pentaKills": 0, "perks": {"statPerks": {"defense": 5001, "flex": 5008, "offense": 5008}, "styles": [{"description": "primaryStyle", "selections": [{"perk": 8128, "var1": 1457, "var2": 22, "var3": 0}, {"perk": 8126, "var1": 662, "var2": 0, "var3": 0}, {"perk": 8140, "var1": 18, "var2": 0, "var3": 0}, {"perk": 8106, "var1": 4, "var2": 26, "var3": 0}], "style": 8100}, {"description": "subStyle", "selections": [{"perk": 8014, "var1": 743, "var2": 0, "var3": 0}, {"perk": 8009, "var1": 3952, "var2": 0, "var3": 0}], "style": 8000}]}, "physicalDamageDealt": 4851, "physicalDamageDealtToChampions": 1934, "physicalDamageTaken": 4499, "placement": 0, "playerAugment1": 0, "playerAugment2": 0, "playerAugment3": 0, "playerAugment4": 0, "playerAugment5": 0, "playerAugment6": 0, "playerSubteamId": 0, "profileIcon": 6941, "pushPings": 0, "puuid": "SqzFuirWbgPsZgSxmRSbu4rrIHdYkxNlqR5Q3LlzAOifmXiZEhY1Zc5qRR19XGJSxLsenhc8Q2PipA", "quadraKills": 0, "retreatPings": 0, "riotIdGameName": "Chromeo", "riotIdTagline": "OOOO", "role": "DUO", "sightWardsBoughtInGame": 0, "spell1Casts": 89, "spell2Casts": 52, "spell3Casts": 46, "spell4Casts": 9, "subteamPlacement": 0, "summoner1Casts": 11, "summoner1Id": 32, "summoner2Casts": 3, "summoner2Id": 4, "summonerId": "we8ka9ZEz3x7TgEh7uaPbODgAZbfCoxu7Pvx2jwK4N4WX0U", "summonerLevel": 441, "summonerName": "", "teamEarlySurrendered": false, "teamId": 200, "teamPosition": "", "timeCCingOthers": 34, "timePlayed": 900, "totalAllyJungleMinionsKilled": 0, "totalDamageDealt": 67145, "totalDamageDealtToChampions": 30003, "totalDamageShieldedOnTeammates": 1903, "totalDamageTaken": 11648, "totalEnemyJungleMinionsKilled": 0, "totalHeal": 1263, "totalHealsOnTeammates": 0, "totalMinionsKilled": 51, "totalTimeCCDealt": 264, "totalTimeSpentDead": 118, "totalUnitsHealed": 1, "tripleKills": 0, "trueDamageDealt": 1407, "trueDamageDealtToChampions": 1407, "trueDamageTaken": 883, "turretKills": 1, "turretTakedowns": 4, "turretsLost": 0, "unrealKills": 0, "visionClearedPings": 0, "visionScore": 0, "visionWardsBoughtInGame": 0, "wardsKilled": 0, "wardsPlaced": 0, "win": true}, {"PlayerScore0": 0, "PlayerScore1": 0, "PlayerScore10": 0, "PlayerScore11": 0, "PlayerScore2": 0, "PlayerScore3": 0, "PlayerScore4": 0, "PlayerScore5": 0, "PlayerScore6": 0, "PlayerScore7": 0, "PlayerScore8": 0, "PlayerScore9": 0, "allInPings": 0, "assistMePings": 0, "assists": 25, "baronKills": 0, "basicPings": 0, "challenges": {"12AssistStreakCount": 2, "HealFromMapSources": 310.62279415130615, "InfernalScalePickup": 0, "SWARM_DefeatAatrox": 0, "SWARM_DefeatBriar": 0, "SWARM_DefeatMiniBosses": 0, "SWARM_EvolveWeapon": 0, "SWARM_Have3Passives": 0, "SWARM_KillEnemy": 0, "SWARM_PickupGold": 0, "SWARM_ReachLevel50": 0, "SWARM_Survive15Min": 0, "SWARM_WinWith5EvolvedWeapons": 0, "abilityUses": 59, "acesBefore15Minutes": 0, "alliedJungleMonsterKills": 0, "baronTakedowns": 0, "blastConeOppositeOpponentCount": 0, "bountyGold": 0, "buffsStolen": 0, "completeSupportQuestInTime": 0, "controlWardsPlaced": 0, "damagePerMinute": 733.89536106713, "damageTakenOnTeamPercentage": 0.2440532737504001, "dancedWithRiftHerald": 0, "deathsByEnemyChamps": 8, "dodgeSkillShotsSmallWindow": 4, "doubleAces": 0, "dragonTakedowns": 0, "effectiveHealAndShielding": 0, "elderDragonKillsWithOpposingSoul": 0, "elderDragonMultikills": 0, "enemyChampionImmobilizations": 6, "enemyJungleMonsterKills": 0, "epicMonsterKillsNearEnemyJungler": 0, "epicMonsterKillsWithin30SecondsOfSpawn": 0, "epicMonsterSteals": 0, "epicMonsterStolenWithoutSmite": 0, "firstTurretKilled": 1, "firstTurretKilledTime": 350.997325685, "fistBumpParticipation": 0, "flawlessAces": 0, "fullTeamTakedown": 7, "gameLength": 900.7492330140001, "getTakedownsInAllLanesEarlyJungleAsLaner": 0, "goldPerMinute": 593.8551059989479, "hadOpenNexus": 0, "immobilizeAndKillWithAlly": 2, "initialBuffCount": 0, "initialCrabCount": 0, "jungleCsBefore10Minutes": 0, "junglerTakedownsNearDamagedEpicMonster": 0, "kTurretsDestroyedBeforePlatesFall": 1, "kda": 3.125, "killAfterHiddenWithAlly": 0, "killParticipation": 0.7352941176470589, "killedChampTookFullTeamDamageSurvived": 0, "killingSprees": 0, "killsNearEnemyTurret": 0, "killsOnOtherLanesEarlyJungleAsLaner": 0, "killsOnRecentlyHealedByAramPack": 0, "killsUnderOwnTurret": 0, "killsWithHelpFromEpicMonster": 0, "knockEnemyIntoTeamAndKill": 0, "landSkillShotsEarlyGame": 0, "laneMinionsFirst10Minutes": 11, "legendaryCount": 0, "legendaryItemUsed": [6610, 6692], "lostAnInhibitor": 0, "maxKillDeficit": 4, "mejaisFullStackInTime": 0, "moreEnemyJungleThanOpponent": 0, "multiKillOneSpell": 0, "multiTurretRiftHeraldCount": 0, "multikills": 0, "multikillsAfterAggressiveFlash": 0, "outerTurretExecutesBefore10Minutes": 0, "outnumberedKills": 0, "outnumberedNexusKill": 0, "perfectDragonSoulsTaken": 0, "perfectGame": 0, "pickKillWithAlly": 19, "poroExplosions": 0, "quickCleanse": 0, "quickFirstTurret": 1, "quickSoloKills": 0, "riftHeraldTakedowns": 0, "saveAllyFromDeath": 0, "scuttleCrabKills": 0, "skillshotsDodged": 61, "skillshotsHit": 0, "snowballsHit": 3, "soloBaronKills": 0, "soloKills": 0, "stealthWardsPlaced": 0, "survivedSingleDigitHpCount": 0, "survivedThreeImmobilizesInFight": 4, "takedownOnFirstTurret": 0, "takedowns": 25, "takedownsAfterGainingLevelAdvantage": 0, "takedownsBeforeJungleMinionSpawn": 2, "takedownsFirstXMinutes": 25, "takedownsInAlcove": 0, "takedownsInEnemyFountain": 0, "teamBaronKills": 0, "teamDamagePercentage": 0.11096393751230971, "teamElderDragonKills": 0, "teamRiftHeraldKills": 0, "tookLargeDamageSurvived": 0, "turretPlatesTaken": 0, "turretTakedowns": 2, "turretsTakenWithRiftHerald": 0, "twentyMinionsIn3SecondsCount": 0, "twoWardsOneSweeperCount": 0, "unseenRecalls": 0, "visionScorePerMinute": 0, "voidMonsterKill": 0, "wardTakedowns": 0, "wardTakedownsBefore20M": 0, "wardsGuarded": 0}, "champExperience": 12523, "champLevel": 14, "championId": 59, "championName": "JarvanIV", "championTransform": 0, "commandPings": 0, "consumablesPurchased": 0, "damageDealtToBuildings": 392, "damageDealtToObjectives": 392, "damageDealtToTurrets": 392, "damageSelfMitigated": 14816, "dangerPings": 0, "deaths": 8, "detectorWardsPlaced": 0, "doubleKills": 0, "dragonKills": 0, "eligibleForProgression": true, "enemyMissingPings": 0, "enemyVisionPings": 0, "firstBloodAssist": false, "firstBloodKill": false, "firstTowerAssist": true, "firstTowerKill": false, "gameEndedInEarlySurrender": false, "gameEndedInSurrender": false, "getBackPings": 0, "goldEarned": 8915, "goldSpent": 7800, "holdPings": 0, "individualPosition": "Invalid", "inhibitorKills": 0, "inhibitorTakedowns": 0, "inhibitorsLost": 0, "item0": 6610, "item1": 6692, "item2": 2019, "item3": 1036, "item4": 1036, "item5": 0, "item6": 2052, "itemsPurchased": 13, "killingSprees": 0, "kills": 0, "lane": "NONE", "largestCriticalStrike": 233, "largestKillingSpree": 0, "largestMultiKill": 0, "longestTimeSpentLiving": 132, "magicDamageDealt": 1490, "magicDamageDealtToChampions": 740, "magicDamageTaken": 8425, "missions": {"playerScore0": 0, "playerScore1": 0, "playerScore2": 0, "playerScore3": 0, "playerScore4": 0, "playerScore5": 0, "playerScore6": 0, "playerScore7": 0, "playerScore8": 0, "playerScore9": 0, "playerScore10": 0, "playerScore11": 0}, "needVisionPings": 0, "neutralMinionsKilled": 0, "nexusKills": 0, "nexusLost": 0, "nexusTakedowns": 1, "objectivesStolen": 0, "objectivesStolenAssists": 0, "onMyWayPings": 0, "participantId": 7, "pentaKills": 0, "perks": {"statPerks": {"defense": 5001, "flex": 5008, "offense": 5008}, "styles": [{"description": "primaryStyle", "selections": [{"perk": 8112, "var1": 874, "var2": 0, "var3": 0}, {"perk": 8143, "var1": 435, "var2": 0, "var3": 0}, {"perk": 8140, "var1": 18, "var2": 0, "var3": 0}, {"perk": 8106, "var1": 4, "var2": 26, "var3": 0}], "style": 8100}, {"description": "subStyle", "selections": [{"perk": 8014, "var1": 220, "var2": 0, "var3": 0}, {"perk": 9111, "var1": 640, "var2": 250, "var3": 0}], "style": 8000}]}, "physicalDamageDealt": 18821, "physicalDamageDealtToChampions": 9761, "physicalDamageTaken": 8446, "placement": 0, "playerAugment1": 0, "playerAugment2": 0, "playerAugment3": 0, "playerAugment4": 0, "playerAugment5": 0, "playerAugment6": 0, "playerSubteamId": 0, "profileIcon": 6621, "pushPings": 0, "puuid": "ynP1c9S8D0rrvUmHPypxN3mMXUtf2UzVICmqRUxkwcvu5yrNeoecRLQ_qJzsW3bhdZDa-r3aG0z_CQ", "quadraKills": 0, "retreatPings": 0, "riotIdGameName": "Burdentomb", "riotIdTagline": "9565", "role": "SUPPORT", "sightWardsBoughtInGame": 0, "spell1Casts": 23, "spell2Casts": 12, "spell3Casts": 19, "spell4Casts": 5, "subteamPlacement": 0, "summoner1Casts": 2, "summoner1Id": 4, "summoner2Casts": 6, "summoner2Id": 32, "summonerId": "YrSJLfReDBGaCZGa2wk8WLwCWLn6IIXxe4_0pmInRzQ34AVhHrQiDaB0_g", "summonerLevel": 17, "summonerName": "", "teamEarlySurrendered": false, "teamId": 200, "teamPosition": "", "timeCCingOthers": 8, "timePlayed": 900, "totalAllyJungleMinionsKilled": 0, "totalDamageDealt": 20867, "totalDamageDealtToChampions": 11017, "totalDamageShieldedOnTeammates": 0, "totalDamageTaken": 18102, "totalEnemyJungleMinionsKilled": 0, "totalHeal": 1631, "totalHealsOnTeammates": 0, "totalMinionsKilled": 15, "totalTimeCCDealt": 49, "totalTimeSpentDead": 175, "totalUnitsHealed": 1, "tripleKills": 0, "trueDamageDealt": 555, "trueDamageDealtToChampions": 515, "trueDamageTaken": 1230, "turretKills": 0, "turretTakedowns": 2, "turretsLost": 0, "unrealKills": 0, "visionClearedPings": 0, "visionScore": 0, "visionWardsBoughtInGame": 0, "wardsKilled": 0, "wardsPlaced": 0, "win": true}, {"PlayerScore0": 0, "PlayerScore1": 0, "PlayerScore10": 0, "PlayerScore11": 0, "PlayerScore2": 0, "PlayerScore3": 0, "PlayerScore4": 0, "PlayerScore5": 0, "PlayerScore6": 0, "PlayerScore7": 0, "PlayerScore8": 0, "PlayerScore9": 0, "allInPings": 0, "assistMePings": 2, "assists": 17, "baronKills": 0, "basicPings": 0, "challenges": {"12AssistStreakCount": 0, "HealFromMapSources": 873.3707580566406, "InfernalScalePickup": 0, "SWARM_DefeatAatrox": 0, "SWARM_DefeatBriar": 0, "SWARM_DefeatMiniBosses": 0, "SWARM_EvolveWeapon": 0, "SWARM_Have3Passives": 0, "SWARM_KillEnemy": 0, "SWARM_PickupGold": 0, "SWARM_ReachLevel50": 0, "SWARM_Survive15Min": 0, "SWARM_WinWith5EvolvedWeapons": 0, "abilityUses": 155, "acesBefore15Minutes": 0, "alliedJungleMonsterKills": 0, "baronTakedowns": 0, "blastConeOppositeOpponentCount": 0, "bountyGold": 485.76116943359375, "buffsStolen": 0, "completeSupportQuestInTime": 0, "controlWardsPlaced": 0, "damagePerMinute": 1226.6970270435147, "damageTakenOnTeamPercentage": 0.16359040396939625, "dancedWithRiftHerald": 0, "deathsByEnemyChamps": 8, "dodgeSkillShotsSmallWindow": 3, "doubleAces": 0, "dragonTakedowns": 0, "effectiveHealAndShielding": 1303.427978515625, "elderDragonKillsWithOpposingSoul": 0, "elderDragonMultikills": 0, "enemyChampionImmobilizations": 36, "enemyJungleMonsterKills": 0, "epicMonsterKillsNearEnemyJungler": 0, "epicMonsterKillsWithin30SecondsOfSpawn": 0, "epicMonsterSteals": 0, "epicMonsterStolenWithoutSmite": 0, "firstTurretKilled": 1, "firstTurretKilledTime": 350.997325685, "fistBumpParticipation": 3, "flawlessAces": 0, "fullTeamTakedown": 7, "gameLength": 900.7492330140001, "getTakedownsInAllLanesEarlyJungleAsLaner": 0, "goldPerMinute": 719.036116524435, "hadOpenNexus": 0, "immobilizeAndKillWithAlly": 8, "initialBuffCount": 0, "initialCrabCount": 0, "jungleCsBefore10Minutes": 0, "junglerTakedownsNearDamagedEpicMonster": 0, "kTurretsDestroyedBeforePlatesFall": 1, "kda": 3.125, "killAfterHiddenWithAlly": 6, "killParticipation": 0.7352941176470589, "killedChampTookFullTeamDamageSurvived": 0, "killingSprees": 2, "killsNearEnemyTurret": 1, "killsOnOtherLanesEarlyJungleAsLaner": 0, "killsOnRecentlyHealedByAramPack": 0, "killsUnderOwnTurret": 3, "killsWithHelpFromEpicMonster": 0, "knockEnemyIntoTeamAndKill": 0, "landSkillShotsEarlyGame": 0, "laneMinionsFirst10Minutes": 14, "legendaryCount": 0, "legendaryItemUsed": [6655, 4646], "lostAnInhibitor": 0, "maxKillDeficit": 4, "mejaisFullStackInTime": 0, "moreEnemyJungleThanOpponent": 0, "multiKillOneSpell": 0, "multiTurretRiftHeraldCount": 0, "multikills": 3, "multikillsAfterAggressiveFlash": 0, "outerTurretExecutesBefore10Minutes": 0, "outnumberedKills": 2, "outnumberedNexusKill": 0, "perfectDragonSoulsTaken": 0, "perfectGame": 0, "pickKillWithAlly": 21, "poroExplosions": 0, "quickCleanse": 0, "quickFirstTurret": 0, "quickSoloKills": 0, "riftHeraldTakedowns": 0, "saveAllyFromDeath": 0, "scuttleCrabKills": 0, "skillshotsDodged": 53, "skillshotsHit": 1, "snowballsHit": 12, "soloBaronKills": 0, "soloKills": 0, "stealthWardsPlaced": 0, "survivedSingleDigitHpCount": 0, "survivedThreeImmobilizesInFight": 6, "takedownOnFirstTurret": 0, "takedowns": 25, "takedownsAfterGainingLevelAdvantage": 0, "takedownsBeforeJungleMinionSpawn": 2, "takedownsFirstXMinutes": 25, "takedownsInAlcove": 0, "takedownsInEnemyFountain": 0, "teamBaronKills": 0, "teamDamagePercentage": 0.18547485033488545, "teamElderDragonKills": 0, "teamRiftHeraldKills": 0, "tookLargeDamageSurvived": 0, "turretPlatesTaken": 0, "turretTakedowns": 3, "turretsTakenWithRiftHerald": 0, "twentyMinionsIn3SecondsCount": 0, "twoWardsOneSweeperCount": 0, "unseenRecalls": 0, "visionScorePerMinute": 0, "voidMonsterKill": 0, "wardTakedowns": 0, "wardTakedownsBefore20M": 0, "wardsGuarded": 0}, "champExperience": 13306, "champLevel": 15, "championId": 1, "championName": "Annie", "championTransform": 0, "commandPings": 0, "consumablesPurchased": 0, "damageDealtToBuildings": 1721, "damageDealtToObjectives": 1721, "damageDealtToTurrets": 1721, "damageSelfMitigated": 6317, "dangerPings": 0, "deaths": 8, "detectorWardsPlaced": 0, "doubleKills": 2, "dragonKills": 0, "eligibleForProgression": true, "enemyMissingPings": 0, "enemyVisionPings": 0, "firstBloodAssist": false, "firstBloodKill": false, "firstTowerAssist": false, "firstTowerKill": false, "gameEndedInEarlySurrender": false, "gameEndedInSurrender": false, "getBackPings": 0, "goldEarned": 10794, "goldSpent": 8950, "holdPings": 0, "individualPosition": "Invalid", "inhibitorKills": 0, "inhibitorTakedowns": 1, "inhibitorsLost": 0, "item0": 6655, "item1": 3020, "item2": 4646, "item3": 3145, "item4": 0, "item5": 1058, "item6": 2052, "itemsPurchased": 14, "killingSprees": 2, "kills": 8, "lane": "NONE", "largestCriticalStrike": 0, "largestKillingSpree": 3, "largestMultiKill": 3, "longestTimeSpentLiving": 136, "magicDamageDealt": 32520, "magicDamageDealtToChampions": 16163, "magicDamageTaken": 7756, "missions": {"playerScore0": 0, "playerScore1": 0, "playerScore2": 0, "playerScore3": 0, "playerScore4": 0, "playerScore5": 0, "playerScore6": 0, "playerScore7": 0, "playerScore8": 0, "playerScore9": 0, "playerScore10": 0, "playerScore11": 0}, "needVisionPings": 0, "neutralMinionsKilled": 0, "nexusKills": 0, "nexusLost": 0, "nexusTakedowns": 1, "objectivesStolen": 0, "objectivesStolenAssists": 0, "onMyWayPings": 0, "participantId": 8, "pentaKills": 0, "perks": {"statPerks": {"defense": 5001, "flex": 5008, "offense": 5008}, "styles": [{"description": "primaryStyle", "selections": [{"perk": 8128, "var1": 1111, "var2": 18, "var3": 0}, {"perk": 8126, "var1": 512, "var2": 0, "var3": 0}, {"perk": 8140, "var1": 18, "var2": 0, "var3": 0}, {"perk": 8106, "var1": 5, "var2": 31, "var3": 0}], "style": 8100}, {"description": "subStyle", "selections": [{"perk": 8014, "var1": 599, "var2": 0, "var3": 0}, {"perk": 8009, "var1": 2243, "var2": 0, "var3": 0}], "style": 8000}]}, "physicalDamageDealt": 2883, "physicalDamageDealtToChampions": 904, "physicalDamageTaken": 4085, "placement": 0, "playerAugment1": 0, "playerAugment2": 0, "playerAugment3": 0, "playerAugment4": 0, "playerAugment5": 0, "playerAugment6": 0, "playerSubteamId": 0, "profileIcon": 4533, "pushPings": 0, "puuid": "MQXYnF9l3o09tQMyvCjN0v_PrKbFcu7uihOCC6_QaGF1njmoXqG4FxvxSn4ezDTgVS2BnWNUmQspdw", "quadraKills": 0, "retreatPings": 0, "riotIdGameName": "XXXoodaXXX", "riotIdTagline": "NA1", "role": "SUPPORT", "sightWardsBoughtInGame": 0, "spell1Casts": 45, "spell2Casts": 36, "spell3Casts": 38, "spell4Casts": 36, "subteamPlacement": 0, "summoner1Casts": 23, "summoner1Id": 32, "summoner2Casts": 5, "summoner2Id": 4, "summonerId": "vsmeKrxhYUxePkundMJ6mfLC9sBh_755CT82_BBCGBUViV7o9Bauj4vbaA", "summonerLevel": 101, "summonerName": "", "teamEarlySurrendered": false, "teamId": 200, "teamPosition": "", "timeCCingOthers": 23, "timePlayed": 900, "totalAllyJungleMinionsKilled": 0, "totalDamageDealt": 41661, "totalDamageDealtToChampions": 18415, "totalDamageShieldedOnTeammates": 1303, "totalDamageTaken": 12134, "totalEnemyJungleMinionsKilled": 0, "totalHeal": 870, "totalHealsOnTeammates": 0, "totalMinionsKilled": 24, "totalTimeCCDealt": 89, "totalTimeSpentDead": 164, "totalUnitsHealed": 1, "tripleKills": 1, "trueDamageDealt": 6257, "trueDamageDealtToChampions": 1347, "trueDamageTaken": 291, "turretKills": 1, "turretTakedowns": 3, "turretsLost": 0, "unrealKills": 0, "visionClearedPings": 0, "visionScore": 0, "visionWardsBoughtInGame": 0, "wardsKilled": 0, "wardsPlaced": 0, "win": true}, {"PlayerScore0": 0, "PlayerScore1": 0, "PlayerScore10": 0, "PlayerScore11": 0, "PlayerScore2": 0, "PlayerScore3": 0, "PlayerScore4": 0, "PlayerScore5": 0, "PlayerScore6": 0, "PlayerScore7": 0, "PlayerScore8": 0, "PlayerScore9": 0, "allInPings": 0, "assistMePings": 2, "assists": 9, "baronKills": 0, "basicPings": 0, "challenges": {"12AssistStreakCount": 0, "HealFromMapSources": 898.0644788742065, "InfernalScalePickup": 0, "SWARM_DefeatAatrox": 0, "SWARM_DefeatBriar": 0, "SWARM_DefeatMiniBosses": 0, "SWARM_EvolveWeapon": 0, "SWARM_Have3Passives": 0, "SWARM_KillEnemy": 0, "SWARM_PickupGold": 0, "SWARM_ReachLevel50": 0, "SWARM_Survive15Min": 0, "SWARM_WinWith5EvolvedWeapons": 0, "abilityUses": 61, "acesBefore15Minutes": 0, "alliedJungleMonsterKills": 0, "baronTakedowns": 0, "blastConeOppositeOpponentCount": 0, "bountyGold": 378.74566650390625, "buffsStolen": 0, "completeSupportQuestInTime": 0, "controlWardsPlaced": 0, "damagePerMinute": 1172.2163395209784, "damageTakenOnTeamPercentage": 0.19551584729227947, "dancedWithRiftHerald": 0, "deathsByEnemyChamps": 6, "dodgeSkillShotsSmallWindow": 0, "doubleAces": 0, "dragonTakedowns": 0, "effectiveHealAndShielding": 0, "elderDragonKillsWithOpposingSoul": 0, "elderDragonMultikills": 0, "enemyChampionImmobilizations": 0, "enemyJungleMonsterKills": 0, "epicMonsterKillsNearEnemyJungler": 0, "epicMonsterKillsWithin30SecondsOfSpawn": 0, "epicMonsterSteals": 0, "epicMonsterStolenWithoutSmite": 0, "firstTurretKilled": 1, "firstTurretKilledTime": 350.997325685, "fistBumpParticipation": 4, "flawlessAces": 0, "fullTeamTakedown": 7, "gameLength": 900.7492330140001, "getTakedownsInAllLanesEarlyJungleAsLaner": 0, "goldPerMinute": 884.2232758111278, "hadOpenNexus": 0, "immobilizeAndKillWithAlly": 0, "initialBuffCount": 0, "initialCrabCount": 0, "jungleCsBefore10Minutes": 0, "junglerTakedownsNearDamagedEpicMonster": 0, "kTurretsDestroyedBeforePlatesFall": 2, "kda": 4.333333333333333, "killAfterHiddenWithAlly": 2, "killParticipation": 0.7647058823529411, "killedChampTookFullTeamDamageSurvived": 0, "killingSprees": 2, "killsNearEnemyTurret": 4, "killsOnOtherLanesEarlyJungleAsLaner": 0, "killsOnRecentlyHealedByAramPack": 0, "killsUnderOwnTurret": 4, "killsWithHelpFromEpicMonster": 0, "knockEnemyIntoTeamAndKill": 0, "landSkillShotsEarlyGame": 4, "laneMinionsFirst10Minutes": 9, "legendaryCount": 0, "legendaryItemUsed": [6676, 3085, 3031], "lostAnInhibitor": 0, "maxKillDeficit": 4, "mejaisFullStackInTime": 0, "moreEnemyJungleThanOpponent": 0, "multiKillOneSpell": 0, "multiTurretRiftHeraldCount": 0, "multikills": 5, "multikillsAfterAggressiveFlash": 0, "outerTurretExecutesBefore10Minutes": 0, "outnumberedKills": 1, "outnumberedNexusKill": 0, "perfectDragonSoulsTaken": 0, "perfectGame": 0, "pickKillWithAlly": 20, "poroExplosions": 0, "quickCleanse": 0, "quickFirstTurret": 1, "quickSoloKills": 0, "riftHeraldTakedowns": 0, "saveAllyFromDeath": 0, "scuttleCrabKills": 0, "skillshotsDodged": 16, "skillshotsHit": 6, "snowballsHit": 0, "soloBaronKills": 0, "soloKills": 0, "stealthWardsPlaced": 0, "survivedSingleDigitHpCount": 0, "survivedThreeImmobilizesInFight": 2, "takedownOnFirstTurret": 1, "takedowns": 26, "takedownsAfterGainingLevelAdvantage": 1, "takedownsBeforeJungleMinionSpawn": 2, "takedownsFirstXMinutes": 26, "takedownsInAlcove": 0, "takedownsInEnemyFountain": 0, "teamBaronKills": 0, "teamDamagePercentage": 0.1772374476660799, "teamElderDragonKills": 0, "teamRiftHeraldKills": 0, "tookLargeDamageSurvived": 0, "turretPlatesTaken": 0, "turretTakedowns": 3, "turretsTakenWithRiftHerald": 0, "twentyMinionsIn3SecondsCount": 0, "twoWardsOneSweeperCount": 0, "unseenRecalls": 0, "visionScorePerMinute": 0, "voidMonsterKill": 0, "wardTakedowns": 0, "wardTakedownsBefore20M": 0, "wardsGuarded": 0}, "champExperience": 13416, "champLevel": 15, "championId": 29, "championName": "Twitch", "championTransform": 0, "commandPings": 0, "consumablesPurchased": 2, "damageDealtToBuildings": 4520, "damageDealtToObjectives": 4520, "damageDealtToTurrets": 4520, "damageSelfMitigated": 7935, "dangerPings": 0, "deaths": 6, "detectorWardsPlaced": 0, "doubleKills": 4, "dragonKills": 0, "eligibleForProgression": true, "enemyMissingPings": 0, "enemyVisionPings": 0, "firstBloodAssist": false, "firstBloodKill": false, "firstTowerAssist": false, "firstTowerKill": true, "gameEndedInEarlySurrender": false, "gameEndedInSurrender": false, "getBackPings": 0, "goldEarned": 13274, "goldSpent": 11600, "holdPings": 0, "individualPosition": "Invalid", "inhibitorKills": 0, "inhibitorTakedowns": 0, "inhibitorsLost": 0, "item0": 3123, "item1": 3006, "item2": 3031, "item3": 1036, "item4": 3085, "item5": 6676, "item6": 2052, "itemsPurchased": 18, "killingSprees": 5, "kills": 17, "lane": "NONE", "largestCriticalStrike": 616, "largestKillingSpree": 6, "largestMultiKill": 3, "longestTimeSpentLiving": 188, "magicDamageDealt": 124, "magicDamageDealtToChampions": 124, "magicDamageTaken": 5949, "missions": {"playerScore0": 0, "playerScore1": 0, "playerScore2": 0, "playerScore3": 0, "playerScore4": 0, "playerScore5": 0, "playerScore6": 0, "playerScore7": 0, "playerScore8": 0, "playerScore9": 0, "playerScore10": 0, "playerScore11": 0}, "needVisionPings": 0, "neutralMinionsKilled": 0, "nexusKills": 0, "nexusLost": 0, "nexusTakedowns": 1, "objectivesStolen": 0, "objectivesStolenAssists": 0, "onMyWayPings": 0, "participantId": 9, "pentaKills": 0, "perks": {"statPerks": {"defense": 5001, "flex": 5008, "offense": 5005}, "styles": [{"description": "primaryStyle", "selections": [{"perk": 8008, "var1": 209, "var2": 209, "var3": 0}, {"perk": 9111, "var1": 909, "var2": 260, "var3": 0}, {"perk": 9104, "var1": 5, "var2": 20, "var3": 0}, {"perk": 8014, "var1": 762, "var2": 0, "var3": 0}], "style": 8000}, {"description": "subStyle", "selections": [{"perk": 8139, "var1": 738, "var2": 0, "var3": 0}, {"perk": 8135, "var1": 450, "var2": 5, "var3": 0}], "style": 8100}]}, "physicalDamageDealt": 32624, "physicalDamageDealtToChampions": 15713, "physicalDamageTaken": 8234, "placement": 0, "playerAugment1": 0, "playerAugment2": 0, "playerAugment3": 0, "playerAugment4": 0, "playerAugment5": 0, "playerAugment6": 0, "playerSubteamId": 0, "profileIcon": 18, "pushPings": 0, "puuid": "SBha5vhP-jFCgA-Gn_IQUogYRES3fPuD72gGOvRfwn33I1IjGByKnx0RXfFXB6zNMYMG5UcqWwhFbg", "quadraKills": 0, "retreatPings": 0, "riotIdGameName": "Grouchy Groot", "riotIdTagline": "NA1", "role": "SUPPORT", "sightWardsBoughtInGame": 0, "spell1Casts": 31, "spell2Casts": 11, "spell3Casts": 12, "spell4Casts": 7, "subteamPlacement": 0, "summoner1Casts": 4, "summoner1Id": 4, "summoner2Casts": 5, "summoner2Id": 6, "summonerId": "fBcTcpIWMDihU4YVrZ2_j9amLQQS-4WFKLmGZ3SGe1G8odNn_Mp1K6LUpg", "summonerLevel": 39, "summonerName": "", "teamEarlySurrendered": false, "teamId": 200, "teamPosition": "", "timeCCingOthers": 6, "timePlayed": 900, "totalAllyJungleMinionsKilled": 0, "totalDamageDealt": 35010, "totalDamageDealtToChampions": 17597, "totalDamageShieldedOnTeammates": 0, "totalDamageTaken": 14502, "totalEnemyJungleMinionsKilled": 0, "totalHeal": 2317, "totalHealsOnTeammates": 0, "totalMinionsKilled": 22, "totalTimeCCDealt": 89, "totalTimeSpentDead": 144, "totalUnitsHealed": 1, "tripleKills": 1, "trueDamageDealt": 2260, "trueDamageDealtToChampions": 1758, "trueDamageTaken": 317, "turretKills": 1, "turretTakedowns": 3, "turretsLost": 0, "unrealKills": 0, "visionClearedPings": 0, "visionScore": 0, "visionWardsBoughtInGame": 0, "wardsKilled": 0, "wardsPlaced": 0, "win": true}, {"PlayerScore0": 0, "PlayerScore1": 0, "PlayerScore10": 0, "PlayerScore11": 0, "PlayerScore2": 0, "PlayerScore3": 0, "PlayerScore4": 0, "PlayerScore5": 0, "PlayerScore6": 0, "PlayerScore7": 0, "PlayerScore8": 0, "PlayerScore9": 0, "allInPings": 0, "assistMePings": 0, "assists": 13, "baronKills": 0, "basicPings": 0, "challenges": {"12AssistStreakCount": 0, "HealFromMapSources": 1142.0955924987793, "InfernalScalePickup": 0, "SWARM_DefeatAatrox": 0, "SWARM_DefeatBriar": 0, "SWARM_DefeatMiniBosses": 0, "SWARM_EvolveWeapon": 0, "SWARM_Have3Passives": 0, "SWARM_KillEnemy": 0, "SWARM_PickupGold": 0, "SWARM_ReachLevel50": 0, "SWARM_Survive15Min": 0, "SWARM_WinWith5EvolvedWeapons": 0, "abilityUses": 69, "acesBefore15Minutes": 0, "alliedJungleMonsterKills": 0, "baronTakedowns": 0, "blastConeOppositeOpponentCount": 0, "bountyGold": 0, "buffsStolen": 0, "completeSupportQuestInTime": 0, "controlWardsPlaced": 0, "damagePerMinute": 1482.4472708340854, "damageTakenOnTeamPercentage": 0.2397960459258721, "dancedWithRiftHerald": 0, "deathsByEnemyChamps": 8, "dodgeSkillShotsSmallWindow": 2, "doubleAces": 0, "dragonTakedowns": 0, "effectiveHealAndShielding": 300, "elderDragonKillsWithOpposingSoul": 0, "elderDragonMultikills": 0, "enemyChampionImmobilizations": 25, "enemyJungleMonsterKills": 0, "epicMonsterKillsNearEnemyJungler": 0, "epicMonsterKillsWithin30SecondsOfSpawn": 0, "epicMonsterSteals": 0, "epicMonsterStolenWithoutSmite": 0, "firstTurretKilled": 1, "firstTurretKilledTime": 350.997325685, "fistBumpParticipation": 2, "flawlessAces": 0, "fullTeamTakedown": 7, "gameLength": 900.7492330140001, "getTakedownsInAllLanesEarlyJungleAsLaner": 0, "goldPerMinute": 645.7909068832467, "hadOpenNexus": 0, "immobilizeAndKillWithAlly": 6, "initialBuffCount": 0, "initialCrabCount": 0, "jungleCsBefore10Minutes": 0, "junglerTakedownsNearDamagedEpicMonster": 0, "kTurretsDestroyedBeforePlatesFall": 2, "kda": 2.125, "killAfterHiddenWithAlly": 3, "killParticipation": 0.5, "killedChampTookFullTeamDamageSurvived": 0, "killingSprees": 0, "killsNearEnemyTurret": 1, "killsOnOtherLanesEarlyJungleAsLaner": 0, "killsOnRecentlyHealedByAramPack": 0, "killsUnderOwnTurret": 2, "killsWithHelpFromEpicMonster": 0, "knockEnemyIntoTeamAndKill": 5, "landSkillShotsEarlyGame": 17, "laneMinionsFirst10Minutes": 18, "legendaryCount": 0, "legendaryItemUsed": [3153, 6672], "lostAnInhibitor": 0, "maxKillDeficit": 4, "mejaisFullStackInTime": 0, "moreEnemyJungleThanOpponent": 0, "multiKillOneSpell": 0, "multiTurretRiftHeraldCount": 0, "multikills": 0, "multikillsAfterAggressiveFlash": 0, "outerTurretExecutesBefore10Minutes": 0, "outnumberedKills": 0, "outnumberedNexusKill": 0, "perfectDragonSoulsTaken": 0, "perfectGame": 0, "pickKillWithAlly": 14, "poroExplosions": 0, "quickCleanse": 0, "quickFirstTurret": 1, "quickSoloKills": 0, "riftHeraldTakedowns": 0, "saveAllyFromDeath": 0, "scuttleCrabKills": 0, "skillshotsDodged": 49, "skillshotsHit": 38, "snowballsHit": 0, "soloBaronKills": 0, "soloKills": 0, "stealthWardsPlaced": 0, "survivedSingleDigitHpCount": 0, "survivedThreeImmobilizesInFight": 5, "takedownOnFirstTurret": 1, "takedowns": 17, "takedownsAfterGainingLevelAdvantage": 0, "takedownsBeforeJungleMinionSpawn": 0, "takedownsFirstXMinutes": 17, "takedownsInAlcove": 0, "takedownsInEnemyFountain": 0, "teamBaronKills": 0, "teamDamagePercentage": 0.22414392439671071, "teamElderDragonKills": 0, "teamRiftHeraldKills": 0, "tookLargeDamageSurvived": 0, "turretPlatesTaken": 0, "turretTakedowns": 4, "turretsTakenWithRiftHerald": 0, "twentyMinionsIn3SecondsCount": 0, "twoWardsOneSweeperCount": 0, "unseenRecalls": 0, "visionScorePerMinute": 0, "voidMonsterKill": 0, "wardTakedowns": 0, "wardTakedownsBefore20M": 0, "wardsGuarded": 0}, "champExperience": 12119, "champLevel": 14, "championId": 67, "championName": "Vayne", "championTransform": 0, "commandPings": 3, "consumablesPurchased": 0, "damageDealtToBuildings": 2592, "damageDealtToObjectives": 2592, "damageDealtToTurrets": 2592, "damageSelfMitigated": 10944, "dangerPings": 0, "deaths": 8, "detectorWardsPlaced": 0, "doubleKills": 0, "dragonKills": 0, "eligibleForProgression": true, "enemyMissingPings": 0, "enemyVisionPings": 0, "firstBloodAssist": false, "firstBloodKill": false, "firstTowerAssist": true, "firstTowerKill": false, "gameEndedInEarlySurrender": false, "gameEndedInSurrender": false, "getBackPings": 0, "goldEarned": 9694, "goldSpent": 8775, "holdPings": 0, "individualPosition": "Invalid", "inhibitorKills": 0, "inhibitorTakedowns": 1, "inhibitorsLost": 0, "item0": 3006, "item1": 3153, "item2": 6672, "item3": 1018, "item4": 1037, "item5": 0, "item6": 2052, "itemsPurchased": 14, "killingSprees": 0, "kills": 4, "lane": "NONE", "largestCriticalStrike": 356, "largestKillingSpree": 0, "largestMultiKill": 1, "longestTimeSpentLiving": 273, "magicDamageDealt": 179, "magicDamageDealtToChampions": 179, "magicDamageTaken": 9935, "missions": {"playerScore0": 0, "playerScore1": 0, "playerScore2": 0, "playerScore3": 0, "playerScore4": 0, "playerScore5": 0, "playerScore6": 0, "playerScore7": 0, "playerScore8": 0, "playerScore9": 0, "playerScore10": 0, "playerScore11": 0}, "needVisionPings": 0, "neutralMinionsKilled": 0, "nexusKills": 1, "nexusLost": 0, "nexusTakedowns": 1, "objectivesStolen": 0, "objectivesStolenAssists": 0, "onMyWayPings": 0, "participantId": 10, "pentaKills": 0, "perks": {"statPerks": {"defense": 5001, "flex": 5008, "offense": 5005}, "styles": [{"description": "primaryStyle", "selections": [{"perk": 8005, "var1": 1215, "var2": 1215, "var3": 0}, {"perk": 9111, "var1": 557, "var2": 170, "var3": 0}, {"perk": 9104, "var1": 7, "var2": 10, "var3": 0}, {"perk": 8014, "var1": 487, "var2": 0, "var3": 0}], "style": 8000}, {"description": "subStyle", "selections": [{"perk": 8429, "var1": 46, "var2": 10, "var3": 9}, {"perk": 8451, "var1": 186, "var2": 0, "var3": 0}], "style": 8400}]}, "physicalDamageDealt": 37767, "physicalDamageDealtToChampions": 16315, "physicalDamageTaken": 7332, "placement": 0, "playerAugment1": 0, "playerAugment2": 0, "playerAugment3": 0, "playerAugment4": 0, "playerAugment5": 0, "playerAugment6": 0, "playerSubteamId": 0, "profileIcon": 5840, "pushPings": 0, "puuid": "xyU4fhtryInp_cdKIJZ08pkgQDNXZcE7zJ3IY_oI66IAn7xFfwky0vRcqc-H2tV4q3CCQiqXzGwCCA", "quadraKills": 0, "retreatPings": 0, "riotIdGameName": "altair089", "riotIdTagline": "NA1", "role": "SUPPORT", "sightWardsBoughtInGame": 0, "spell1Casts": 47, "spell2Casts": 0, "spell3Casts": 17, "spell4Casts": 5, "subteamPlacement": 0, "summoner1Casts": 3, "summoner1Id": 4, "summoner2Casts": 5, "summoner2Id": 7, "summonerId": "5-KBPLKIcs3Dr9PSqlwCrybabM3DMabnWpgpLpWTFZUiUNo", "summonerLevel": 231, "summonerName": "", "teamEarlySurrendered": false, "teamId": 200, "teamPosition": "", "timeCCingOthers": 12, "timePlayed": 900, "totalAllyJungleMinionsKilled": 0, "totalDamageDealt": 44562, "totalDamageDealtToChampions": 22255, "totalDamageShieldedOnTeammates": 0, "totalDamageTaken": 17786, "totalEnemyJungleMinionsKilled": 0, "totalHeal": 4289, "totalHealsOnTeammates": 300, "totalMinionsKilled": 32, "totalTimeCCDealt": 23, "totalTimeSpentDead": 194, "totalUnitsHealed": 4, "tripleKills": 0, "trueDamageDealt": 6615, "trueDamageDealtToChampions": 5760, "trueDamageTaken": 518, "turretKills": 1, "turretTakedowns": 4, "turretsLost": 0, "unrealKills": 0, "visionClearedPings": 0, "visionScore": 0, "visionWardsBoughtInGame": 0, "wardsKilled": 0, "wardsPlaced": 0, "win": true}], "platformId": "NA1", "queueId": 450, "teams": [{"bans": [], "feats": {"EPIC_MONSTER_KILL": {"featState": 0}, "FIRST_BLOOD": {"featState": 0}, "FIRST_TURRET": {"featState": 0}}, "objectives": {"atakhan": {"first": false, "kills": 0}, "baron": {"first": false, "kills": 0}, "champion": {"first": true, "kills": 35}, "dragon": {"first": false, "kills": 0}, "horde": {"first": false, "kills": 0}, "inhibitor": {"first": false, "kills": 0}, "riftHerald": {"first": false, "kills": 0}, "tower": {"first": false, "kills": 0}}, "teamId": 100, "win": false}, {"bans": [], "feats": {"EPIC_MONSTER_KILL": {"featState": 0}, "FIRST_BLOOD": {"featState": 0}, "FIRST_TURRET": {"featState": 0}}, "objectives": {"atakhan": {"first": false, "kills": 0}, "baron": {"first": false, "kills": 0}, "champion": {"first": false, "kills": 34}, "dragon": {"first": false, "kills": 0}, "horde": {"first": false, "kills": 0}, "inhibitor": {"first": true, "kills": 1}, "riftHerald": {"first": false, "kills": 0}, "tower": {"first": true, "kills": 4}}, "teamId": 200, "win": true}], "tournamentCode": ""}}